Workbook

Sheet LISEZMOI
B1: Base de données CGPP RDC : riposte à la MVE-17 (virus Bundibugyo)
B2: Canevas de la base Excel normalisée : une feuille par table, une ligne par observation, des identifiants stables. Les scripts Python du dossier « scripts » lisent et écrivent ces feuilles.
B4: Légende
C5: En-tête bleu foncé : nom technique de la colonne (ne pas modifier). Survoler l'en-tête pour lire la description.
C6: Fond jaune : cellule à saisir (ligne d'exemple en italique, à supprimer avant usage).
C7: Fond gris : cellule calculée par formule (ne pas saisir).
C8: Fond bleu pâle : référentiel tenu par l'équipe SI (zones, indicateurs, semaines).
B10: Qui remplit quoi
B11: saisie_hebdo | C11: Points focaux des IP, chaque vendredi (dimanche au plus tard) : une ligne par indicateur, ZS et semaine ; numérateur ET dénominateur pour les pourcentages.
B12: sbc_activites / sbc_synthese_as | C12: Export de la fiche SBC journalière (ODK), une ligne par site visité et une ligne par aire de santé et par jour.
B13: reunions / points_action | C13: Représentant CGPP à chaque réunion : la réunion, puis chaque point d'action avec responsable, échéance et statut.
B14: sitrep_notes | C14: Équipe SI : faits marquants, défis et actions repris dans le SitRep CGPP.
B15: feuilles sitrep_*, epi_*, … | C15: Remplies automatiquement par le script s01 à partir des SitReps nationaux : ne pas saisir à la main.
B16: tableau_suivi | C16: Calculé par formules à partir de saisie_hebdo et ref_indicateurs.
B17: qc_suivi | C17: Alimentée par le contrôle qualité (s03) ; l'équipe complète responsable, statut et date de résolution.
B19: Règles de saisie
B20: 1. Une valeur par cellule ; pas de texte dans les colonnes numériques ; pas de cellules fusionnées.
B21: 2. Les codes (province, ZS, partenaire, indicateur) viennent des listes déroulantes.
B22: 3. Un pourcentage se saisit toujours en numérateur et dénominateur, jamais en pourcentage tout fait.
B23: 4. Une semaine se renseigne même si la valeur est zéro : une cellule vide signifie « non rapporté ».
B25: Commandes
B26: python pipeline.py (extraction, contrôle qualité, analyses et SitRep CGPP)
B27: python pipeline.py --etapes qc,sitrep (relancer seulement le contrôle et le SitRep)
B29: Canevas généré le 12/10/2026 ; modèle de données : 22 tables.

Sheet tableau_suivi
A1: Suivi des indicateurs : calculé à partir de la feuille saisie_hebdo
A2: Les pourcentages sont recalculés à partir de la somme des numérateurs et de la somme des dénominateurs (jamais en additionnant des pourcentages). Ne rien saisir dans cette feuille.
A4: id_indicateur | B4: pilier | C4: indicateur | D4: type | E4: cible DOS | F4: cible DOS (nombre) | G4: numérateur cumulé | H4: dénominateur cumulé | I4: réalisé | J4: % de la cible | K4: dernière semaine saisie | L4: lignes saisies | M4: statut
A5: =IFERROR(INDEX(ref_indicateurs!$A:$A,2)&"","") | B5: =IF($A5="","",INDEX(ref_indicateurs!$B:$B,MATCH($A5,ref_indicateurs!$A:$A,0))&"") | C5: =IF($A5="","",INDEX(ref_indicateurs!$C:$C,MATCH($A5,ref_indicateurs!$A:$A,0))&"") | D5: =IF($A5="","",INDEX(ref_indicateurs!$E:$E,MATCH($A5,ref_indicateurs!$A:$A,0))&"") | E5: =IF($A5="","",INDEX(ref_indicateurs!$M:$M,MATCH($A5,ref_indicateurs!$A:$A,0))&"") | F5: =IF($A5="","",IF(INDEX(ref_indicateurs!$O:$O,MATCH($A5,ref_indicateurs!$A:$A,0))="","",INDEX(ref_indicateurs!$O:$O,MATCH($A5,ref_indicateurs!$A:$A,0)))) | G5: =IF($A5="","",SUMIFS(saisie_hebdo!$L:$L,saisie_hebdo!$I:$I,$A5)) | H5: =IF($A5="","",SUMIFS(saisie_hebdo!$M:$M,saisie_hebdo!$I:$I,$A5)) | I5: =IF(OR($A5="",L5=0),"",IF(D5="Pourcentage",IF(H5>0,G5/H5*100,""),G5)) | J5: =IF(OR(I5="",F5="",F5=0),"",I5/F5) | K5: =IF(OR($A5="",L5=0),"",IF(_xlfn.MAXIFS(saisie_hebdo!$C:$C,saisie_hebdo!$I:$I,$A5)=0,"",_xlfn.MAXIFS(saisie_hebdo!$C:$C,saisie_hebdo!$I:$I,$A5))) | L5: =IF($A5="","",COUNTIFS(saisie_hebdo!$I:$I,$A5)) | M5: =IF($A5="","",IF(L5=0,"Non rapporté",IF(F5="","Suivi sans cible",IF(D5="Pourcentage",IF(I5>=F5,"Cible atteinte","Sous la cible"),IF(J5>=1,"Cible atteinte","En cours")))))
A6: =IFERROR(INDEX(ref_indicateurs!$A:$A,3)&"","") | B6: =IF($A6="","",INDEX(ref_indicateurs!$B:$B,MATCH($A6,ref_indicateurs!$A:$A,0))&"") | C6: =IF($A6="","",INDEX(ref_indicateurs!$C:$C,MATCH($A6,ref_indicateurs!$A:$A,0))&"") | D6: =IF($A6="","",INDEX(ref_indicateurs!$E:$E,MATCH($A6,ref_indicateurs!$A:$A,0))&"") | E6: =IF($A6="","",INDEX(ref_indicateurs!$M:$M,MATCH($A6,ref_indicateurs!$A:$A,0))&"") | F6: =IF($A6="","",IF(INDEX(ref_indicateurs!$O:$O,MATCH($A6,ref_indicateurs!$A:$A,0))="","",INDEX(ref_indicateurs!$O:$O,MATCH($A6,ref_indicateurs!$A:$A,0)))) | G6: =IF($A6="","",SUMIFS(saisie_hebdo!$L:$L,saisie_hebdo!$I:$I,$A6)) | H6: =IF($A6="","",SUMIFS(saisie_hebdo!$M:$M,saisie_hebdo!$I:$I,$A6)) | I6: =IF(OR($A6="",L6=0),"",IF(D6="Pourcentage",IF(H6>0,G6/H6*100,""),G6)) | J6: =IF(OR(I6="",F6="",F6=0),"",I6/F6) | K6: =IF(OR($A6="",L6=0),"",IF(_xlfn.MAXIFS(saisie_hebdo!$C:$C,saisie_hebdo!$I:$I,$A6)=0,"",_xlfn.MAXIFS(saisie_hebdo!$C:$C,saisie_hebdo!$I:$I,$A6))) | L6: =IF($A6="","",COUNTIFS(saisie_hebdo!$I:$I,$A6)) | M6: =IF($A6="","",IF(L6=0,"Non rapporté",IF(F6="","Suivi sans cible",IF(D6="Pourcentage",IF(I6>=F6,"Cible atteinte","Sous la cible"),IF(J6>=1,"Cible atteinte","En cours")))))
A7: =IFERROR(INDEX(ref_indicateurs!$A:$A,4)&"","") | B7: =IF($A7="","",INDEX(ref_indicateurs!$B:$B,MATCH($A7,ref_indicateurs!$A:$A,0))&"") | C7: =IF($A7="","",INDEX(ref_indicateurs!$C:$C,MATCH($A7,ref_indicateurs!$A:$A,0))&"") | D7: =IF($A7="","",INDEX(ref_indicateurs!$E:$E,MATCH($A7,ref_indicateurs!$A:$A,0))&"") | E7: =IF($A7="","",INDEX(ref_indicateurs!$M:$M,MATCH($A7,ref_indicateurs!$A:$A,0))&"") | F7: =IF($A7="","",IF(INDEX(ref_indicateurs!$O:$O,MATCH($A7,ref_indicateurs!$A:$A,0))="","",INDEX(ref_indicateurs!$O:$O,MATCH($A7,ref_indicateurs!$A:$A,0)))) | G7: =IF($A7="","",SUMIFS(saisie_hebdo!$L:$L,saisie_hebdo!$I:$I,$A7)) | H7: =IF($A7="","",SUMIFS(saisie_hebdo!$M:$M,saisie_hebdo!$I:$I,$A7)) | I7: =IF(OR($A7="",L7=0),"",IF(D7="Pourcentage",IF(H7>0,G7/H7*100,""),G7)) | J7: =IF(OR(I7="",F7="",F7=0),"",I7/F7) | K7: =IF(OR($A7="",L7=0),"",IF(_xlfn.MAXIFS(saisie_hebdo!$C:$C,saisie_hebdo!$I:$I,$A7)=0,"",_xlfn.MAXIFS(saisie_hebdo!$C:$C,saisie_hebdo!$I:$I,$A7))) | L7: =IF($A7="","",COUNTIFS(saisie_hebdo!$I:$I,$A7)) | M7: =IF($A7="","",IF(L7=0,"Non rapporté",IF(F7="","Suivi sans cible",IF(D7="Pourcentage",IF(I7>=F7,"Cible atteinte","Sous la cible"),IF(J7>=1,"Cible atteinte","En cours")))))
A8: =IFERROR(INDEX(ref_indicateurs!$A:$A,5)&"","") | B8: =IF($A8="","",INDEX(ref_indicateurs!$B:$B,MATCH($A8,ref_indicateurs!$A:$A,0))&"") | C8: =IF($A8="","",INDEX(ref_indicateurs!$C:$C,MATCH($A8,ref_indicateurs!$A:$A,0))&"") | D8: =IF($A8="","",INDEX(ref_indicateurs!$E:$E,MATCH($A8,ref_indicateurs!$A:$A,0))&"") | E8: =IF($A8="","",INDEX(ref_indicateurs!$M:$M,MATCH($A8,ref_indicateurs!$A:$A,0))&"") | F8: =IF($A8="","",IF(INDEX(ref_indicateurs!$O:$O,MATCH($A8,ref_indicateurs!$A:$A,0))="","",INDEX(ref_indicateurs!$O:$O,MATCH($A8,ref_indicateurs!$A:$A,0)))) | G8: =IF($A8="","",SUMIFS(saisie_hebdo!$L:$L,saisie_hebdo!$I:$I,$A8)) | H8: =IF($A8="","",SUMIFS(saisie_hebdo!$M:$M,saisie_hebdo!$I:$I,$A8)) | I8: =IF(OR($A8="",L8=0),"",IF(D8="Pourcentage",IF(H8>0,G8/H8*100,""),G8)) | J8: =IF(OR(I8="",F8="",F8=0),"",I8/F8) | K8: =IF(OR($A8="",L8=0),"",IF(_xlfn.MAXIFS(saisie_hebdo!$C:$C,saisie_hebdo!$I:$I,$A8)=0,"",_xlfn.MAXIFS(saisie_hebdo!$C:$C,saisie_hebdo!$I:$I,$A8))) | L8: =IF($A8="","",COUNTIFS(saisie_hebdo!$I:$I,$A8)) | M8: =IF($A8="","",IF(L8=0,"Non rapporté",IF(F8="","Suivi sans cible",IF(D8="Pourcentage",IF(I8>=F8,"Cible atteinte","Sous la cible"),IF(J8>=1,"Cible atteinte","En cours")))))
A9: =IFERROR(INDEX(ref_indicateurs!$A:$A,6)&"","") | B9: =IF($A9="","",INDEX(ref_indicateurs!$B:$B,MATCH($A9,ref_indicateurs!$A:$A,0))&"") | C9: =IF($A9="","",INDEX(ref_indicateurs!$C:$C,MATCH($A9,ref_indicateurs!$A:$A,0))&"") | D9: =IF($A9="","",INDEX(ref_indicateurs!$E:$E,MATCH($A9,ref_indicateurs!$A:$A,0))&"") | E9: =IF($A9="","",INDEX(ref_indicateurs!$M:$M,MATCH($A9,ref_indicateurs!$A:$A,0))&"") | F9: =IF($A9="","",IF(INDEX(ref_indicateurs!$O:$O,MATCH($A9,ref_indicateurs!$A:$A,0))="","",INDEX(ref_indicateurs!$O:$O,MATCH($A9,ref_indicateurs!$A:$A,0)))) | G9: =IF($A9="","",SUMIFS(saisie_hebdo!$L:$L,saisie_hebdo!$I:$I,$A9)) | H9: =IF($A9="","",SUMIFS(saisie_hebdo!$M:$M,saisie_hebdo!$I:$I,$A9)) | I9: =IF(OR($A9="",L9=0),"",IF(D9="Pourcentage",IF(H9>0,G9/H9*100,""),G9)) | J9: =IF(OR(I9="",F9="",F9=0),"",I9/F9) | K9: =IF(OR($A9="",L9=0),"",IF(_xlfn.MAXIFS(saisie_hebdo!$C:$C,saisie_hebdo!$I:$I,$A9)=0,"",_xlfn.MAXIFS(saisie_hebdo!$C:$C,saisie_hebdo!$I:$I,$A9))) | L9: =IF($A9="","",COUNTIFS(saisie_hebdo!$I:$I,$A9)) | M9: =IF($A9="","",IF(L9=0,"Non rapporté",IF(F9="","Suivi sans cible",IF(D9="Pourcentage",IF(I9>=F9,"Cible atteinte","Sous la cible"),IF(J9>=1,"Cible atteinte","En cours")))))
A10: =IFERROR(INDEX(ref_indicateurs!$A:$A,7)&"","") | B10: =IF($A10="","",INDEX(ref_indicateurs!$B:$B,MATCH($A10,ref_indicateurs!$A:$A,0))&"") | C10: =IF($A10="","",INDEX(ref_indicateurs!$C:$C,MATCH($A10,ref_indicateurs!$A:$A,0))&"") | D10: =IF($A10="","",INDEX(ref_indicateurs!$E:$E,MATCH($A10,ref_indicateurs!$A:$A,0))&"") | E10: =IF($A10="","",INDEX(ref_indicateurs!$M:$M,MATCH($A10,ref_indicateurs!$A:$A,0))&"") | F10: =IF($A10="","",IF(INDEX(ref_indicateurs!$O:$O,MATCH($A10,ref_indicateurs!$A:$A,0))="","",INDEX(ref_indicateurs!$O:$O,MATCH($A10,ref_indicateurs!$A:$A,0)))) | G10: =IF($A10="","",SUMIFS(saisie_hebdo!$L:$L,saisie_hebdo!$I:$I,$A10)) | H10: =IF($A10="","",SUMIFS(saisie_hebdo!$M:$M,saisie_hebdo!$I:$I,$A10)) | I10: =IF(OR($A10="",L10=0),"",IF(D10="Pourcentage",IF(H10>0,G10/H10*100,""),G10)) | J10: =IF(OR(I10="",F10="",F10=0),"",I10/F10) | K10: =IF(OR($A10="",L10=0),"",IF(_xlfn.MAXIFS(saisie_hebdo!$C:$C,saisie_hebdo!$I:$I,$A10)=0,"",_xlfn.MAXIFS(saisie_hebdo!$C:$C,saisie_hebdo!$I:$I,$A10))) | L10: =IF($A10="","",COUNTIFS(saisie_hebdo!$I:$I,$A10)) | M10: =IF($A10="","",IF(L10=0,"Non rapporté",IF(F10="","Suivi sans cible",IF(D10="Pourcentage",IF(I10>=F10,"Cible atteinte","Sous la cible"),IF(J10>=1,"Cible atteinte","En cours")))))
A11: =IFERROR(INDEX(ref_indicateurs!$A:$A,8)&"","") | B11: =IF($A11="","",INDEX(ref_indicateurs!$B:$B,MATCH($A11,ref_indicateurs!$A:$A,0))&"") | C11: =IF($A11="","",INDEX(ref_indicateurs!$C:$C,MATCH($A11,ref_indicateurs!$A:$A,0))&"") | D11: =IF($A11="","",INDEX(ref_indicateurs!$E:$E,MATCH($A11,ref_indicateurs!$A:$A,0))&"") | E11: =IF($A11="","",INDEX(ref_indicateurs!$M:$M,MATCH($A11,ref_indicateurs!$A:$A,0))&"") | F11: =IF($A11="","",IF(INDEX(ref_indicateurs!$O:$O,MATCH($A11,ref_indicateurs!$A:$A,0))="","",INDEX(ref_indicateurs!$O:$O,MATCH($A11,ref_indicateurs!$A:$A,0)))) | G11: =IF($A11="","",SUMIFS(saisie_hebdo!$L:$L,saisie_hebdo!$I:$I,$A11)) | H11: =IF($A11="","",SUMIFS(saisie_hebdo!$M:$M,saisie_hebdo!$I:$I,$A11)) | I11: =IF(OR($A11="",L11=0),"",IF(D11="Pourcentage",IF(H11>0,G11/H11*100,""),G11)) | J11: =IF(OR(I11="",F11="",F11=0),"",I11/F11) | K11: =IF(OR($A11="",L11=0),"",IF(_xlfn.MAXIFS(saisie_hebdo!$C:$C,saisie_hebdo!$I:$I,$A11)=0,"",_xlfn.MAXIFS(saisie_hebdo!$C:$C,saisie_hebdo!$I:$I,$A11))) | L11: =IF($A11="","",COUNTIFS(saisie_hebdo!$I:$I,$A11)) | M11: =IF($A11="","",IF(L11=0,"Non rapporté",IF(F11="","Suivi sans cible",IF(D11="Pourcentage",IF(I11>=F11,"Cible atteinte","Sous la cible"),IF(J11>=1,"Cible atteinte","En cours")))))
A12: =IFERROR(INDEX(ref_indicateurs!$A:$A,9)&"","") | B12: =IF($A12="","",INDEX(ref_indicateurs!$B:$B,MATCH($A12,ref_indicateurs!$A:$A,0))&"") | C12: =IF($A12="","",INDEX(ref_indicateurs!$C:$C,MATCH($A12,ref_indicateurs!$A:$A,0))&"") | D12: =IF($A12="","",INDEX(ref_indicateurs!$E:$E,MATCH($A12,ref_indicateurs!$A:$A,0))&"") | E12: =IF($A12="","",INDEX(ref_indicateurs!$M:$M,MATCH($A12,ref_indicateurs!$A:$A,0))&"") | F12: =IF($A12="","",IF(INDEX(ref_indicateurs!$O:$O,MATCH($A12,ref_indicateurs!$A:$A,0))="","",INDEX(ref_indicateurs!$O:$O,MATCH($A12,ref_indicateurs!$A:$A,0)))) | G12: =IF($A12="","",SUMIFS(saisie_hebdo!$L:$L,saisie_hebdo!$I:$I,$A12)) | H12: =IF($A12="","",SUMIFS(saisie_hebdo!$M:$M,saisie_hebdo!$I:$I,$A12)) | I12: =IF(OR($A12="",L12=0),"",IF(D12="Pourcentage",IF(H12>0,G12/H12*100,""),G12)) | J12: =IF(OR(I12="",F12="",F12=0),"",I12/F12) | K12: =IF(OR($A12="",L12=0),"",IF(_xlfn.MAXIFS(saisie_hebdo!$C:$C,saisie_hebdo!$I:$I,$A12)=0,"",_xlfn.MAXIFS(saisie_hebdo!$C:$C,saisie_hebdo!$I:$I,$A12))) | L12: =IF($A12="","",COUNTIFS(saisie_hebdo!$I:$I,$A12)) | M12: =IF($A12="","",IF(L12=0,"Non rapporté",IF(F12="","Suivi sans cible",IF(D12="Pourcentage",IF(I12>=F12,"Cible atteinte","Sous la cible"),IF(J12>=1,"Cible atteinte","En cours")))))
A13: =IFERROR(INDEX(ref_indicateurs!$A:$A,10)&"","") | B13: =IF($A13="","",INDEX(ref_indicateurs!$B:$B,MATCH($A13,ref_indicateurs!$A:$A,0))&"") | C13: =IF($A13="","",INDEX(ref_indicateurs!$C:$C,MATCH($A13,ref_indicateurs!$A:$A,0))&"") | D13: =IF($A13="","",INDEX(ref_indicateurs!$E:$E,MATCH($A13,ref_indicateurs!$A:$A,0))&"") | E13: =IF($A13="","",INDEX(ref_indicateurs!$M:$M,MATCH($A13,ref_indicateurs!$A:$A,0))&"") | F13: =IF($A13="","",IF(INDEX(ref_indicateurs!$O:$O,MATCH($A13,ref_indicateurs!$A:$A,0))="","",INDEX(ref_indicateurs!$O:$O,MATCH($A13,ref_indicateurs!$A:$A,0)))) | G13: =IF($A13="","",SUMIFS(saisie_hebdo!$L:$L,saisie_hebdo!$I:$I,$A13)) | H13: =IF($A13="","",SUMIFS(saisie_hebdo!$M:$M,saisie_hebdo!$I:$I,$A13)) | I13: =IF(OR($A13="",L13=0),"",IF(D13="Pourcentage",IF(H13>0,G13/H13*100,""),G13)) | J13: =IF(OR(I13="",F13="",F13=0),"",I13/F13) | K13: =IF(OR($A13="",L13=0),"",IF(_xlfn.MAXIFS(saisie_hebdo!$C:$C,saisie_hebdo!$I:$I,$A13)=0,"",_xlfn.MAXIFS(saisie_hebdo!$C:$C,saisie_hebdo!$I:$I,$A13))) | L13: =IF($A13="","",COUNTIFS(saisie_hebdo!$I:$I,$A13)) | M13: =IF($A13="","",IF(L13=0,"Non rapporté",IF(F13="","Suivi sans cible",IF(D13="Pourcentage",IF(I13>=F13,"Cible atteinte","Sous la cible"),IF(J13>=1,"Cible atteinte","En cours")))))
A14: =IFERROR(INDEX(ref_indicateurs!$A:$A,11)&"","") | B14: =IF($A14="","",INDEX(ref_indicateurs!$B:$B,MATCH($A14,ref_indicateurs!$A:$A,0))&"") | C14: =IF($A14="","",INDEX(ref_indicateurs!$C:$C,MATCH($A14,ref_indicateurs!$A:$A,0))&"") | D14: =IF($A14="","",INDEX(ref_indicateurs!$E:$E,MATCH($A14,ref_indicateurs!$A:$A,0))&"") | E14: =IF($A14="","",INDEX(ref_indicateurs!$M:$M,MATCH($A14,ref_indicateurs!$A:$A,0))&"") | F14: =IF($A14="","",IF(INDEX(ref_indicateurs!$O:$O,MATCH($A14,ref_indicateurs!$A:$A,0))="","",INDEX(ref_indicateurs!$O:$O,MATCH($A14,ref_indicateurs!$A:$A,0)))) | G14: =IF($A14="","",SUMIFS(saisie_hebdo!$L:$L,saisie_hebdo!$I:$I,$A14)) | H14: =IF($A14="","",SUMIFS(saisie_hebdo!$M:$M,saisie_hebdo!$I:$I,$A14)) | I14: =IF(OR($A14="",L14=0),"",IF(D14="Pourcentage",IF(H14>0,G14/H14*100,""),G14)) | J14: =IF(OR(I14="",F14="",F14=0),"",I14/F14) | K14: =IF(OR($A14="",L14=0),"",IF(_xlfn.MAXIFS(saisie_hebdo!$C:$C,saisie_hebdo!$I:$I,$A14)=0,"",_xlfn.MAXIFS(saisie_hebdo!$C:$C,saisie_hebdo!$I:$I,$A14))) | L14: =IF($A14="","",COUNTIFS(saisie_hebdo!$I:$I,$A14)) | M14: =IF($A14="","",IF(L14=0,"Non rapporté",IF(F14="","Suivi sans cible",IF(D14="Pourcentage",IF(I14>=F14,"Cible atteinte","Sous la cible"),IF(J14>=1,"Cible atteinte","En cours")))))
A15: =IFERROR(INDEX(ref_indicateurs!$A:$A,12)&"","") | B15: =IF($A15="","",INDEX(ref_indicateurs!$B:$B,MATCH($A15,ref_indicateurs!$A:$A,0))&"") | C15: =IF($A15="","",INDEX(ref_indicateurs!$C:$C,MATCH($A15,ref_indicateurs!$A:$A,0))&"") | D15: =IF($A15="","",INDEX(ref_indicateurs!$E:$E,MATCH($A15,ref_indicateurs!$A:$A,0))&"") | E15: =IF($A15="","",INDEX(ref_indicateurs!$M:$M,MATCH($A15,ref_indicateurs!$A:$A,0))&"") | F15: =IF($A15="","",IF(INDEX(ref_indicateurs!$O:$O,MATCH($A15,ref_indicateurs!$A:$A,0))="","",INDEX(ref_indicateurs!$O:$O,MATCH($A15,ref_indicateurs!$A:$A,0)))) | G15: =IF($A15="","",SUMIFS(saisie_hebdo!$L:$L,saisie_hebdo!$I:$I,$A15)) | H15: =IF($A15="","",SUMIFS(saisie_hebdo!$M:$M,saisie_hebdo!$I:$I,$A15)) | I15: =IF(OR($A15="",L15=0),"",IF(D15="Pourcentage",IF(H15>0,G15/H15*100,""),G15)) | J15: =IF(OR(I15="",F15="",F15=0),"",I15/F15) | K15: =IF(OR($A15="",L15=0),"",IF(_xlfn.MAXIFS(saisie_hebdo!$C:$C,saisie_hebdo!$I:$I,$A15)=0,"",_xlfn.MAXIFS(saisie_hebdo!$C:$C,saisie_hebdo!$I:$I,$A15))) | L15: =IF($A15="","",COUNTIFS(saisie_hebdo!$I:$I,$A15)) | M15: =IF($A15="","",IF(L15=0,"Non rapporté",IF(F15="","Suivi sans cible",IF(D15="Pourcentage",IF(I15>=F15,"Cible atteinte","Sous la cible"),IF(J15>=1,"Cible atteinte","En cours")))))
A16: =IFERROR(INDEX(ref_indicateurs!$A:$A,13)&"","") | B16: =IF($A16="","",INDEX(ref_indicateurs!$B:$B,MATCH($A16,ref_indicateurs!$A:$A,0))&"") | C16: =IF($A16="","",INDEX(ref_indicateurs!$C:$C,MATCH($A16,ref_indicateurs!$A:$A,0))&"") | D16: =IF($A16="","",INDEX(ref_indicateurs!$E:$E,MATCH($A16,ref_indicateurs!$A:$A,0))&"") | E16: =IF($A16="","",INDEX(ref_indicateurs!$M:$M,MATCH($A16,ref_indicateurs!$A:$A,0))&"") | F16: =IF($A16="","",IF(INDEX(ref_indicateurs!$O:$O,MATCH($A16,ref_indicateurs!$A:$A,0))="","",INDEX(ref_indicateurs!$O:$O,MATCH($A16,ref_indicateurs!$A:$A,0)))) | G16: =IF($A16="","",SUMIFS(saisie_hebdo!$L:$L,saisie_hebdo!$I:$I,$A16)) | H16: =IF($A16="","",SUMIFS(saisie_hebdo!$M:$M,saisie_hebdo!$I:$I,$A16)) | I16: =IF(OR($A16="",L16=0),"",IF(D16="Pourcentage",IF(H16>0,G16/H16*100,""),G16)) | J16: =IF(OR(I16="",F16="",F16=0),"",I16/F16) | K16: =IF(OR($A16="",L16=0),"",IF(_xlfn.MAXIFS(saisie_hebdo!$C:$C,saisie_hebdo!$I:$I,$A16)=0,"",_xlfn.MAXIFS(saisie_hebdo!$C:$C,saisie_hebdo!$I:$I,$A16))) | L16: =IF($A16="","",COUNTIFS(saisie_hebdo!$I:$I,$A16)) | M16: =IF($A16="","",IF(L16=0,"Non rapporté",IF(F16="","Suivi sans cible",IF(D16="Pourcentage",IF(I16>=F16,"Cible atteinte","Sous la cible"),IF(J16>=1,"Cible atteinte","En cours")))))
A17: =IFERROR(INDEX(ref_indicateurs!$A:$A,14)&"","") | B17: =IF($A17="","",INDEX(ref_indicateurs!$B:$B,MATCH($A17,ref_indicateurs!$A:$A,0))&"") | C17: =IF($A17="","",INDEX(ref_indicateurs!$C:$C,MATCH($A17,ref_indicateurs!$A:$A,0))&"") | D17: =IF($A17="","",INDEX(ref_indicateurs!$E:$E,MATCH($A17,ref_indicateurs!$A:$A,0))&"") | E17: =IF($A17="","",INDEX(ref_indicateurs!$M:$M,MATCH($A17,ref_indicateurs!$A:$A,0))&"") | F17: =IF($A17="","",IF(INDEX(ref_indicateurs!$O:$O,MATCH($A17,ref_indicateurs!$A:$A,0))="","",INDEX(ref_indicateurs!$O:$O,MATCH($A17,ref_indicateurs!$A:$A,0)))) | G17: =IF($A17="","",SUMIFS(saisie_hebdo!$L:$L,saisie_hebdo!$I:$I,$A17)) | H17: =IF($A17="","",SUMIFS(saisie_hebdo!$M:$M,saisie_hebdo!$I:$I,$A17)) | I17: =IF(OR($A17="",L17=0),"",IF(D17="Pourcentage",IF(H17>0,G17/H17*100,""),G17)) | J17: =IF(OR(I17="",F17="",F17=0),"",I17/F17) | K17: =IF(OR($A17="",L17=0),"",IF(_xlfn.MAXIFS(saisie_hebdo!$C:$C,saisie_hebdo!$I:$I,$A17)=0,"",_xlfn.MAXIFS(saisie_hebdo!$C:$C,saisie_hebdo!$I:$I,$A17))) | L17: =IF($A17="","",COUNTIFS(saisie_hebdo!$I:$I,$A17)) | M17: =IF($A17="","",IF(L17=0,"Non rapporté",IF(F17="","Suivi sans cible",IF(D17="Pourcentage",IF(I17>=F17,"Cible atteinte","Sous la cible"),IF(J17>=1,"Cible atteinte","En cours")))))
A18: =IFERROR(INDEX(ref_indicateurs!$A:$A,15)&"","") | B18: =IF($A18="","",INDEX(ref_indicateurs!$B:$B,MATCH($A18,ref_indicateurs!$A:$A,0))&"") | C18: =IF($A18="","",INDEX(ref_indicateurs!$C:$C,MATCH($A18,ref_indicateurs!$A:$A,0))&"") | D18: =IF($A18="","",INDEX(ref_indicateurs!$E:$E,MATCH($A18,ref_indicateurs!$A:$A,0))&"") | E18: =IF($A18="","",INDEX(ref_indicateurs!$M:$M,MATCH($A18,ref_indicateurs!$A:$A,0))&"") | F18: =IF($A18="","",IF(INDEX(ref_indicateurs!$O:$O,MATCH($A18,ref_indicateurs!$A:$A,0))="","",INDEX(ref_indicateurs!$O:$O,MATCH($A18,ref_indicateurs!$A:$A,0)))) | G18: =IF($A18="","",SUMIFS(saisie_hebdo!$L:$L,saisie_hebdo!$I:$I,$A18)) | H18: =IF($A18="","",SUMIFS(saisie_hebdo!$M:$M,saisie_hebdo!$I:$I,$A18)) | I18: =IF(OR($A18="",L18=0),"",IF(D18="Pourcentage",IF(H18>0,G18/H18*100,""),G18)) | J18: =IF(OR(I18="",F18="",F18=0),"",I18/F18) | K18: =IF(OR($A18="",L18=0),"",IF(_xlfn.MAXIFS(saisie_hebdo!$C:$C,saisie_hebdo!$I:$I,$A18)=0,"",_xlfn.MAXIFS(saisie_hebdo!$C:$C,saisie_hebdo!$I:$I,$A18))) | L18: =IF($A18="","",COUNTIFS(saisie_hebdo!$I:$I,$A18)) | M18: =IF($A18="","",IF(L18=0,"Non rapporté",IF(F18="","Suivi sans cible",IF(D18="Pourcentage",IF(I18>=F18,"Cible atteinte","Sous la cible"),IF(J18>=1,"Cible atteinte","En cours")))))
A19: =IFERROR(INDEX(ref_indicateurs!$A:$A,16)&"","") | B19: =IF($A19="","",INDEX(ref_indicateurs!$B:$B,MATCH($A19,ref_indicateurs!$A:$A,0))&"") | C19: =IF($A19="","",INDEX(ref_indicateurs!$C:$C,MATCH($A19,ref_indicateurs!$A:$A,0))&"") | D19: =IF($A19="","",INDEX(ref_indicateurs!$E:$E,MATCH($A19,ref_indicateurs!$A:$A,0))&"") | E19: =IF($A19="","",INDEX(ref_indicateurs!$M:$M,MATCH($A19,ref_indicateurs!$A:$A,0))&"") | F19: =IF($A19="","",IF(INDEX(ref_indicateurs!$O:$O,MATCH($A19,ref_indicateurs!$A:$A,0))="","",INDEX(ref_indicateurs!$O:$O,MATCH($A19,ref_indicateurs!$A:$A,0)))) | G19: =IF($A19="","",SUMIFS(saisie_hebdo!$L:$L,saisie_hebdo!$I:$I,$A19)) | H19: =IF($A19="","",SUMIFS(saisie_hebdo!$M:$M,saisie_hebdo!$I:$I,$A19)) | I19: =IF(OR($A19="",L19=0),"",IF(D19="Pourcentage",IF(H19>0,G19/H19*100,""),G19)) | J19: =IF(OR(I19="",F19="",F19=0),"",I19/F19) | K19: =IF(OR($A19="",L19=0),"",IF(_xlfn.MAXIFS(saisie_hebdo!$C:$C,saisie_hebdo!$I:$I,$A19)=0,"",_xlfn.MAXIFS(saisie_hebdo!$C:$C,saisie_hebdo!$I:$I,$A19))) | L19: =IF($A19="","",COUNTIFS(saisie_hebdo!$I:$I,$A19)) | M19: =IF($A19="","",IF(L19=0,"Non rapporté",IF(F19="","Suivi sans cible",IF(D19="Pourcentage",IF(I19>=F19,"Cible atteinte","Sous la cible"),IF(J19>=1,"Cible atteinte","En cours")))))
A20: =IFERROR(INDEX(ref_indicateurs!$A:$A,17)&"","") | B20: =IF($A20="","",INDEX(ref_indicateurs!$B:$B,MATCH($A20,ref_indicateurs!$A:$A,0))&"") | C20: =IF($A20="","",INDEX(ref_indicateurs!$C:$C,MATCH($A20,ref_indicateurs!$A:$A,0))&"") | D20: =IF($A20="","",INDEX(ref_indicateurs!$E:$E,MATCH($A20,ref_indicateurs!$A:$A,0))&"") | E20: =IF($A20="","",INDEX(ref_indicateurs!$M:$M,MATCH($A20,ref_indicateurs!$A:$A,0))&"") | F20: =IF($A20="","",IF(INDEX(ref_indicateurs!$O:$O,MATCH($A20,ref_indicateurs!$A:$A,0))="","",INDEX(ref_indicateurs!$O:$O,MATCH($A20,ref_indicateurs!$A:$A,0)))) | G20: =IF($A20="","",SUMIFS(saisie_hebdo!$L:$L,saisie_hebdo!$I:$I,$A20)) | H20: =IF($A20="","",SUMIFS(saisie_hebdo!$M:$M,saisie_hebdo!$I:$I,$A20)) | I20: =IF(OR($A20="",L20=0),"",IF(D20="Pourcentage",IF(H20>0,G20/H20*100,""),G20)) | J20: =IF(OR(I20="",F20="",F20=0),"",I20/F20) | K20: =IF(OR($A20="",L20=0),"",IF(_xlfn.MAXIFS(saisie_hebdo!$C:$C,saisie_hebdo!$I:$I,$A20)=0,"",_xlfn.MAXIFS(saisie_hebdo!$C:$C,saisie_hebdo!$I:$I,$A20))) | L20: =IF($A20="","",COUNTIFS(saisie_hebdo!$I:$I,$A20)) | M20: =IF($A20="","",IF(L20=0,"Non rapporté",IF(F20="","Suivi sans cible",IF(D20="Pourcentage",IF(I20>=F20,"Cible atteinte","Sous la cible"),IF(J20>=1,"Cible atteinte","En cours")))))
A21: =IFERROR(INDEX(ref_indicateurs!$A:$A,18)&"","") | B21: =IF($A21="","",INDEX(ref_indicateurs!$B:$B,MATCH($A21,ref_indicateurs!$A:$A,0))&"") | C21: =IF($A21="","",INDEX(ref_indicateurs!$C:$C,MATCH($A21,ref_indicateurs!$A:$A,0))&"") | D21: =IF($A21="","",INDEX(ref_indicateurs!$E:$E,MATCH($A21,ref_indicateurs!$A:$A,0))&"") | E21: =IF($A21="","",INDEX(ref_indicateurs!$M:$M,MATCH($A21,ref_indicateurs!$A:$A,0))&"") | F21: =IF($A21="","",IF(INDEX(ref_indicateurs!$O:$O,MATCH($A21,ref_indicateurs!$A:$A,0))="","",INDEX(ref_indicateurs!$O:$O,MATCH($A21,ref_indicateurs!$A:$A,0)))) | G21: =IF($A21="","",SUMIFS(saisie_hebdo!$L:$L,saisie_hebdo!$I:$I,$A21)) | H21: =IF($A21="","",SUMIFS(saisie_hebdo!$M:$M,saisie_hebdo!$I:$I,$A21)) | I21: =IF(OR($A21="",L21=0),"",IF(D21="Pourcentage",IF(H21>0,G21/H21*100,""),G21)) | J21: =IF(OR(I21="",F21="",F21=0),"",I21/F21) | K21: =IF(OR($A21="",L21=0),"",IF(_xlfn.MAXIFS(saisie_hebdo!$C:$C,saisie_hebdo!$I:$I,$A21)=0,"",_xlfn.MAXIFS(saisie_hebdo!$C:$C,saisie_hebdo!$I:$I,$A21))) | L21: =IF($A21="","",COUNTIFS(saisie_hebdo!$I:$I,$A21)) | M21: =IF($A21="","",IF(L21=0,"Non rapporté",IF(F21="","Suivi sans cible",IF(D21="Pourcentage",IF(I21>=F21,"Cible atteinte","Sous la cible"),IF(J21>=1,"Cible atteinte","En cours")))))
A22: =IFERROR(INDEX(ref_indicateurs!$A:$A,19)&"","") | B22: =IF($A22="","",INDEX(ref_indicateurs!$B:$B,MATCH($A22,ref_indicateurs!$A:$A,0))&"") | C22: =IF($A22="","",INDEX(ref_indicateurs!$C:$C,MATCH($A22,ref_indicateurs!$A:$A,0))&"") | D22: =IF($A22="","",INDEX(ref_indicateurs!$E:$E,MATCH($A22,ref_indicateurs!$A:$A,0))&"") | E22: =IF($A22="","",INDEX(ref_indicateurs!$M:$M,MATCH($A22,ref_indicateurs!$A:$A,0))&"") | F22: =IF($A22="","",IF(INDEX(ref_indicateurs!$O:$O,MATCH($A22,ref_indicateurs!$A:$A,0))="","",INDEX(ref_indicateurs!$O:$O,MATCH($A22,ref_indicateurs!$A:$A,0)))) | G22: =IF($A22="","",SUMIFS(saisie_hebdo!$L:$L,saisie_hebdo!$I:$I,$A22)) | H22: =IF($A22="","",SUMIFS(saisie_hebdo!$M:$M,saisie_hebdo!$I:$I,$A22)) | I22: =IF(OR($A22="",L22=0),"",IF(D22="Pourcentage",IF(H22>0,G22/H22*100,""),G22)) | J22: =IF(OR(I22="",F22="",F22=0),"",I22/F22) | K22: =IF(OR($A22="",L22=0),"",IF(_xlfn.MAXIFS(saisie_hebdo!$C:$C,saisie_hebdo!$I:$I,$A22)=0,"",_xlfn.MAXIFS(saisie_hebdo!$C:$C,saisie_hebdo!$I:$I,$A22))) | L22: =IF($A22="","",COUNTIFS(saisie_hebdo!$I:$I,$A22)) | M22: =IF($A22="","",IF(L22=0,"Non rapporté",IF(F22="","Suivi sans cible",IF(D22="Pourcentage",IF(I22>=F22,"Cible atteinte","Sous la cible"),IF(J22>=1,"Cible atteinte","En cours")))))
A23: =IFERROR(INDEX(ref_indicateurs!$A:$A,20)&"","") | B23: =IF($A23="","",INDEX(ref_indicateurs!$B:$B,MATCH($A23,ref_indicateurs!$A:$A,0))&"") | C23: =IF($A23="","",INDEX(ref_indicateurs!$C:$C,MATCH($A23,ref_indicateurs!$A:$A,0))&"") | D23: =IF($A23="","",INDEX(ref_indicateurs!$E:$E,MATCH($A23,ref_indicateurs!$A:$A,0))&"") | E23: =IF($A23="","",INDEX(ref_indicateurs!$M:$M,MATCH($A23,ref_indicateurs!$A:$A,0))&"") | F23: =IF($A23="","",IF(INDEX(ref_indicateurs!$O:$O,MATCH($A23,ref_indicateurs!$A:$A,0))="","",INDEX(ref_indicateurs!$O:$O,MATCH($A23,ref_indicateurs!$A:$A,0)))) | G23: =IF($A23="","",SUMIFS(saisie_hebdo!$L:$L,saisie_hebdo!$I:$I,$A23)) | H23: =IF($A23="","",SUMIFS(saisie_hebdo!$M:$M,saisie_hebdo!$I:$I,$A23)) | I23: =IF(OR($A23="",L23=0),"",IF(D23="Pourcentage",IF(H23>0,G23/H23*100,""),G23)) | J23: =IF(OR(I23="",F23="",F23=0),"",I23/F23) | K23: =IF(OR($A23="",L23=0),"",IF(_xlfn.MAXIFS(saisie_hebdo!$C:$C,saisie_hebdo!$I:$I,$A23)=0,"",_xlfn.MAXIFS(saisie_hebdo!$C:$C,saisie_hebdo!$I:$I,$A23))) | L23: =IF($A23="","",COUNTIFS(saisie_hebdo!$I:$I,$A23)) | M23: =IF($A23="","",IF(L23=0,"Non rapporté",IF(F23="","Suivi sans cible",IF(D23="Pourcentage",IF(I23>=F23,"Cible atteinte","Sous la cible"),IF(J23>=1,"Cible atteinte","En cours")))))
A24: =IFERROR(INDEX(ref_indicateurs!$A:$A,21)&"","") | B24: =IF($A24="","",INDEX(ref_indicateurs!$B:$B,MATCH($A24,ref_indicateurs!$A:$A,0))&"") | C24: =IF($A24="","",INDEX(ref_indicateurs!$C:$C,MATCH($A24,ref_indicateurs!$A:$A,0))&"") | D24: =IF($A24="","",INDEX(ref_indicateurs!$E:$E,MATCH($A24,ref_indicateurs!$A:$A,0))&"") | E24: =IF($A24="","",INDEX(ref_indicateurs!$M:$M,MATCH($A24,ref_indicateurs!$A:$A,0))&"") | F24: =IF($A24="","",IF(INDEX(ref_indicateurs!$O:$O,MATCH($A24,ref_indicateurs!$A:$A,0))="","",INDEX(ref_indicateurs!$O:$O,MATCH($A24,ref_indicateurs!$A:$A,0)))) | G24: =IF($A24="","",SUMIFS(saisie_hebdo!$L:$L,saisie_hebdo!$I:$I,$A24)) | H24: =IF($A24="","",SUMIFS(saisie_hebdo!$M:$M,saisie_hebdo!$I:$I,$A24)) | I24: =IF(OR($A24="",L24=0),"",IF(D24="Pourcentage",IF(H24>0,G24/H24*100,""),G24)) | J24: =IF(OR(I24="",F24="",F24=0),"",I24/F24) | K24: =IF(OR($A24="",L24=0),"",IF(_xlfn.MAXIFS(saisie_hebdo!$C:$C,saisie_hebdo!$I:$I,$A24)=0,"",_xlfn.MAXIFS(saisie_hebdo!$C:$C,saisie_hebdo!$I:$I,$A24))) | L24: =IF($A24="","",COUNTIFS(saisie_hebdo!$I:$I,$A24)) | M24: =IF($A24="","",IF(L24=0,"Non rapporté",IF(F24="","Suivi sans cible",IF(D24="Pourcentage",IF(I24>=F24,"Cible atteinte","Sous la cible"),IF(J24>=1,"Cible atteinte","En cours")))))
A25: =IFERROR(INDEX(ref_indicateurs!$A:$A,22)&"","") | B25: =IF($A25="","",INDEX(ref_indicateurs!$B:$B,MATCH($A25,ref_indicateurs!$A:$A,0))&"") | C25: =IF($A25="","",INDEX(ref_indicateurs!$C:$C,MATCH($A25,ref_indicateurs!$A:$A,0))&"") | D25: =IF($A25="","",INDEX(ref_indicateurs!$E:$E,MATCH($A25,ref_indicateurs!$A:$A,0))&"") | E25: =IF($A25="","",INDEX(ref_indicateurs!$M:$M,MATCH($A25,ref_indicateurs!$A:$A,0))&"") | F25: =IF($A25="","",IF(INDEX(ref_indicateurs!$O:$O,MATCH($A25,ref_indicateurs!$A:$A,0))="","",INDEX(ref_indicateurs!$O:$O,MATCH($A25,ref_indicateurs!$A:$A,0)))) | G25: =IF($A25="","",SUMIFS(saisie_hebdo!$L:$L,saisie_hebdo!$I:$I,$A25)) | H25: =IF($A25="","",SUMIFS(saisie_hebdo!$M:$M,saisie_hebdo!$I:$I,$A25)) | I25: =IF(OR($A25="",L25=0),"",IF(D25="Pourcentage",IF(H25>0,G25/H25*100,""),G25)) | J25: =IF(OR(I25="",F25="",F25=0),"",I25/F25) | K25: =IF(OR($A25="",L25=0),"",IF(_xlfn.MAXIFS(saisie_hebdo!$C:$C,saisie_hebdo!$I:$I,$A25)=0,"",_xlfn.MAXIFS(saisie_hebdo!$C:$C,saisie_hebdo!$I:$I,$A25))) | L25: =IF($A25="","",COUNTIFS(saisie_hebdo!$I:$I,$A25)) | M25: =IF($A25="","",IF(L25=0,"Non rapporté",IF(F25="","Suivi sans cible",IF(D25="Pourcentage",IF(I25>=F25,"Cible atteinte","Sous la cible"),IF(J25>=1,"Cible atteinte","En cours")))))
A26: =IFERROR(INDEX(ref_indicateurs!$A:$A,23)&"","") | B26: =IF($A26="","",INDEX(ref_indicateurs!$B:$B,MATCH($A26,ref_indicateurs!$A:$A,0))&"") | C26: =IF($A26="","",INDEX(ref_indicateurs!$C:$C,MATCH($A26,ref_indicateurs!$A:$A,0))&"") | D26: =IF($A26="","",INDEX(ref_indicateurs!$E:$E,MATCH($A26,ref_indicateurs!$A:$A,0))&"") | E26: =IF($A26="","",INDEX(ref_indicateurs!$M:$M,MATCH($A26,ref_indicateurs!$A:$A,0))&"") | F26: =IF($A26="","",IF(INDEX(ref_indicateurs!$O:$O,MATCH($A26,ref_indicateurs!$A:$A,0))="","",INDEX(ref_indicateurs!$O:$O,MATCH($A26,ref_indicateurs!$A:$A,0)))) | G26: =IF($A26="","",SUMIFS(saisie_hebdo!$L:$L,saisie_hebdo!$I:$I,$A26)) | H26: =IF($A26="","",SUMIFS(saisie_hebdo!$M:$M,saisie_hebdo!$I:$I,$A26)) | I26: =IF(OR($A26="",L26=0),"",IF(D26="Pourcentage",IF(H26>0,G26/H26*100,""),G26)) | J26: =IF(OR(I26="",F26="",F26=0),"",I26/F26) | K26: =IF(OR($A26="",L26=0),"",IF(_xlfn.MAXIFS(saisie_hebdo!$C:$C,saisie_hebdo!$I:$I,$A26)=0,"",_xlfn.MAXIFS(saisie_hebdo!$C:$C,saisie_hebdo!$I:$I,$A26))) | L26: =IF($A26="","",COUNTIFS(saisie_hebdo!$I:$I,$A26)) | M26: =IF($A26="","",IF(L26=0,"Non rapporté",IF(F26="","Suivi sans cible",IF(D26="Pourcentage",IF(I26>=F26,"Cible atteinte","Sous la cible"),IF(J26>=1,"Cible atteinte","En cours")))))
A27: =IFERROR(INDEX(ref_indicateurs!$A:$A,24)&"","") | B27: =IF($A27="","",INDEX(ref_indicateurs!$B:$B,MATCH($A27,ref_indicateurs!$A:$A,0))&"") | C27: =IF($A27="","",INDEX(ref_indicateurs!$C:$C,MATCH($A27,ref_indicateurs!$A:$A,0))&"") | D27: =IF($A27="","",INDEX(ref_indicateurs!$E:$E,MATCH($A27,ref_indicateurs!$A:$A,0))&"") | E27: =IF($A27="","",INDEX(ref_indicateurs!$M:$M,MATCH($A27,ref_indicateurs!$A:$A,0))&"") | F27: =IF($A27="","",IF(INDEX(ref_indicateurs!$O:$O,MATCH($A27,ref_indicateurs!$A:$A,0))="","",INDEX(ref_indicateurs!$O:$O,MATCH($A27,ref_indicateurs!$A:$A,0)))) | G27: =IF($A27="","",SUMIFS(saisie_hebdo!$L:$L,saisie_hebdo!$I:$I,$A27)) | H27: =IF($A27="","",SUMIFS(saisie_hebdo!$M:$M,saisie_hebdo!$I:$I,$A27)) | I27: =IF(OR($A27="",L27=0),"",IF(D27="Pourcentage",IF(H27>0,G27/H27*100,""),G27)) | J27: =IF(OR(I27="",F27="",F27=0),"",I27/F27) | K27: =IF(OR($A27="",L27=0),"",IF(_xlfn.MAXIFS(saisie_hebdo!$C:$C,saisie_hebdo!$I:$I,$A27)=0,"",_xlfn.MAXIFS(saisie_hebdo!$C:$C,saisie_hebdo!$I:$I,$A27))) | L27: =IF($A27="","",COUNTIFS(saisie_hebdo!$I:$I,$A27)) | M27: =IF($A27="","",IF(L27=0,"Non rapporté",IF(F27="","Suivi sans cible",IF(D27="Pourcentage",IF(I27>=F27,"Cible atteinte","Sous la cible"),IF(J27>=1,"Cible atteinte","En cours")))))
A28: =IFERROR(INDEX(ref_indicateurs!$A:$A,25)&"","") | B28: =IF($A28="","",INDEX(ref_indicateurs!$B:$B,MATCH($A28,ref_indicateurs!$A:$A,0))&"") | C28: =IF($A28="","",INDEX(ref_indicateurs!$C:$C,MATCH($A28,ref_indicateurs!$A:$A,0))&"") | D28: =IF($A28="","",INDEX(ref_indicateurs!$E:$E,MATCH($A28,ref_indicateurs!$A:$A,0))&"") | E28: =IF($A28="","",INDEX(ref_indicateurs!$M:$M,MATCH($A28,ref_indicateurs!$A:$A,0))&"") | F28: =IF($A28="","",IF(INDEX(ref_indicateurs!$O:$O,MATCH($A28,ref_indicateurs!$A:$A,0))="","",INDEX(ref_indicateurs!$O:$O,MATCH($A28,ref_indicateurs!$A:$A,0)))) | G28: =IF($A28="","",SUMIFS(saisie_hebdo!$L:$L,saisie_hebdo!$I:$I,$A28)) | H28: =IF($A28="","",SUMIFS(saisie_hebdo!$M:$M,saisie_hebdo!$I:$I,$A28)) | I28: =IF(OR($A28="",L28=0),"",IF(D28="Pourcentage",IF(H28>0,G28/H28*100,""),G28)) | J28: =IF(OR(I28="",F28="",F28=0),"",I28/F28) | K28: =IF(OR($A28="",L28=0),"",IF(_xlfn.MAXIFS(saisie_hebdo!$C:$C,saisie_hebdo!$I:$I,$A28)=0,"",_xlfn.MAXIFS(saisie_hebdo!$C:$C,saisie_hebdo!$I:$I,$A28))) | L28: =IF($A28="","",COUNTIFS(saisie_hebdo!$I:$I,$A28)) | M28: =IF($A28="","",IF(L28=0,"Non rapporté",IF(F28="","Suivi sans cible",IF(D28="Pourcentage",IF(I28>=F28,"Cible atteinte","Sous la cible"),IF(J28>=1,"Cible atteinte","En cours")))))
A29: =IFERROR(INDEX(ref_indicateurs!$A:$A,26)&"","") | B29: =IF($A29="","",INDEX(ref_indicateurs!$B:$B,MATCH($A29,ref_indicateurs!$A:$A,0))&"") | C29: =IF($A29="","",INDEX(ref_indicateurs!$C:$C,MATCH($A29,ref_indicateurs!$A:$A,0))&"") | D29: =IF($A29="","",INDEX(ref_indicateurs!$E:$E,MATCH($A29,ref_indicateurs!$A:$A,0))&"") | E29: =IF($A29="","",INDEX(ref_indicateurs!$M:$M,MATCH($A29,ref_indicateurs!$A:$A,0))&"") | F29: =IF($A29="","",IF(INDEX(ref_indicateurs!$O:$O,MATCH($A29,ref_indicateurs!$A:$A,0))="","",INDEX(ref_indicateurs!$O:$O,MATCH($A29,ref_indicateurs!$A:$A,0)))) | G29: =IF($A29="","",SUMIFS(saisie_hebdo!$L:$L,saisie_hebdo!$I:$I,$A29)) | H29: =IF($A29="","",SUMIFS(saisie_hebdo!$M:$M,saisie_hebdo!$I:$I,$A29)) | I29: =IF(OR($A29="",L29=0),"",IF(D29="Pourcentage",IF(H29>0,G29/H29*100,""),G29)) | J29: =IF(OR(I29="",F29="",F29=0),"",I29/F29) | K29: =IF(OR($A29="",L29=0),"",IF(_xlfn.MAXIFS(saisie_hebdo!$C:$C,saisie_hebdo!$I:$I,$A29)=0,"",_xlfn.MAXIFS(saisie_hebdo!$C:$C,saisie_hebdo!$I:$I,$A29))) | L29: =IF($A29="","",COUNTIFS(saisie_hebdo!$I:$I,$A29)) | M29: =IF($A29="","",IF(L29=0,"Non rapporté",IF(F29="","Suivi sans cible",IF(D29="Pourcentage",IF(I29>=F29,"Cible atteinte","Sous la cible"),IF(J29>=1,"Cible atteinte","En cours")))))
A30: =IFERROR(INDEX(ref_indicateurs!$A:$A,27)&"","") | B30: =IF($A30="","",INDEX(ref_indicateurs!$B:$B,MATCH($A30,ref_indicateurs!$A:$A,0))&"") | C30: =IF($A30="","",INDEX(ref_indicateurs!$C:$C,MATCH($A30,ref_indicateurs!$A:$A,0))&"") | D30: =IF($A30="","",INDEX(ref_indicateurs!$E:$E,MATCH($A30,ref_indicateurs!$A:$A,0))&"") | E30: =IF($A30="","",INDEX(ref_indicateurs!$M:$M,MATCH($A30,ref_indicateurs!$A:$A,0))&"") | F30: =IF($A30="","",IF(INDEX(ref_indicateurs!$O:$O,MATCH($A30,ref_indicateurs!$A:$A,0))="","",INDEX(ref_indicateurs!$O:$O,MATCH($A30,ref_indicateurs!$A:$A,0)))) | G30: =IF($A30="","",SUMIFS(saisie_hebdo!$L:$L,saisie_hebdo!$I:$I,$A30)) | H30: =IF($A30="","",SUMIFS(saisie_hebdo!$M:$M,saisie_hebdo!$I:$I,$A30)) | I30: =IF(OR($A30="",L30=0),"",IF(D30="Pourcentage",IF(H30>0,G30/H30*100,""),G30)) | J30: =IF(OR(I30="",F30="",F30=0),"",I30/F30) | K30: =IF(OR($A30="",L30=0),"",IF(_xlfn.MAXIFS(saisie_hebdo!$C:$C,saisie_hebdo!$I:$I,$A30)=0,"",_xlfn.MAXIFS(saisie_hebdo!$C:$C,saisie_hebdo!$I:$I,$A30))) | L30: =IF($A30="","",COUNTIFS(saisie_hebdo!$I:$I,$A30)) | M30: =IF($A30="","",IF(L30=0,"Non rapporté",IF(F30="","Suivi sans cible",IF(D30="Pourcentage",IF(I30>=F30,"Cible atteinte","Sous la cible"),IF(J30>=1,"Cible atteinte","En cours")))))
A31: =IFERROR(INDEX(ref_indicateurs!$A:$A,28)&"","") | B31: =IF($A31="","",INDEX(ref_indicateurs!$B:$B,MATCH($A31,ref_indicateurs!$A:$A,0))&"") | C31: =IF($A31="","",INDEX(ref_indicateurs!$C:$C,MATCH($A31,ref_indicateurs!$A:$A,0))&"") | D31: =IF($A31="","",INDEX(ref_indicateurs!$E:$E,MATCH($A31,ref_indicateurs!$A:$A,0))&"") | E31: =IF($A31="","",INDEX(ref_indicateurs!$M:$M,MATCH($A31,ref_indicateurs!$A:$A,0))&"") | F31: =IF($A31="","",IF(INDEX(ref_indicateurs!$O:$O,MATCH($A31,ref_indicateurs!$A:$A,0))="","",INDEX(ref_indicateurs!$O:$O,MATCH($A31,ref_indicateurs!$A:$A,0)))) | G31: =IF($A31="","",SUMIFS(saisie_hebdo!$L:$L,saisie_hebdo!$I:$I,$A31)) | H31: =IF($A31="","",SUMIFS(saisie_hebdo!$M:$M,saisie_hebdo!$I:$I,$A31)) | I31: =IF(OR($A31="",L31=0),"",IF(D31="Pourcentage",IF(H31>0,G31/H31*100,""),G31)) | J31: =IF(OR(I31="",F31="",F31=0),"",I31/F31) | K31: =IF(OR($A31="",L31=0),"",IF(_xlfn.MAXIFS(saisie_hebdo!$C:$C,saisie_hebdo!$I:$I,$A31)=0,"",_xlfn.MAXIFS(saisie_hebdo!$C:$C,saisie_hebdo!$I:$I,$A31))) | L31: =IF($A31="","",COUNTIFS(saisie_hebdo!$I:$I,$A31)) | M31: =IF($A31="","",IF(L31=0,"Non rapporté",IF(F31="","Suivi sans cible",IF(D31="Pourcentage",IF(I31>=F31,"Cible atteinte","Sous la cible"),IF(J31>=1,"Cible atteinte","En cours")))))
A32: =IFERROR(INDEX(ref_indicateurs!$A:$A,29)&"","") | B32: =IF($A32="","",INDEX(ref_indicateurs!$B:$B,MATCH($A32,ref_indicateurs!$A:$A,0))&"") | C32: =IF($A32="","",INDEX(ref_indicateurs!$C:$C,MATCH($A32,ref_indicateurs!$A:$A,0))&"") | D32: =IF($A32="","",INDEX(ref_indicateurs!$E:$E,MATCH($A32,ref_indicateurs!$A:$A,0))&"") | E32: =IF($A32="","",INDEX(ref_indicateurs!$M:$M,MATCH($A32,ref_indicateurs!$A:$A,0))&"") | F32: =IF($A32="","",IF(INDEX(ref_indicateurs!$O:$O,MATCH($A32,ref_indicateurs!$A:$A,0))="","",INDEX(ref_indicateurs!$O:$O,MATCH($A32,ref_indicateurs!$A:$A,0)))) | G32: =IF($A32="","",SUMIFS(saisie_hebdo!$L:$L,saisie_hebdo!$I:$I,$A32)) | H32: =IF($A32="","",SUMIFS(saisie_hebdo!$M:$M,saisie_hebdo!$I:$I,$A32)) | I32: =IF(OR($A32="",L32=0),"",IF(D32="Pourcentage",IF(H32>0,G32/H32*100,""),G32)) | J32: =IF(OR(I32="",F32="",F32=0),"",I32/F32) | K32: =IF(OR($A32="",L32=0),"",IF(_xlfn.MAXIFS(saisie_hebdo!$C:$C,saisie_hebdo!$I:$I,$A32)=0,"",_xlfn.MAXIFS(saisie_hebdo!$C:$C,saisie_hebdo!$I:$I,$A32))) | L32: =IF($A32="","",COUNTIFS(saisie_hebdo!$I:$I,$A32)) | M32: =IF($A32="","",IF(L32=0,"Non rapporté",IF(F32="","Suivi sans cible",IF(D32="Pourcentage",IF(I32>=F32,"Cible atteinte","Sous la cible"),IF(J32>=1,"Cible atteinte","En cours")))))
A33: =IFERROR(INDEX(ref_indicateurs!$A:$A,30)&"","") | B33: =IF($A33="","",INDEX(ref_indicateurs!$B:$B,MATCH($A33,ref_indicateurs!$A:$A,0))&"") | C33: =IF($A33="","",INDEX(ref_indicateurs!$C:$C,MATCH($A33,ref_indicateurs!$A:$A,0))&"") | D33: =IF($A33="","",INDEX(ref_indicateurs!$E:$E,MATCH($A33,ref_indicateurs!$A:$A,0))&"") | E33: =IF($A33="","",INDEX(ref_indicateurs!$M:$M,MATCH($A33,ref_indicateurs!$A:$A,0))&"") | F33: =IF($A33="","",IF(INDEX(ref_indicateurs!$O:$O,MATCH($A33,ref_indicateurs!$A:$A,0))="","",INDEX(ref_indicateurs!$O:$O,MATCH($A33,ref_indicateurs!$A:$A,0)))) | G33: =IF($A33="","",SUMIFS(saisie_hebdo!$L:$L,saisie_hebdo!$I:$I,$A33)) | H33: =IF($A33="","",SUMIFS(saisie_hebdo!$M:$M,saisie_hebdo!$I:$I,$A33)) | I33: =IF(OR($A33="",L33=0),"",IF(D33="Pourcentage",IF(H33>0,G33/H33*100,""),G33)) | J33: =IF(OR(I33="",F33="",F33=0),"",I33/F33) | K33: =IF(OR($A33="",L33=0),"",IF(_xlfn.MAXIFS(saisie_hebdo!$C:$C,saisie_hebdo!$I:$I,$A33)=0,"",_xlfn.MAXIFS(saisie_hebdo!$C:$C,saisie_hebdo!$I:$I,$A33))) | L33: =IF($A33="","",COUNTIFS(saisie_hebdo!$I:$I,$A33)) | M33: =IF($A33="","",IF(L33=0,"Non rapporté",IF(F33="","Suivi sans cible",IF(D33="Pourcentage",IF(I33>=F33,"Cible atteinte","Sous la cible"),IF(J33>=1,"Cible atteinte","En cours")))))
A34: =IFERROR(INDEX(ref_indicateurs!$A:$A,31)&"","") | B34: =IF($A34="","",INDEX(ref_indicateurs!$B:$B,MATCH($A34,ref_indicateurs!$A:$A,0))&"") | C34: =IF($A34="","",INDEX(ref_indicateurs!$C:$C,MATCH($A34,ref_indicateurs!$A:$A,0))&"") | D34: =IF($A34="","",INDEX(ref_indicateurs!$E:$E,MATCH($A34,ref_indicateurs!$A:$A,0))&"") | E34: =IF($A34="","",INDEX(ref_indicateurs!$M:$M,MATCH($A34,ref_indicateurs!$A:$A,0))&"") | F34: =IF($A34="","",IF(INDEX(ref_indicateurs!$O:$O,MATCH($A34,ref_indicateurs!$A:$A,0))="","",INDEX(ref_indicateurs!$O:$O,MATCH($A34,ref_indicateurs!$A:$A,0)))) | G34: =IF($A34="","",SUMIFS(saisie_hebdo!$L:$L,saisie_hebdo!$I:$I,$A34)) | H34: =IF($A34="","",SUMIFS(saisie_hebdo!$M:$M,saisie_hebdo!$I:$I,$A34)) | I34: =IF(OR($A34="",L34=0),"",IF(D34="Pourcentage",IF(H34>0,G34/H34*100,""),G34)) | J34: =IF(OR(I34="",F34="",F34=0),"",I34/F34) | K34: =IF(OR($A34="",L34=0),"",IF(_xlfn.MAXIFS(saisie_hebdo!$C:$C,saisie_hebdo!$I:$I,$A34)=0,"",_xlfn.MAXIFS(saisie_hebdo!$C:$C,saisie_hebdo!$I:$I,$A34))) | L34: =IF($A34="","",COUNTIFS(saisie_hebdo!$I:$I,$A34)) | M34: =IF($A34="","",IF(L34=0,"Non rapporté",IF(F34="","Suivi sans cible",IF(D34="Pourcentage",IF(I34>=F34,"Cible atteinte","Sous la cible"),IF(J34>=1,"Cible atteinte","En cours")))))
A35: =IFERROR(INDEX(ref_indicateurs!$A:$A,32)&"","") | B35: =IF($A35="","",INDEX(ref_indicateurs!$B:$B,MATCH($A35,ref_indicateurs!$A:$A,0))&"") | C35: =IF($A35="","",INDEX(ref_indicateurs!$C:$C,MATCH($A35,ref_indicateurs!$A:$A,0))&"") | D35: =IF($A35="","",INDEX(ref_indicateurs!$E:$E,MATCH($A35,ref_indicateurs!$A:$A,0))&"") | E35: =IF($A35="","",INDEX(ref_indicateurs!$M:$M,MATCH($A35,ref_indicateurs!$A:$A,0))&"") | F35: =IF($A35="","",IF(INDEX(ref_indicateurs!$O:$O,MATCH($A35,ref_indicateurs!$A:$A,0))="","",INDEX(ref_indicateurs!$O:$O,MATCH($A35,ref_indicateurs!$A:$A,0)))) | G35: =IF($A35="","",SUMIFS(saisie_hebdo!$L:$L,saisie_hebdo!$I:$I,$A35)) | H35: =IF($A35="","",SUMIFS(saisie_hebdo!$M:$M,saisie_hebdo!$I:$I,$A35)) | I35: =IF(OR($A35="",L35=0),"",IF(D35="Pourcentage",IF(H35>0,G35/H35*100,""),G35)) | J35: =IF(OR(I35="",F35="",F35=0),"",I35/F35) | K35: =IF(OR($A35="",L35=0),"",IF(_xlfn.MAXIFS(saisie_hebdo!$C:$C,saisie_hebdo!$I:$I,$A35)=0,"",_xlfn.MAXIFS(saisie_hebdo!$C:$C,saisie_hebdo!$I:$I,$A35))) | L35: =IF($A35="","",COUNTIFS(saisie_hebdo!$I:$I,$A35)) | M35: =IF($A35="","",IF(L35=0,"Non rapporté",IF(F35="","Suivi sans cible",IF(D35="Pourcentage",IF(I35>=F35,"Cible atteinte","Sous la cible"),IF(J35>=1,"Cible atteinte","En cours")))))
A36: =IFERROR(INDEX(ref_indicateurs!$A:$A,33)&"","") | B36: =IF($A36="","",INDEX(ref_indicateurs!$B:$B,MATCH($A36,ref_indicateurs!$A:$A,0))&"") | C36: =IF($A36="","",INDEX(ref_indicateurs!$C:$C,MATCH($A36,ref_indicateurs!$A:$A,0))&"") | D36: =IF($A36="","",INDEX(ref_indicateurs!$E:$E,MATCH($A36,ref_indicateurs!$A:$A,0))&"") | E36: =IF($A36="","",INDEX(ref_indicateurs!$M:$M,MATCH($A36,ref_indicateurs!$A:$A,0))&"") | F36: =IF($A36="","",IF(INDEX(ref_indicateurs!$O:$O,MATCH($A36,ref_indicateurs!$A:$A,0))="","",INDEX(ref_indicateurs!$O:$O,MATCH($A36,ref_indicateurs!$A:$A,0)))) | G36: =IF($A36="","",SUMIFS(saisie_hebdo!$L:$L,saisie_hebdo!$I:$I,$A36)) | H36: =IF($A36="","",SUMIFS(saisie_hebdo!$M:$M,saisie_hebdo!$I:$I,$A36)) | I36: =IF(OR($A36="",L36=0),"",IF(D36="Pourcentage",IF(H36>0,G36/H36*100,""),G36)) | J36: =IF(OR(I36="",F36="",F36=0),"",I36/F36) | K36: =IF(OR($A36="",L36=0),"",IF(_xlfn.MAXIFS(saisie_hebdo!$C:$C,saisie_hebdo!$I:$I,$A36)=0,"",_xlfn.MAXIFS(saisie_hebdo!$C:$C,saisie_hebdo!$I:$I,$A36))) | L36: =IF($A36="","",COUNTIFS(saisie_hebdo!$I:$I,$A36)) | M36: =IF($A36="","",IF(L36=0,"Non rapporté",IF(F36="","Suivi sans cible",IF(D36="Pourcentage",IF(I36>=F36,"Cible atteinte","Sous la cible"),IF(J36>=1,"Cible atteinte","En cours")))))
A37: =IFERROR(INDEX(ref_indicateurs!$A:$A,34)&"","") | B37: =IF($A37="","",INDEX(ref_indicateurs!$B:$B,MATCH($A37,ref_indicateurs!$A:$A,0))&"") | C37: =IF($A37="","",INDEX(ref_indicateurs!$C:$C,MATCH($A37,ref_indicateurs!$A:$A,0))&"") | D37: =IF($A37="","",INDEX(ref_indicateurs!$E:$E,MATCH($A37,ref_indicateurs!$A:$A,0))&"") | E37: =IF($A37="","",INDEX(ref_indicateurs!$M:$M,MATCH($A37,ref_indicateurs!$A:$A,0))&"") | F37: =IF($A37="","",IF(INDEX(ref_indicateurs!$O:$O,MATCH($A37,ref_indicateurs!$A:$A,0))="","",INDEX(ref_indicateurs!$O:$O,MATCH($A37,ref_indicateurs!$A:$A,0)))) | G37: =IF($A37="","",SUMIFS(saisie_hebdo!$L:$L,saisie_hebdo!$I:$I,$A37)) | H37: =IF($A37="","",SUMIFS(saisie_hebdo!$M:$M,saisie_hebdo!$I:$I,$A37)) | I37: =IF(OR($A37="",L37=0),"",IF(D37="Pourcentage",IF(H37>0,G37/H37*100,""),G37)) | J37: =IF(OR(I37="",F37="",F37=0),"",I37/F37) | K37: =IF(OR($A37="",L37=0),"",IF(_xlfn.MAXIFS(saisie_hebdo!$C:$C,saisie_hebdo!$I:$I,$A37)=0,"",_xlfn.MAXIFS(saisie_hebdo!$C:$C,saisie_hebdo!$I:$I,$A37))) | L37: =IF($A37="","",COUNTIFS(saisie_hebdo!$I:$I,$A37)) | M37: =IF($A37="","",IF(L37=0,"Non rapporté",IF(F37="","Suivi sans cible",IF(D37="Pourcentage",IF(I37>=F37,"Cible atteinte","Sous la cible"),IF(J37>=1,"Cible atteinte","En cours")))))
A38: =IFERROR(INDEX(ref_indicateurs!$A:$A,35)&"","") | B38: =IF($A38="","",INDEX(ref_indicateurs!$B:$B,MATCH($A38,ref_indicateurs!$A:$A,0))&"") | C38: =IF($A38="","",INDEX(ref_indicateurs!$C:$C,MATCH($A38,ref_indicateurs!$A:$A,0))&"") | D38: =IF($A38="","",INDEX(ref_indicateurs!$E:$E,MATCH($A38,ref_indicateurs!$A:$A,0))&"") | E38: =IF($A38="","",INDEX(ref_indicateurs!$M:$M,MATCH($A38,ref_indicateurs!$A:$A,0))&"") | F38: =IF($A38="","",IF(INDEX(ref_indicateurs!$O:$O,MATCH($A38,ref_indicateurs!$A:$A,0))="","",INDEX(ref_indicateurs!$O:$O,MATCH($A38,ref_indicateurs!$A:$A,0)))) | G38: =IF($A38="","",SUMIFS(saisie_hebdo!$L:$L,saisie_hebdo!$I:$I,$A38)) | H38: =IF($A38="","",SUMIFS(saisie_hebdo!$M:$M,saisie_hebdo!$I:$I,$A38)) | I38: =IF(OR($A38="",L38=0),"",IF(D38="Pourcentage",IF(H38>0,G38/H38*100,""),G38)) | J38: =IF(OR(I38="",F38="",F38=0),"",I38/F38) | K38: =IF(OR($A38="",L38=0),"",IF(_xlfn.MAXIFS(saisie_hebdo!$C:$C,saisie_hebdo!$I:$I,$A38)=0,"",_xlfn.MAXIFS(saisie_hebdo!$C:$C,saisie_hebdo!$I:$I,$A38))) | L38: =IF($A38="","",COUNTIFS(saisie_hebdo!$I:$I,$A38)) | M38: =IF($A38="","",IF(L38=0,"Non rapporté",IF(F38="","Suivi sans cible",IF(D38="Pourcentage",IF(I38>=F38,"Cible atteinte","Sous la cible"),IF(J38>=1,"Cible atteinte","En cours")))))
A39: =IFERROR(INDEX(ref_indicateurs!$A:$A,36)&"","") | B39: =IF($A39="","",INDEX(ref_indicateurs!$B:$B,MATCH($A39,ref_indicateurs!$A:$A,0))&"") | C39: =IF($A39="","",INDEX(ref_indicateurs!$C:$C,MATCH($A39,ref_indicateurs!$A:$A,0))&"") | D39: =IF($A39="","",INDEX(ref_indicateurs!$E:$E,MATCH($A39,ref_indicateurs!$A:$A,0))&"") | E39: =IF($A39="","",INDEX(ref_indicateurs!$M:$M,MATCH($A39,ref_indicateurs!$A:$A,0))&"") | F39: =IF($A39="","",IF(INDEX(ref_indicateurs!$O:$O,MATCH($A39,ref_indicateurs!$A:$A,0))="","",INDEX(ref_indicateurs!$O:$O,MATCH($A39,ref_indicateurs!$A:$A,0)))) | G39: =IF($A39="","",SUMIFS(saisie_hebdo!$L:$L,saisie_hebdo!$I:$I,$A39)) | H39: =IF($A39="","",SUMIFS(saisie_hebdo!$M:$M,saisie_hebdo!$I:$I,$A39)) | I39: =IF(OR($A39="",L39=0),"",IF(D39="Pourcentage",IF(H39>0,G39/H39*100,""),G39)) | J39: =IF(OR(I39="",F39="",F39=0),"",I39/F39) | K39: =IF(OR($A39="",L39=0),"",IF(_xlfn.MAXIFS(saisie_hebdo!$C:$C,saisie_hebdo!$I:$I,$A39)=0,"",_xlfn.MAXIFS(saisie_hebdo!$C:$C,saisie_hebdo!$I:$I,$A39))) | L39: =IF($A39="","",COUNTIFS(saisie_hebdo!$I:$I,$A39)) | M39: =IF($A39="","",IF(L39=0,"Non rapporté",IF(F39="","Suivi sans cible",IF(D39="Pourcentage",IF(I39>=F39,"Cible atteinte","Sous la cible"),IF(J39>=1,"Cible atteinte","En cours")))))
A40: =IFERROR(INDEX(ref_indicateurs!$A:$A,37)&"","") | B40: =IF($A40="","",INDEX(ref_indicateurs!$B:$B,MATCH($A40,ref_indicateurs!$A:$A,0))&"") | C40: =IF($A40="","",INDEX(ref_indicateurs!$C:$C,MATCH($A40,ref_indicateurs!$A:$A,0))&"") | D40: =IF($A40="","",INDEX(ref_indicateurs!$E:$E,MATCH($A40,ref_indicateurs!$A:$A,0))&"") | E40: =IF($A40="","",INDEX(ref_indicateurs!$M:$M,MATCH($A40,ref_indicateurs!$A:$A,0))&"") | F40: =IF($A40="","",IF(INDEX(ref_indicateurs!$O:$O,MATCH($A40,ref_indicateurs!$A:$A,0))="","",INDEX(ref_indicateurs!$O:$O,MATCH($A40,ref_indicateurs!$A:$A,0)))) | G40: =IF($A40="","",SUMIFS(saisie_hebdo!$L:$L,saisie_hebdo!$I:$I,$A40)) | H40: =IF($A40="","",SUMIFS(saisie_hebdo!$M:$M,saisie_hebdo!$I:$I,$A40)) | I40: =IF(OR($A40="",L40=0),"",IF(D40="Pourcentage",IF(H40>0,G40/H40*100,""),G40)) | J40: =IF(OR(I40="",F40="",F40=0),"",I40/F40) | K40: =IF(OR($A40="",L40=0),"",IF(_xlfn.MAXIFS(saisie_hebdo!$C:$C,saisie_hebdo!$I:$I,$A40)=0,"",_xlfn.MAXIFS(saisie_hebdo!$C:$C,saisie_hebdo!$I:$I,$A40))) | L40: =IF($A40="","",COUNTIFS(saisie_hebdo!$I:$I,$A40)) | M40: =IF($A40="","",IF(L40=0,"Non rapporté",IF(F40="","Suivi sans cible",IF(D40="Pourcentage",IF(I40>=F40,"Cible atteinte","Sous la cible"),IF(J40>=1,"Cible atteinte","En cours")))))
A41: =IFERROR(INDEX(ref_indicateurs!$A:$A,38)&"","") | B41: =IF($A41="","",INDEX(ref_indicateurs!$B:$B,MATCH($A41,ref_indicateurs!$A:$A,0))&"") | C41: =IF($A41="","",INDEX(ref_indicateurs!$C:$C,MATCH($A41,ref_indicateurs!$A:$A,0))&"") | D41: =IF($A41="","",INDEX(ref_indicateurs!$E:$E,MATCH($A41,ref_indicateurs!$A:$A,0))&"") | E41: =IF($A41="","",INDEX(ref_indicateurs!$M:$M,MATCH($A41,ref_indicateurs!$A:$A,0))&"") | F41: =IF($A41="","",IF(INDEX(ref_indicateurs!$O:$O,MATCH($A41,ref_indicateurs!$A:$A,0))="","",INDEX(ref_indicateurs!$O:$O,MATCH($A41,ref_indicateurs!$A:$A,0)))) | G41: =IF($A41="","",SUMIFS(saisie_hebdo!$L:$L,saisie_hebdo!$I:$I,$A41)) | H41: =IF($A41="","",SUMIFS(saisie_hebdo!$M:$M,saisie_hebdo!$I:$I,$A41)) | I41: =IF(OR($A41="",L41=0),"",IF(D41="Pourcentage",IF(H41>0,G41/H41*100,""),G41)) | J41: =IF(OR(I41="",F41="",F41=0),"",I41/F41) | K41: =IF(OR($A41="",L41=0),"",IF(_xlfn.MAXIFS(saisie_hebdo!$C:$C,saisie_hebdo!$I:$I,$A41)=0,"",_xlfn.MAXIFS(saisie_hebdo!$C:$C,saisie_hebdo!$I:$I,$A41))) | L41: =IF($A41="","",COUNTIFS(saisie_hebdo!$I:$I,$A41)) | M41: =IF($A41="","",IF(L41=0,"Non rapporté",IF(F41="","Suivi sans cible",IF(D41="Pourcentage",IF(I41>=F41,"Cible atteinte","Sous la cible"),IF(J41>=1,"Cible atteinte","En cours")))))
A42: =IFERROR(INDEX(ref_indicateurs!$A:$A,39)&"","") | B42: =IF($A42="","",INDEX(ref_indicateurs!$B:$B,MATCH($A42,ref_indicateurs!$A:$A,0))&"") | C42: =IF($A42="","",INDEX(ref_indicateurs!$C:$C,MATCH($A42,ref_indicateurs!$A:$A,0))&"") | D42: =IF($A42="","",INDEX(ref_indicateurs!$E:$E,MATCH($A42,ref_indicateurs!$A:$A,0))&"") | E42: =IF($A42="","",INDEX(ref_indicateurs!$M:$M,MATCH($A42,ref_indicateurs!$A:$A,0))&"") | F42: =IF($A42="","",IF(INDEX(ref_indicateurs!$O:$O,MATCH($A42,ref_indicateurs!$A:$A,0))="","",INDEX(ref_indicateurs!$O:$O,MATCH($A42,ref_indicateurs!$A:$A,0)))) | G42: =IF($A42="","",SUMIFS(saisie_hebdo!$L:$L,saisie_hebdo!$I:$I,$A42)) | H42: =IF($A42="","",SUMIFS(saisie_hebdo!$M:$M,saisie_hebdo!$I:$I,$A42)) | I42: =IF(OR($A42="",L42=0),"",IF(D42="Pourcentage",IF(H42>0,G42/H42*100,""),G42)) | J42: =IF(OR(I42="",F42="",F42=0),"",I42/F42) | K42: =IF(OR($A42="",L42=0),"",IF(_xlfn.MAXIFS(saisie_hebdo!$C:$C,saisie_hebdo!$I:$I,$A42)=0,"",_xlfn.MAXIFS(saisie_hebdo!$C:$C,saisie_hebdo!$I:$I,$A42))) | L42: =IF($A42="","",COUNTIFS(saisie_hebdo!$I:$I,$A42)) | M42: =IF($A42="","",IF(L42=0,"Non rapporté",IF(F42="","Suivi sans cible",IF(D42="Pourcentage",IF(I42>=F42,"Cible atteinte","Sous la cible"),IF(J42>=1,"Cible atteinte","En cours")))))
A43: =IFERROR(INDEX(ref_indicateurs!$A:$A,40)&"","") | B43: =IF($A43="","",INDEX(ref_indicateurs!$B:$B,MATCH($A43,ref_indicateurs!$A:$A,0))&"") | C43: =IF($A43="","",INDEX(ref_indicateurs!$C:$C,MATCH($A43,ref_indicateurs!$A:$A,0))&"") | D43: =IF($A43="","",INDEX(ref_indicateurs!$E:$E,MATCH($A43,ref_indicateurs!$A:$A,0))&"") | E43: =IF($A43="","",INDEX(ref_indicateurs!$M:$M,MATCH($A43,ref_indicateurs!$A:$A,0))&"") | F43: =IF($A43="","",IF(INDEX(ref_indicateurs!$O:$O,MATCH($A43,ref_indicateurs!$A:$A,0))="","",INDEX(ref_indicateurs!$O:$O,MATCH($A43,ref_indicateurs!$A:$A,0)))) | G43: =IF($A43="","",SUMIFS(saisie_hebdo!$L:$L,saisie_hebdo!$I:$I,$A43)) | H43: =IF($A43="","",SUMIFS(saisie_hebdo!$M:$M,saisie_hebdo!$I:$I,$A43)) | I43: =IF(OR($A43="",L43=0),"",IF(D43="Pourcentage",IF(H43>0,G43/H43*100,""),G43)) | J43: =IF(OR(I43="",F43="",F43=0),"",I43/F43) | K43: =IF(OR($A43="",L43=0),"",IF(_xlfn.MAXIFS(saisie_hebdo!$C:$C,saisie_hebdo!$I:$I,$A43)=0,"",_xlfn.MAXIFS(saisie_hebdo!$C:$C,saisie_hebdo!$I:$I,$A43))) | L43: =IF($A43="","",COUNTIFS(saisie_hebdo!$I:$I,$A43)) | M43: =IF($A43="","",IF(L43=0,"Non rapporté",IF(F43="","Suivi sans cible",IF(D43="Pourcentage",IF(I43>=F43,"Cible atteinte","Sous la cible"),IF(J43>=1,"Cible atteinte","En cours")))))
A44: =IFERROR(INDEX(ref_indicateurs!$A:$A,41)&"","") | B44: =IF($A44="","",INDEX(ref_indicateurs!$B:$B,MATCH($A44,ref_indicateurs!$A:$A,0))&"") | C44: =IF($A44="","",INDEX(ref_indicateurs!$C:$C,MATCH($A44,ref_indicateurs!$A:$A,0))&"") | D44: =IF($A44="","",INDEX(ref_indicateurs!$E:$E,MATCH($A44,ref_indicateurs!$A:$A,0))&"") | E44: =IF($A44="","",INDEX(ref_indicateurs!$M:$M,MATCH($A44,ref_indicateurs!$A:$A,0))&"") | F44: =IF($A44="","",IF(INDEX(ref_indicateurs!$O:$O,MATCH($A44,ref_indicateurs!$A:$A,0))="","",INDEX(ref_indicateurs!$O:$O,MATCH($A44,ref_indicateurs!$A:$A,0)))) | G44: =IF($A44="","",SUMIFS(saisie_hebdo!$L:$L,saisie_hebdo!$I:$I,$A44)) | H44: =IF($A44="","",SUMIFS(saisie_hebdo!$M:$M,saisie_hebdo!$I:$I,$A44)) | I44: =IF(OR($A44="",L44=0),"",IF(D44="Pourcentage",IF(H44>0,G44/H44*100,""),G44)) | J44: =IF(OR(I44="",F44="",F44=0),"",I44/F44) | K44: =IF(OR($A44="",L44=0),"",IF(_xlfn.MAXIFS(saisie_hebdo!$C:$C,saisie_hebdo!$I:$I,$A44)=0,"",_xlfn.MAXIFS(saisie_hebdo!$C:$C,saisie_hebdo!$I:$I,$A44))) | L44: =IF($A44="","",COUNTIFS(saisie_hebdo!$I:$I,$A44)) | M44: =IF($A44="","",IF(L44=0,"Non rapporté",IF(F44="","Suivi sans cible",IF(D44="Pourcentage",IF(I44>=F44,"Cible atteinte","Sous la cible"),IF(J44>=1,"Cible atteinte","En cours")))))
A45: =IFERROR(INDEX(ref_indicateurs!$A:$A,42)&"","") | B45: =IF($A45="","",INDEX(ref_indicateurs!$B:$B,MATCH($A45,ref_indicateurs!$A:$A,0))&"") | C45: =IF($A45="","",INDEX(ref_indicateurs!$C:$C,MATCH($A45,ref_indicateurs!$A:$A,0))&"") | D45: =IF($A45="","",INDEX(ref_indicateurs!$E:$E,MATCH($A45,ref_indicateurs!$A:$A,0))&"") | E45: =IF($A45="","",INDEX(ref_indicateurs!$M:$M,MATCH($A45,ref_indicateurs!$A:$A,0))&"") | F45: =IF($A45="","",IF(INDEX(ref_indicateurs!$O:$O,MATCH($A45,ref_indicateurs!$A:$A,0))="","",INDEX(ref_indicateurs!$O:$O,MATCH($A45,ref_indicateurs!$A:$A,0)))) | G45: =IF($A45="","",SUMIFS(saisie_hebdo!$L:$L,saisie_hebdo!$I:$I,$A45)) | H45: =IF($A45="","",SUMIFS(saisie_hebdo!$M:$M,saisie_hebdo!$I:$I,$A45)) | I45: =IF(OR($A45="",L45=0),"",IF(D45="Pourcentage",IF(H45>0,G45/H45*100,""),G45)) | J45: =IF(OR(I45="",F45="",F45=0),"",I45/F45) | K45: =IF(OR($A45="",L45=0),"",IF(_xlfn.MAXIFS(saisie_hebdo!$C:$C,saisie_hebdo!$I:$I,$A45)=0,"",_xlfn.MAXIFS(saisie_hebdo!$C:$C,saisie_hebdo!$I:$I,$A45))) | L45: =IF($A45="","",COUNTIFS(saisie_hebdo!$I:$I,$A45)) | M45: =IF($A45="","",IF(L45=0,"Non rapporté",IF(F45="","Suivi sans cible",IF(D45="Pourcentage",IF(I45>=F45,"Cible atteinte","Sous la cible"),IF(J45>=1,"Cible atteinte","En cours")))))
A46: =IFERROR(INDEX(ref_indicateurs!$A:$A,43)&"","") | B46: =IF($A46="","",INDEX(ref_indicateurs!$B:$B,MATCH($A46,ref_indicateurs!$A:$A,0))&"") | C46: =IF($A46="","",INDEX(ref_indicateurs!$C:$C,MATCH($A46,ref_indicateurs!$A:$A,0))&"") | D46: =IF($A46="","",INDEX(ref_indicateurs!$E:$E,MATCH($A46,ref_indicateurs!$A:$A,0))&"") | E46: =IF($A46="","",INDEX(ref_indicateurs!$M:$M,MATCH($A46,ref_indicateurs!$A:$A,0))&"") | F46: =IF($A46="","",IF(INDEX(ref_indicateurs!$O:$O,MATCH($A46,ref_indicateurs!$A:$A,0))="","",INDEX(ref_indicateurs!$O:$O,MATCH($A46,ref_indicateurs!$A:$A,0)))) | G46: =IF($A46="","",SUMIFS(saisie_hebdo!$L:$L,saisie_hebdo!$I:$I,$A46)) | H46: =IF($A46="","",SUMIFS(saisie_hebdo!$M:$M,saisie_hebdo!$I:$I,$A46)) | I46: =IF(OR($A46="",L46=0),"",IF(D46="Pourcentage",IF(H46>0,G46/H46*100,""),G46)) | J46: =IF(OR(I46="",F46="",F46=0),"",I46/F46) | K46: =IF(OR($A46="",L46=0),"",IF(_xlfn.MAXIFS(saisie_hebdo!$C:$C,saisie_hebdo!$I:$I,$A46)=0,"",_xlfn.MAXIFS(saisie_hebdo!$C:$C,saisie_hebdo!$I:$I,$A46))) | L46: =IF($A46="","",COUNTIFS(saisie_hebdo!$I:$I,$A46)) | M46: =IF($A46="","",IF(L46=0,"Non rapporté",IF(F46="","Suivi sans cible",IF(D46="Pourcentage",IF(I46>=F46,"Cible atteinte","Sous la cible"),IF(J46>=1,"Cible atteinte","En cours")))))
A47: =IFERROR(INDEX(ref_indicateurs!$A:$A,44)&"","") | B47: =IF($A47="","",INDEX(ref_indicateurs!$B:$B,MATCH($A47,ref_indicateurs!$A:$A,0))&"") | C47: =IF($A47="","",INDEX(ref_indicateurs!$C:$C,MATCH($A47,ref_indicateurs!$A:$A,0))&"") | D47: =IF($A47="","",INDEX(ref_indicateurs!$E:$E,MATCH($A47,ref_indicateurs!$A:$A,0))&"") | E47: =IF($A47="","",INDEX(ref_indicateurs!$M:$M,MATCH($A47,ref_indicateurs!$A:$A,0))&"") | F47: =IF($A47="","",IF(INDEX(ref_indicateurs!$O:$O,MATCH($A47,ref_indicateurs!$A:$A,0))="","",INDEX(ref_indicateurs!$O:$O,MATCH($A47,ref_indicateurs!$A:$A,0)))) | G47: =IF($A47="","",SUMIFS(saisie_hebdo!$L:$L,saisie_hebdo!$I:$I,$A47)) | H47: =IF($A47="","",SUMIFS(saisie_hebdo!$M:$M,saisie_hebdo!$I:$I,$A47)) | I47: =IF(OR($A47="",L47=0),"",IF(D47="Pourcentage",IF(H47>0,G47/H47*100,""),G47)) | J47: =IF(OR(I47="",F47="",F47=0),"",I47/F47) | K47: =IF(OR($A47="",L47=0),"",IF(_xlfn.MAXIFS(saisie_hebdo!$C:$C,saisie_hebdo!$I:$I,$A47)=0,"",_xlfn.MAXIFS(saisie_hebdo!$C:$C,saisie_hebdo!$I:$I,$A47))) | L47: =IF($A47="","",COUNTIFS(saisie_hebdo!$I:$I,$A47)) | M47: =IF($A47="","",IF(L47=0,"Non rapporté",IF(F47="","Suivi sans cible",IF(D47="Pourcentage",IF(I47>=F47,"Cible atteinte","Sous la cible"),IF(J47>=1,"Cible atteinte","En cours")))))
A48: =IFERROR(INDEX(ref_indicateurs!$A:$A,45)&"","") | B48: =IF($A48="","",INDEX(ref_indicateurs!$B:$B,MATCH($A48,ref_indicateurs!$A:$A,0))&"") | C48: =IF($A48="","",INDEX(ref_indicateurs!$C:$C,MATCH($A48,ref_indicateurs!$A:$A,0))&"") | D48: =IF($A48="","",INDEX(ref_indicateurs!$E:$E,MATCH($A48,ref_indicateurs!$A:$A,0))&"") | E48: =IF($A48="","",INDEX(ref_indicateurs!$M:$M,MATCH($A48,ref_indicateurs!$A:$A,0))&"") | F48: =IF($A48="","",IF(INDEX(ref_indicateurs!$O:$O,MATCH($A48,ref_indicateurs!$A:$A,0))="","",INDEX(ref_indicateurs!$O:$O,MATCH($A48,ref_indicateurs!$A:$A,0)))) | G48: =IF($A48="","",SUMIFS(saisie_hebdo!$L:$L,saisie_hebdo!$I:$I,$A48)) | H48: =IF($A48="","",SUMIFS(saisie_hebdo!$M:$M,saisie_hebdo!$I:$I,$A48)) | I48: =IF(OR($A48="",L48=0),"",IF(D48="Pourcentage",IF(H48>0,G48/H48*100,""),G48)) | J48: =IF(OR(I48="",F48="",F48=0),"",I48/F48) | K48: =IF(OR($A48="",L48=0),"",IF(_xlfn.MAXIFS(saisie_hebdo!$C:$C,saisie_hebdo!$I:$I,$A48)=0,"",_xlfn.MAXIFS(saisie_hebdo!$C:$C,saisie_hebdo!$I:$I,$A48))) | L48: =IF($A48="","",COUNTIFS(saisie_hebdo!$I:$I,$A48)) | M48: =IF($A48="","",IF(L48=0,"Non rapporté",IF(F48="","Suivi sans cible",IF(D48="Pourcentage",IF(I48>=F48,"Cible atteinte","Sous la cible"),IF(J48>=1,"Cible atteinte","En cours")))))
A49: =IFERROR(INDEX(ref_indicateurs!$A:$A,46)&"","") | B49: =IF($A49="","",INDEX(ref_indicateurs!$B:$B,MATCH($A49,ref_indicateurs!$A:$A,0))&"") | C49: =IF($A49="","",INDEX(ref_indicateurs!$C:$C,MATCH($A49,ref_indicateurs!$A:$A,0))&"") | D49: =IF($A49="","",INDEX(ref_indicateurs!$E:$E,MATCH($A49,ref_indicateurs!$A:$A,0))&"") | E49: =IF($A49="","",INDEX(ref_indicateurs!$M:$M,MATCH($A49,ref_indicateurs!$A:$A,0))&"") | F49: =IF($A49="","",IF(INDEX(ref_indicateurs!$O:$O,MATCH($A49,ref_indicateurs!$A:$A,0))="","",INDEX(ref_indicateurs!$O:$O,MATCH($A49,ref_indicateurs!$A:$A,0)))) | G49: =IF($A49="","",SUMIFS(saisie_hebdo!$L:$L,saisie_hebdo!$I:$I,$A49)) | H49: =IF($A49="","",SUMIFS(saisie_hebdo!$M:$M,saisie_hebdo!$I:$I,$A49)) | I49: =IF(OR($A49="",L49=0),"",IF(D49="Pourcentage",IF(H49>0,G49/H49*100,""),G49)) | J49: =IF(OR(I49="",F49="",F49=0),"",I49/F49) | K49: =IF(OR($A49="",L49=0),"",IF(_xlfn.MAXIFS(saisie_hebdo!$C:$C,saisie_hebdo!$I:$I,$A49)=0,"",_xlfn.MAXIFS(saisie_hebdo!$C:$C,saisie_hebdo!$I:$I,$A49))) | L49: =IF($A49="","",COUNTIFS(saisie_hebdo!$I:$I,$A49)) | M49: =IF($A49="","",IF(L49=0,"Non rapporté",IF(F49="","Suivi sans cible",IF(D49="Pourcentage",IF(I49>=F49,"Cible atteinte","Sous la cible"),IF(J49>=1,"Cible atteinte","En cours")))))
A50: =IFERROR(INDEX(ref_indicateurs!$A:$A,47)&"","") | B50: =IF($A50="","",INDEX(ref_indicateurs!$B:$B,MATCH($A50,ref_indicateurs!$A:$A,0))&"") | C50: =IF($A50="","",INDEX(ref_indicateurs!$C:$C,MATCH($A50,ref_indicateurs!$A:$A,0))&"") | D50: =IF($A50="","",INDEX(ref_indicateurs!$E:$E,MATCH($A50,ref_indicateurs!$A:$A,0))&"") | E50: =IF($A50="","",INDEX(ref_indicateurs!$M:$M,MATCH($A50,ref_indicateurs!$A:$A,0))&"") | F50: =IF($A50="","",IF(INDEX(ref_indicateurs!$O:$O,MATCH($A50,ref_indicateurs!$A:$A,0))="","",INDEX(ref_indicateurs!$O:$O,MATCH($A50,ref_indicateurs!$A:$A,0)))) | G50: =IF($A50="","",SUMIFS(saisie_hebdo!$L:$L,saisie_hebdo!$I:$I,$A50)) | H50: =IF($A50="","",SUMIFS(saisie_hebdo!$M:$M,saisie_hebdo!$I:$I,$A50)) | I50: =IF(OR($A50="",L50=0),"",IF(D50="Pourcentage",IF(H50>0,G50/H50*100,""),G50)) | J50: =IF(OR(I50="",F50="",F50=0),"",I50/F50) | K50: =IF(OR($A50="",L50=0),"",IF(_xlfn.MAXIFS(saisie_hebdo!$C:$C,saisie_hebdo!$I:$I,$A50)=0,"",_xlfn.MAXIFS(saisie_hebdo!$C:$C,saisie_hebdo!$I:$I,$A50))) | L50: =IF($A50="","",COUNTIFS(saisie_hebdo!$I:$I,$A50)) | M50: =IF($A50="","",IF(L50=0,"Non rapporté",IF(F50="","Suivi sans cible",IF(D50="Pourcentage",IF(I50>=F50,"Cible atteinte","Sous la cible"),IF(J50>=1,"Cible atteinte","En cours")))))
A51: =IFERROR(INDEX(ref_indicateurs!$A:$A,48)&"","") | B51: =IF($A51="","",INDEX(ref_indicateurs!$B:$B,MATCH($A51,ref_indicateurs!$A:$A,0))&"") | C51: =IF($A51="","",INDEX(ref_indicateurs!$C:$C,MATCH($A51,ref_indicateurs!$A:$A,0))&"") | D51: =IF($A51="","",INDEX(ref_indicateurs!$E:$E,MATCH($A51,ref_indicateurs!$A:$A,0))&"") | E51: =IF($A51="","",INDEX(ref_indicateurs!$M:$M,MATCH($A51,ref_indicateurs!$A:$A,0))&"") | F51: =IF($A51="","",IF(INDEX(ref_indicateurs!$O:$O,MATCH($A51,ref_indicateurs!$A:$A,0))="","",INDEX(ref_indicateurs!$O:$O,MATCH($A51,ref_indicateurs!$A:$A,0)))) | G51: =IF($A51="","",SUMIFS(saisie_hebdo!$L:$L,saisie_hebdo!$I:$I,$A51)) | H51: =IF($A51="","",SUMIFS(saisie_hebdo!$M:$M,saisie_hebdo!$I:$I,$A51)) | I51: =IF(OR($A51="",L51=0),"",IF(D51="Pourcentage",IF(H51>0,G51/H51*100,""),G51)) | J51: =IF(OR(I51="",F51="",F51=0),"",I51/F51) | K51: =IF(OR($A51="",L51=0),"",IF(_xlfn.MAXIFS(saisie_hebdo!$C:$C,saisie_hebdo!$I:$I,$A51)=0,"",_xlfn.MAXIFS(saisie_hebdo!$C:$C,saisie_hebdo!$I:$I,$A51))) | L51: =IF($A51="","",COUNTIFS(saisie_hebdo!$I:$I,$A51)) | M51: =IF($A51="","",IF(L51=0,"Non rapporté",IF(F51="","Suivi sans cible",IF(D51="Pourcentage",IF(I51>=F51,"Cible atteinte","Sous la cible"),IF(J51>=1,"Cible atteinte","En cours")))))
A52: =IFERROR(INDEX(ref_indicateurs!$A:$A,49)&"","") | B52: =IF($A52="","",INDEX(ref_indicateurs!$B:$B,MATCH($A52,ref_indicateurs!$A:$A,0))&"") | C52: =IF($A52="","",INDEX(ref_indicateurs!$C:$C,MATCH($A52,ref_indicateurs!$A:$A,0))&"") | D52: =IF($A52="","",INDEX(ref_indicateurs!$E:$E,MATCH($A52,ref_indicateurs!$A:$A,0))&"") | E52: =IF($A52="","",INDEX(ref_indicateurs!$M:$M,MATCH($A52,ref_indicateurs!$A:$A,0))&"") | F52: =IF($A52="","",IF(INDEX(ref_indicateurs!$O:$O,MATCH($A52,ref_indicateurs!$A:$A,0))="","",INDEX(ref_indicateurs!$O:$O,MATCH($A52,ref_indicateurs!$A:$A,0)))) | G52: =IF($A52="","",SUMIFS(saisie_hebdo!$L:$L,saisie_hebdo!$I:$I,$A52)) | H52: =IF($A52="","",SUMIFS(saisie_hebdo!$M:$M,saisie_hebdo!$I:$I,$A52)) | I52: =IF(OR($A52="",L52=0),"",IF(D52="Pourcentage",IF(H52>0,G52/H52*100,""),G52)) | J52: =IF(OR(I52="",F52="",F52=0),"",I52/F52) | K52: =IF(OR($A52="",L52=0),"",IF(_xlfn.MAXIFS(saisie_hebdo!$C:$C,saisie_hebdo!$I:$I,$A52)=0,"",_xlfn.MAXIFS(saisie_hebdo!$C:$C,saisie_hebdo!$I:$I,$A52))) | L52: =IF($A52="","",COUNTIFS(saisie_hebdo!$I:$I,$A52)) | M52: =IF($A52="","",IF(L52=0,"Non rapporté",IF(F52="","Suivi sans cible",IF(D52="Pourcentage",IF(I52>=F52,"Cible atteinte","Sous la cible"),IF(J52>=1,"Cible atteinte","En cours")))))
A53: =IFERROR(INDEX(ref_indicateurs!$A:$A,50)&"","") | B53: =IF($A53="","",INDEX(ref_indicateurs!$B:$B,MATCH($A53,ref_indicateurs!$A:$A,0))&"") | C53: =IF($A53="","",INDEX(ref_indicateurs!$C:$C,MATCH($A53,ref_indicateurs!$A:$A,0))&"") | D53: =IF($A53="","",INDEX(ref_indicateurs!$E:$E,MATCH($A53,ref_indicateurs!$A:$A,0))&"") | E53: =IF($A53="","",INDEX(ref_indicateurs!$M:$M,MATCH($A53,ref_indicateurs!$A:$A,0))&"") | F53: =IF($A53="","",IF(INDEX(ref_indicateurs!$O:$O,MATCH($A53,ref_indicateurs!$A:$A,0))="","",INDEX(ref_indicateurs!$O:$O,MATCH($A53,ref_indicateurs!$A:$A,0)))) | G53: =IF($A53="","",SUMIFS(saisie_hebdo!$L:$L,saisie_hebdo!$I:$I,$A53)) | H53: =IF($A53="","",SUMIFS(saisie_hebdo!$M:$M,saisie_hebdo!$I:$I,$A53)) | I53: =IF(OR($A53="",L53=0),"",IF(D53="Pourcentage",IF(H53>0,G53/H53*100,""),G53)) | J53: =IF(OR(I53="",F53="",F53=0),"",I53/F53) | K53: =IF(OR($A53="",L53=0),"",IF(_xlfn.MAXIFS(saisie_hebdo!$C:$C,saisie_hebdo!$I:$I,$A53)=0,"",_xlfn.MAXIFS(saisie_hebdo!$C:$C,saisie_hebdo!$I:$I,$A53))) | L53: =IF($A53="","",COUNTIFS(saisie_hebdo!$I:$I,$A53)) | M53: =IF($A53="","",IF(L53=0,"Non rapporté",IF(F53="","Suivi sans cible",IF(D53="Pourcentage",IF(I53>=F53,"Cible atteinte","Sous la cible"),IF(J53>=1,"Cible atteinte","En cours")))))
A54: =IFERROR(INDEX(ref_indicateurs!$A:$A,51)&"","") | B54: =IF($A54="","",INDEX(ref_indicateurs!$B:$B,MATCH($A54,ref_indicateurs!$A:$A,0))&"") | C54: =IF($A54="","",INDEX(ref_indicateurs!$C:$C,MATCH($A54,ref_indicateurs!$A:$A,0))&"") | D54: =IF($A54="","",INDEX(ref_indicateurs!$E:$E,MATCH($A54,ref_indicateurs!$A:$A,0))&"") | E54: =IF($A54="","",INDEX(ref_indicateurs!$M:$M,MATCH($A54,ref_indicateurs!$A:$A,0))&"") | F54: =IF($A54="","",IF(INDEX(ref_indicateurs!$O:$O,MATCH($A54,ref_indicateurs!$A:$A,0))="","",INDEX(ref_indicateurs!$O:$O,MATCH($A54,ref_indicateurs!$A:$A,0)))) | G54: =IF($A54="","",SUMIFS(saisie_hebdo!$L:$L,saisie_hebdo!$I:$I,$A54)) | H54: =IF($A54="","",SUMIFS(saisie_hebdo!$M:$M,saisie_hebdo!$I:$I,$A54)) | I54: =IF(OR($A54="",L54=0),"",IF(D54="Pourcentage",IF(H54>0,G54/H54*100,""),G54)) | J54: =IF(OR(I54="",F54="",F54=0),"",I54/F54) | K54: =IF(OR($A54="",L54=0),"",IF(_xlfn.MAXIFS(saisie_hebdo!$C:$C,saisie_hebdo!$I:$I,$A54)=0,"",_xlfn.MAXIFS(saisie_hebdo!$C:$C,saisie_hebdo!$I:$I,$A54))) | L54: =IF($A54="","",COUNTIFS(saisie_hebdo!$I:$I,$A54)) | M54: =IF($A54="","",IF(L54=0,"Non rapporté",IF(F54="","Suivi sans cible",IF(D54="Pourcentage",IF(I54>=F54,"Cible atteinte","Sous la cible"),IF(J54>=1,"Cible atteinte","En cours")))))
A55: =IFERROR(INDEX(ref_indicateurs!$A:$A,52)&"","") | B55: =IF($A55="","",INDEX(ref_indicateurs!$B:$B,MATCH($A55,ref_indicateurs!$A:$A,0))&"") | C55: =IF($A55="","",INDEX(ref_indicateurs!$C:$C,MATCH($A55,ref_indicateurs!$A:$A,0))&"") | D55: =IF($A55="","",INDEX(ref_indicateurs!$E:$E,MATCH($A55,ref_indicateurs!$A:$A,0))&"") | E55: =IF($A55="","",INDEX(ref_indicateurs!$M:$M,MATCH($A55,ref_indicateurs!$A:$A,0))&"") | F55: =IF($A55="","",IF(INDEX(ref_indicateurs!$O:$O,MATCH($A55,ref_indicateurs!$A:$A,0))="","",INDEX(ref_indicateurs!$O:$O,MATCH($A55,ref_indicateurs!$A:$A,0)))) | G55: =IF($A55="","",SUMIFS(saisie_hebdo!$L:$L,saisie_hebdo!$I:$I,$A55)) | H55: =IF($A55="","",SUMIFS(saisie_hebdo!$M:$M,saisie_hebdo!$I:$I,$A55)) | I55: =IF(OR($A55="",L55=0),"",IF(D55="Pourcentage",IF(H55>0,G55/H55*100,""),G55)) | J55: =IF(OR(I55="",F55="",F55=0),"",I55/F55) | K55: =IF(OR($A55="",L55=0),"",IF(_xlfn.MAXIFS(saisie_hebdo!$C:$C,saisie_hebdo!$I:$I,$A55)=0,"",_xlfn.MAXIFS(saisie_hebdo!$C:$C,saisie_hebdo!$I:$I,$A55))) | L55: =IF($A55="","",COUNTIFS(saisie_hebdo!$I:$I,$A55)) | M55: =IF($A55="","",IF(L55=0,"Non rapporté",IF(F55="","Suivi sans cible",IF(D55="Pourcentage",IF(I55>=F55,"Cible atteinte","Sous la cible"),IF(J55>=1,"Cible atteinte","En cours")))))
A56: =IFERROR(INDEX(ref_indicateurs!$A:$A,53)&"","") | B56: =IF($A56="","",INDEX(ref_indicateurs!$B:$B,MATCH($A56,ref_indicateurs!$A:$A,0))&"") | C56: =IF($A56="","",INDEX(ref_indicateurs!$C:$C,MATCH($A56,ref_indicateurs!$A:$A,0))&"") | D56: =IF($A56="","",INDEX(ref_indicateurs!$E:$E,MATCH($A56,ref_indicateurs!$A:$A,0))&"") | E56: =IF($A56="","",INDEX(ref_indicateurs!$M:$M,MATCH($A56,ref_indicateurs!$A:$A,0))&"") | F56: =IF($A56="","",IF(INDEX(ref_indicateurs!$O:$O,MATCH($A56,ref_indicateurs!$A:$A,0))="","",INDEX(ref_indicateurs!$O:$O,MATCH($A56,ref_indicateurs!$A:$A,0)))) | G56: =IF($A56="","",SUMIFS(saisie_hebdo!$L:$L,saisie_hebdo!$I:$I,$A56)) | H56: =IF($A56="","",SUMIFS(saisie_hebdo!$M:$M,saisie_hebdo!$I:$I,$A56)) | I56: =IF(OR($A56="",L56=0),"",IF(D56="Pourcentage",IF(H56>0,G56/H56*100,""),G56)) | J56: =IF(OR(I56="",F56="",F56=0),"",I56/F56) | K56: =IF(OR($A56="",L56=0),"",IF(_xlfn.MAXIFS(saisie_hebdo!$C:$C,saisie_hebdo!$I:$I,$A56)=0,"",_xlfn.MAXIFS(saisie_hebdo!$C:$C,saisie_hebdo!$I:$I,$A56))) | L56: =IF($A56="","",COUNTIFS(saisie_hebdo!$I:$I,$A56)) | M56: =IF($A56="","",IF(L56=0,"Non rapporté",IF(F56="","Suivi sans cible",IF(D56="Pourcentage",IF(I56>=F56,"Cible atteinte","Sous la cible"),IF(J56>=1,"Cible atteinte","En cours")))))
A57: =IFERROR(INDEX(ref_indicateurs!$A:$A,54)&"","") | B57: =IF($A57="","",INDEX(ref_indicateurs!$B:$B,MATCH($A57,ref_indicateurs!$A:$A,0))&"") | C57: =IF($A57="","",INDEX(ref_indicateurs!$C:$C,MATCH($A57,ref_indicateurs!$A:$A,0))&"") | D57: =IF($A57="","",INDEX(ref_indicateurs!$E:$E,MATCH($A57,ref_indicateurs!$A:$A,0))&"") | E57: =IF($A57="","",INDEX(ref_indicateurs!$M:$M,MATCH($A57,ref_indicateurs!$A:$A,0))&"") | F57: =IF($A57="","",IF(INDEX(ref_indicateurs!$O:$O,MATCH($A57,ref_indicateurs!$A:$A,0))="","",INDEX(ref_indicateurs!$O:$O,MATCH($A57,ref_indicateurs!$A:$A,0)))) | G57: =IF($A57="","",SUMIFS(saisie_hebdo!$L:$L,saisie_hebdo!$I:$I,$A57)) | H57: =IF($A57="","",SUMIFS(saisie_hebdo!$M:$M,saisie_hebdo!$I:$I,$A57)) | I57: =IF(OR($A57="",L57=0),"",IF(D57="Pourcentage",IF(H57>0,G57/H57*100,""),G57)) | J57: =IF(OR(I57="",F57="",F57=0),"",I57/F57) | K57: =IF(OR($A57="",L57=0),"",IF(_xlfn.MAXIFS(saisie_hebdo!$C:$C,saisie_hebdo!$I:$I,$A57)=0,"",_xlfn.MAXIFS(saisie_hebdo!$C:$C,saisie_hebdo!$I:$I,$A57))) | L57: =IF($A57="","",COUNTIFS(saisie_hebdo!$I:$I,$A57)) | M57: =IF($A57="","",IF(L57=0,"Non rapporté",IF(F57="","Suivi sans cible",IF(D57="Pourcentage",IF(I57>=F57,"Cible atteinte","Sous la cible"),IF(J57>=1,"Cible atteinte","En cours")))))
A58: =IFERROR(INDEX(ref_indicateurs!$A:$A,55)&"","") | B58: =IF($A58="","",INDEX(ref_indicateurs!$B:$B,MATCH($A58,ref_indicateurs!$A:$A,0))&"") | C58: =IF($A58="","",INDEX(ref_indicateurs!$C:$C,MATCH($A58,ref_indicateurs!$A:$A,0))&"") | D58: =IF($A58="","",INDEX(ref_indicateurs!$E:$E,MATCH($A58,ref_indicateurs!$A:$A,0))&"") | E58: =IF($A58="","",INDEX(ref_indicateurs!$M:$M,MATCH($A58,ref_indicateurs!$A:$A,0))&"") | F58: =IF($A58="","",IF(INDEX(ref_indicateurs!$O:$O,MATCH($A58,ref_indicateurs!$A:$A,0))="","",INDEX(ref_indicateurs!$O:$O,MATCH($A58,ref_indicateurs!$A:$A,0)))) | G58: =IF($A58="","",SUMIFS(saisie_hebdo!$L:$L,saisie_hebdo!$I:$I,$A58)) | H58: =IF($A58="","",SUMIFS(saisie_hebdo!$M:$M,saisie_hebdo!$I:$I,$A58)) | I58: =IF(OR($A58="",L58=0),"",IF(D58="Pourcentage",IF(H58>0,G58/H58*100,""),G58)) | J58: =IF(OR(I58="",F58="",F58=0),"",I58/F58) | K58: =IF(OR($A58="",L58=0),"",IF(_xlfn.MAXIFS(saisie_hebdo!$C:$C,saisie_hebdo!$I:$I,$A58)=0,"",_xlfn.MAXIFS(saisie_hebdo!$C:$C,saisie_hebdo!$I:$I,$A58))) | L58: =IF($A58="","",COUNTIFS(saisie_hebdo!$I:$I,$A58)) | M58: =IF($A58="","",IF(L58=0,"Non rapporté",IF(F58="","Suivi sans cible",IF(D58="Pourcentage",IF(I58>=F58,"Cible atteinte","Sous la cible"),IF(J58>=1,"Cible atteinte","En cours")))))
A59: =IFERROR(INDEX(ref_indicateurs!$A:$A,56)&"","") | B59: =IF($A59="","",INDEX(ref_indicateurs!$B:$B,MATCH($A59,ref_indicateurs!$A:$A,0))&"") | C59: =IF($A59="","",INDEX(ref_indicateurs!$C:$C,MATCH($A59,ref_indicateurs!$A:$A,0))&"") | D59: =IF($A59="","",INDEX(ref_indicateurs!$E:$E,MATCH($A59,ref_indicateurs!$A:$A,0))&"") | E59: =IF($A59="","",INDEX(ref_indicateurs!$M:$M,MATCH($A59,ref_indicateurs!$A:$A,0))&"") | F59: =IF($A59="","",IF(INDEX(ref_indicateurs!$O:$O,MATCH($A59,ref_indicateurs!$A:$A,0))="","",INDEX(ref_indicateurs!$O:$O,MATCH($A59,ref_indicateurs!$A:$A,0)))) | G59: =IF($A59="","",SUMIFS(saisie_hebdo!$L:$L,saisie_hebdo!$I:$I,$A59)) | H59: =IF($A59="","",SUMIFS(saisie_hebdo!$M:$M,saisie_hebdo!$I:$I,$A59)) | I59: =IF(OR($A59="",L59=0),"",IF(D59="Pourcentage",IF(H59>0,G59/H59*100,""),G59)) | J59: =IF(OR(I59="",F59="",F59=0),"",I59/F59) | K59: =IF(OR($A59="",L59=0),"",IF(_xlfn.MAXIFS(saisie_hebdo!$C:$C,saisie_hebdo!$I:$I,$A59)=0,"",_xlfn.MAXIFS(saisie_hebdo!$C:$C,saisie_hebdo!$I:$I,$A59))) | L59: =IF($A59="","",COUNTIFS(saisie_hebdo!$I:$I,$A59)) | M59: =IF($A59="","",IF(L59=0,"Non rapporté",IF(F59="","Suivi sans cible",IF(D59="Pourcentage",IF(I59>=F59,"Cible atteinte","Sous la cible"),IF(J59>=1,"Cible atteinte","En cours")))))
A60: =IFERROR(INDEX(ref_indicateurs!$A:$A,57)&"","") | B60: =IF($A60="","",INDEX(ref_indicateurs!$B:$B,MATCH($A60,ref_indicateurs!$A:$A,0))&"") | C60: =IF($A60="","",INDEX(ref_indicateurs!$C:$C,MATCH($A60,ref_indicateurs!$A:$A,0))&"") | D60: =IF($A60="","",INDEX(ref_indicateurs!$E:$E,MATCH($A60,ref_indicateurs!$A:$A,0))&"") | E60: =IF($A60="","",INDEX(ref_indicateurs!$M:$M,MATCH($A60,ref_indicateurs!$A:$A,0))&"") | F60: =IF($A60="","",IF(INDEX(ref_indicateurs!$O:$O,MATCH($A60,ref_indicateurs!$A:$A,0))="","",INDEX(ref_indicateurs!$O:$O,MATCH($A60,ref_indicateurs!$A:$A,0)))) | G60: =IF($A60="","",SUMIFS(saisie_hebdo!$L:$L,saisie_hebdo!$I:$I,$A60)) | H60: =IF($A60="","",SUMIFS(saisie_hebdo!$M:$M,saisie_hebdo!$I:$I,$A60)) | I60: =IF(OR($A60="",L60=0),"",IF(D60="Pourcentage",IF(H60>0,G60/H60*100,""),G60)) | J60: =IF(OR(I60="",F60="",F60=0),"",I60/F60) | K60: =IF(OR($A60="",L60=0),"",IF(_xlfn.MAXIFS(saisie_hebdo!$C:$C,saisie_hebdo!$I:$I,$A60)=0,"",_xlfn.MAXIFS(saisie_hebdo!$C:$C,saisie_hebdo!$I:$I,$A60))) | L60: =IF($A60="","",COUNTIFS(saisie_hebdo!$I:$I,$A60)) | M60: =IF($A60="","",IF(L60=0,"Non rapporté",IF(F60="","Suivi sans cible",IF(D60="Pourcentage",IF(I60>=F60,"Cible atteinte","Sous la cible"),IF(J60>=1,"Cible atteinte","En cours")))))
A61: =IFERROR(INDEX(ref_indicateurs!$A:$A,58)&"","") | B61: =IF($A61="","",INDEX(ref_indicateurs!$B:$B,MATCH($A61,ref_indicateurs!$A:$A,0))&"") | C61: =IF($A61="","",INDEX(ref_indicateurs!$C:$C,MATCH($A61,ref_indicateurs!$A:$A,0))&"") | D61: =IF($A61="","",INDEX(ref_indicateurs!$E:$E,MATCH($A61,ref_indicateurs!$A:$A,0))&"") | E61: =IF($A61="","",INDEX(ref_indicateurs!$M:$M,MATCH($A61,ref_indicateurs!$A:$A,0))&"") | F61: =IF($A61="","",IF(INDEX(ref_indicateurs!$O:$O,MATCH($A61,ref_indicateurs!$A:$A,0))="","",INDEX(ref_indicateurs!$O:$O,MATCH($A61,ref_indicateurs!$A:$A,0)))) | G61: =IF($A61="","",SUMIFS(saisie_hebdo!$L:$L,saisie_hebdo!$I:$I,$A61)) | H61: =IF($A61="","",SUMIFS(saisie_hebdo!$M:$M,saisie_hebdo!$I:$I,$A61)) | I61: =IF(OR($A61="",L61=0),"",IF(D61="Pourcentage",IF(H61>0,G61/H61*100,""),G61)) | J61: =IF(OR(I61="",F61="",F61=0),"",I61/F61) | K61: =IF(OR($A61="",L61=0),"",IF(_xlfn.MAXIFS(saisie_hebdo!$C:$C,saisie_hebdo!$I:$I,$A61)=0,"",_xlfn.MAXIFS(saisie_hebdo!$C:$C,saisie_hebdo!$I:$I,$A61))) | L61: =IF($A61="","",COUNTIFS(saisie_hebdo!$I:$I,$A61)) | M61: =IF($A61="","",IF(L61=0,"Non rapporté",IF(F61="","Suivi sans cible",IF(D61="Pourcentage",IF(I61>=F61,"Cible atteinte","Sous la cible"),IF(J61>=1,"Cible atteinte","En cours")))))
A62: =IFERROR(INDEX(ref_indicateurs!$A:$A,59)&"","") | B62: =IF($A62="","",INDEX(ref_indicateurs!$B:$B,MATCH($A62,ref_indicateurs!$A:$A,0))&"") | C62: =IF($A62="","",INDEX(ref_indicateurs!$C:$C,MATCH($A62,ref_indicateurs!$A:$A,0))&"") | D62: =IF($A62="","",INDEX(ref_indicateurs!$E:$E,MATCH($A62,ref_indicateurs!$A:$A,0))&"") | E62: =IF($A62="","",INDEX(ref_indicateurs!$M:$M,MATCH($A62,ref_indicateurs!$A:$A,0))&"") | F62: =IF($A62="","",IF(INDEX(ref_indicateurs!$O:$O,MATCH($A62,ref_indicateurs!$A:$A,0))="","",INDEX(ref_indicateurs!$O:$O,MATCH($A62,ref_indicateurs!$A:$A,0)))) | G62: =IF($A62="","",SUMIFS(saisie_hebdo!$L:$L,saisie_hebdo!$I:$I,$A62)) | H62: =IF($A62="","",SUMIFS(saisie_hebdo!$M:$M,saisie_hebdo!$I:$I,$A62)) | I62: =IF(OR($A62="",L62=0),"",IF(D62="Pourcentage",IF(H62>0,G62/H62*100,""),G62)) | J62: =IF(OR(I62="",F62="",F62=0),"",I62/F62) | K62: =IF(OR($A62="",L62=0),"",IF(_xlfn.MAXIFS(saisie_hebdo!$C:$C,saisie_hebdo!$I:$I,$A62)=0,"",_xlfn.MAXIFS(saisie_hebdo!$C:$C,saisie_hebdo!$I:$I,$A62))) | L62: =IF($A62="","",COUNTIFS(saisie_hebdo!$I:$I,$A62)) | M62: =IF($A62="","",IF(L62=0,"Non rapporté",IF(F62="","Suivi sans cible",IF(D62="Pourcentage",IF(I62>=F62,"Cible atteinte","Sous la cible"),IF(J62>=1,"Cible atteinte","En cours")))))
A63: =IFERROR(INDEX(ref_indicateurs!$A:$A,60)&"","") | B63: =IF($A63="","",INDEX(ref_indicateurs!$B:$B,MATCH($A63,ref_indicateurs!$A:$A,0))&"") | C63: =IF($A63="","",INDEX(ref_indicateurs!$C:$C,MATCH($A63,ref_indicateurs!$A:$A,0))&"") | D63: =IF($A63="","",INDEX(ref_indicateurs!$E:$E,MATCH($A63,ref_indicateurs!$A:$A,0))&"") | E63: =IF($A63="","",INDEX(ref_indicateurs!$M:$M,MATCH($A63,ref_indicateurs!$A:$A,0))&"") | F63: =IF($A63="","",IF(INDEX(ref_indicateurs!$O:$O,MATCH($A63,ref_indicateurs!$A:$A,0))="","",INDEX(ref_indicateurs!$O:$O,MATCH($A63,ref_indicateurs!$A:$A,0)))) | G63: =IF($A63="","",SUMIFS(saisie_hebdo!$L:$L,saisie_hebdo!$I:$I,$A63)) | H63: =IF($A63="","",SUMIFS(saisie_hebdo!$M:$M,saisie_hebdo!$I:$I,$A63)) | I63: =IF(OR($A63="",L63=0),"",IF(D63="Pourcentage",IF(H63>0,G63/H63*100,""),G63)) | J63: =IF(OR(I63="",F63="",F63=0),"",I63/F63) | K63: =IF(OR($A63="",L63=0),"",IF(_xlfn.MAXIFS(saisie_hebdo!$C:$C,saisie_hebdo!$I:$I,$A63)=0,"",_xlfn.MAXIFS(saisie_hebdo!$C:$C,saisie_hebdo!$I:$I,$A63))) | L63: =IF($A63="","",COUNTIFS(saisie_hebdo!$I:$I,$A63)) | M63: =IF($A63="","",IF(L63=0,"Non rapporté",IF(F63="","Suivi sans cible",IF(D63="Pourcentage",IF(I63>=F63,"Cible atteinte","Sous la cible"),IF(J63>=1,"Cible atteinte","En cours")))))
A64: =IFERROR(INDEX(ref_indicateurs!$A:$A,61)&"","") | B64: =IF($A64="","",INDEX(ref_indicateurs!$B:$B,MATCH($A64,ref_indicateurs!$A:$A,0))&"") | C64: =IF($A64="","",INDEX(ref_indicateurs!$C:$C,MATCH($A64,ref_indicateurs!$A:$A,0))&"") | D64: =IF($A64="","",INDEX(ref_indicateurs!$E:$E,MATCH($A64,ref_indicateurs!$A:$A,0))&"") | E64: =IF($A64="","",INDEX(ref_indicateurs!$M:$M,MATCH($A64,ref_indicateurs!$A:$A,0))&"") | F64: =IF($A64="","",IF(INDEX(ref_indicateurs!$O:$O,MATCH($A64,ref_indicateurs!$A:$A,0))="","",INDEX(ref_indicateurs!$O:$O,MATCH($A64,ref_indicateurs!$A:$A,0)))) | G64: =IF($A64="","",SUMIFS(saisie_hebdo!$L:$L,saisie_hebdo!$I:$I,$A64)) | H64: =IF($A64="","",SUMIFS(saisie_hebdo!$M:$M,saisie_hebdo!$I:$I,$A64)) | I64: =IF(OR($A64="",L64=0),"",IF(D64="Pourcentage",IF(H64>0,G64/H64*100,""),G64)) | J64: =IF(OR(I64="",F64="",F64=0),"",I64/F64) | K64: =IF(OR($A64="",L64=0),"",IF(_xlfn.MAXIFS(saisie_hebdo!$C:$C,saisie_hebdo!$I:$I,$A64)=0,"",_xlfn.MAXIFS(saisie_hebdo!$C:$C,saisie_hebdo!$I:$I,$A64))) | L64: =IF($A64="","",COUNTIFS(saisie_hebdo!$I:$I,$A64)) | M64: =IF($A64="","",IF(L64=0,"Non rapporté",IF(F64="","Suivi sans cible",IF(D64="Pourcentage",IF(I64>=F64,"Cible atteinte","Sous la cible"),IF(J64>=1,"Cible atteinte","En cours")))))
A65: =IFERROR(INDEX(ref_indicateurs!$A:$A,62)&"","") | B65: =IF($A65="","",INDEX(ref_indicateurs!$B:$B,MATCH($A65,ref_indicateurs!$A:$A,0))&"") | C65: =IF($A65="","",INDEX(ref_indicateurs!$C:$C,MATCH($A65,ref_indicateurs!$A:$A,0))&"") | D65: =IF($A65="","",INDEX(ref_indicateurs!$E:$E,MATCH($A65,ref_indicateurs!$A:$A,0))&"") | E65: =IF($A65="","",INDEX(ref_indicateurs!$M:$M,MATCH($A65,ref_indicateurs!$A:$A,0))&"") | F65: =IF($A65="","",IF(INDEX(ref_indicateurs!$O:$O,MATCH($A65,ref_indicateurs!$A:$A,0))="","",INDEX(ref_indicateurs!$O:$O,MATCH($A65,ref_indicateurs!$A:$A,0)))) | G65: =IF($A65="","",SUMIFS(saisie_hebdo!$L:$L,saisie_hebdo!$I:$I,$A65)) | H65: =IF($A65="","",SUMIFS(saisie_hebdo!$M:$M,saisie_hebdo!$I:$I,$A65)) | I65: =IF(OR($A65="",L65=0),"",IF(D65="Pourcentage",IF(H65>0,G65/H65*100,""),G65)) | J65: =IF(OR(I65="",F65="",F65=0),"",I65/F65) | K65: =IF(OR($A65="",L65=0),"",IF(_xlfn.MAXIFS(saisie_hebdo!$C:$C,saisie_hebdo!$I:$I,$A65)=0,"",_xlfn.MAXIFS(saisie_hebdo!$C:$C,saisie_hebdo!$I:$I,$A65))) | L65: =IF($A65="","",COUNTIFS(saisie_hebdo!$I:$I,$A65)) | M65: =IF($A65="","",IF(L65=0,"Non rapporté",IF(F65="","Suivi sans cible",IF(D65="Pourcentage",IF(I65>=F65,"Cible atteinte","Sous la cible"),IF(J65>=1,"Cible atteinte","En cours")))))
A66: =IFERROR(INDEX(ref_indicateurs!$A:$A,63)&"","") | B66: =IF($A66="","",INDEX(ref_indicateurs!$B:$B,MATCH($A66,ref_indicateurs!$A:$A,0))&"") | C66: =IF($A66="","",INDEX(ref_indicateurs!$C:$C,MATCH($A66,ref_indicateurs!$A:$A,0))&"") | D66: =IF($A66="","",INDEX(ref_indicateurs!$E:$E,MATCH($A66,ref_indicateurs!$A:$A,0))&"") | E66: =IF($A66="","",INDEX(ref_indicateurs!$M:$M,MATCH($A66,ref_indicateurs!$A:$A,0))&"") | F66: =IF($A66="","",IF(INDEX(ref_indicateurs!$O:$O,MATCH($A66,ref_indicateurs!$A:$A,0))="","",INDEX(ref_indicateurs!$O:$O,MATCH($A66,ref_indicateurs!$A:$A,0)))) | G66: =IF($A66="","",SUMIFS(saisie_hebdo!$L:$L,saisie_hebdo!$I:$I,$A66)) | H66: =IF($A66="","",SUMIFS(saisie_hebdo!$M:$M,saisie_hebdo!$I:$I,$A66)) | I66: =IF(OR($A66="",L66=0),"",IF(D66="Pourcentage",IF(H66>0,G66/H66*100,""),G66)) | J66: =IF(OR(I66="",F66="",F66=0),"",I66/F66) | K66: =IF(OR($A66="",L66=0),"",IF(_xlfn.MAXIFS(saisie_hebdo!$C:$C,saisie_hebdo!$I:$I,$A66)=0,"",_xlfn.MAXIFS(saisie_hebdo!$C:$C,saisie_hebdo!$I:$I,$A66))) | L66: =IF($A66="","",COUNTIFS(saisie_hebdo!$I:$I,$A66)) | M66: =IF($A66="","",IF(L66=0,"Non rapporté",IF(F66="","Suivi sans cible",IF(D66="Pourcentage",IF(I66>=F66,"Cible atteinte","Sous la cible"),IF(J66>=1,"Cible atteinte","En cours")))))
A67: =IFERROR(INDEX(ref_indicateurs!$A:$A,64)&"","") | B67: =IF($A67="","",INDEX(ref_indicateurs!$B:$B,MATCH($A67,ref_indicateurs!$A:$A,0))&"") | C67: =IF($A67="","",INDEX(ref_indicateurs!$C:$C,MATCH($A67,ref_indicateurs!$A:$A,0))&"") | D67: =IF($A67="","",INDEX(ref_indicateurs!$E:$E,MATCH($A67,ref_indicateurs!$A:$A,0))&"") | E67: =IF($A67="","",INDEX(ref_indicateurs!$M:$M,MATCH($A67,ref_indicateurs!$A:$A,0))&"") | F67: =IF($A67="","",IF(INDEX(ref_indicateurs!$O:$O,MATCH($A67,ref_indicateurs!$A:$A,0))="","",INDEX(ref_indicateurs!$O:$O,MATCH($A67,ref_indicateurs!$A:$A,0)))) | G67: =IF($A67="","",SUMIFS(saisie_hebdo!$L:$L,saisie_hebdo!$I:$I,$A67)) | H67: =IF($A67="","",SUMIFS(saisie_hebdo!$M:$M,saisie_hebdo!$I:$I,$A67)) | I67: =IF(OR($A67="",L67=0),"",IF(D67="Pourcentage",IF(H67>0,G67/H67*100,""),G67)) | J67: =IF(OR(I67="",F67="",F67=0),"",I67/F67) | K67: =IF(OR($A67="",L67=0),"",IF(_xlfn.MAXIFS(saisie_hebdo!$C:$C,saisie_hebdo!$I:$I,$A67)=0,"",_xlfn.MAXIFS(saisie_hebdo!$C:$C,saisie_hebdo!$I:$I,$A67))) | L67: =IF($A67="","",COUNTIFS(saisie_hebdo!$I:$I,$A67)) | M67: =IF($A67="","",IF(L67=0,"Non rapporté",IF(F67="","Suivi sans cible",IF(D67="Pourcentage",IF(I67>=F67,"Cible atteinte","Sous la cible"),IF(J67>=1,"Cible atteinte","En cours")))))
A68: =IFERROR(INDEX(ref_indicateurs!$A:$A,65)&"","") | B68: =IF($A68="","",INDEX(ref_indicateurs!$B:$B,MATCH($A68,ref_indicateurs!$A:$A,0))&"") | C68: =IF($A68="","",INDEX(ref_indicateurs!$C:$C,MATCH($A68,ref_indicateurs!$A:$A,0))&"") | D68: =IF($A68="","",INDEX(ref_indicateurs!$E:$E,MATCH($A68,ref_indicateurs!$A:$A,0))&"") | E68: =IF($A68="","",INDEX(ref_indicateurs!$M:$M,MATCH($A68,ref_indicateurs!$A:$A,0))&"") | F68: =IF($A68="","",IF(INDEX(ref_indicateurs!$O:$O,MATCH($A68,ref_indicateurs!$A:$A,0))="","",INDEX(ref_indicateurs!$O:$O,MATCH($A68,ref_indicateurs!$A:$A,0)))) | G68: =IF($A68="","",SUMIFS(saisie_hebdo!$L:$L,saisie_hebdo!$I:$I,$A68)) | H68: =IF($A68="","",SUMIFS(saisie_hebdo!$M:$M,saisie_hebdo!$I:$I,$A68)) | I68: =IF(OR($A68="",L68=0),"",IF(D68="Pourcentage",IF(H68>0,G68/H68*100,""),G68)) | J68: =IF(OR(I68="",F68="",F68=0),"",I68/F68) | K68: =IF(OR($A68="",L68=0),"",IF(_xlfn.MAXIFS(saisie_hebdo!$C:$C,saisie_hebdo!$I:$I,$A68)=0,"",_xlfn.MAXIFS(saisie_hebdo!$C:$C,saisie_hebdo!$I:$I,$A68))) | L68: =IF($A68="","",COUNTIFS(saisie_hebdo!$I:$I,$A68)) | M68: =IF($A68="","",IF(L68=0,"Non rapporté",IF(F68="","Suivi sans cible",IF(D68="Pourcentage",IF(I68>=F68,"Cible atteinte","Sous la cible"),IF(J68>=1,"Cible atteinte","En cours")))))
A69: =IFERROR(INDEX(ref_indicateurs!$A:$A,66)&"","") | B69: =IF($A69="","",INDEX(ref_indicateurs!$B:$B,MATCH($A69,ref_indicateurs!$A:$A,0))&"") | C69: =IF($A69="","",INDEX(ref_indicateurs!$C:$C,MATCH($A69,ref_indicateurs!$A:$A,0))&"") | D69: =IF($A69="","",INDEX(ref_indicateurs!$E:$E,MATCH($A69,ref_indicateurs!$A:$A,0))&"") | E69: =IF($A69="","",INDEX(ref_indicateurs!$M:$M,MATCH($A69,ref_indicateurs!$A:$A,0))&"") | F69: =IF($A69="","",IF(INDEX(ref_indicateurs!$O:$O,MATCH($A69,ref_indicateurs!$A:$A,0))="","",INDEX(ref_indicateurs!$O:$O,MATCH($A69,ref_indicateurs!$A:$A,0)))) | G69: =IF($A69="","",SUMIFS(saisie_hebdo!$L:$L,saisie_hebdo!$I:$I,$A69)) | H69: =IF($A69="","",SUMIFS(saisie_hebdo!$M:$M,saisie_hebdo!$I:$I,$A69)) | I69: =IF(OR($A69="",L69=0),"",IF(D69="Pourcentage",IF(H69>0,G69/H69*100,""),G69)) | J69: =IF(OR(I69="",F69="",F69=0),"",I69/F69) | K69: =IF(OR($A69="",L69=0),"",IF(_xlfn.MAXIFS(saisie_hebdo!$C:$C,saisie_hebdo!$I:$I,$A69)=0,"",_xlfn.MAXIFS(saisie_hebdo!$C:$C,saisie_hebdo!$I:$I,$A69))) | L69: =IF($A69="","",COUNTIFS(saisie_hebdo!$I:$I,$A69)) | M69: =IF($A69="","",IF(L69=0,"Non rapporté",IF(F69="","Suivi sans cible",IF(D69="Pourcentage",IF(I69>=F69,"Cible atteinte","Sous la cible"),IF(J69>=1,"Cible atteinte","En cours")))))
A70: =IFERROR(INDEX(ref_indicateurs!$A:$A,67)&"","") | B70: =IF($A70="","",INDEX(ref_indicateurs!$B:$B,MATCH($A70,ref_indicateurs!$A:$A,0))&"") | C70: =IF($A70="","",INDEX(ref_indicateurs!$C:$C,MATCH($A70,ref_indicateurs!$A:$A,0))&"") | D70: =IF($A70="","",INDEX(ref_indicateurs!$E:$E,MATCH($A70,ref_indicateurs!$A:$A,0))&"") | E70: =IF($A70="","",INDEX(ref_indicateurs!$M:$M,MATCH($A70,ref_indicateurs!$A:$A,0))&"") | F70: =IF($A70="","",IF(INDEX(ref_indicateurs!$O:$O,MATCH($A70,ref_indicateurs!$A:$A,0))="","",INDEX(ref_indicateurs!$O:$O,MATCH($A70,ref_indicateurs!$A:$A,0)))) | G70: =IF($A70="","",SUMIFS(saisie_hebdo!$L:$L,saisie_hebdo!$I:$I,$A70)) | H70: =IF($A70="","",SUMIFS(saisie_hebdo!$M:$M,saisie_hebdo!$I:$I,$A70)) | I70: =IF(OR($A70="",L70=0),"",IF(D70="Pourcentage",IF(H70>0,G70/H70*100,""),G70)) | J70: =IF(OR(I70="",F70="",F70=0),"",I70/F70) | K70: =IF(OR($A70="",L70=0),"",IF(_xlfn.MAXIFS(saisie_hebdo!$C:$C,saisie_hebdo!$I:$I,$A70)=0,"",_xlfn.MAXIFS(saisie_hebdo!$C:$C,saisie_hebdo!$I:$I,$A70))) | L70: =IF($A70="","",COUNTIFS(saisie_hebdo!$I:$I,$A70)) | M70: =IF($A70="","",IF(L70=0,"Non rapporté",IF(F70="","Suivi sans cible",IF(D70="Pourcentage",IF(I70>=F70,"Cible atteinte","Sous la cible"),IF(J70>=1,"Cible atteinte","En cours")))))
A71: =IFERROR(INDEX(ref_indicateurs!$A:$A,68)&"","") | B71: =IF($A71="","",INDEX(ref_indicateurs!$B:$B,MATCH($A71,ref_indicateurs!$A:$A,0))&"") | C71: =IF($A71="","",INDEX(ref_indicateurs!$C:$C,MATCH($A71,ref_indicateurs!$A:$A,0))&"") | D71: =IF($A71="","",INDEX(ref_indicateurs!$E:$E,MATCH($A71,ref_indicateurs!$A:$A,0))&"") | E71: =IF($A71="","",INDEX(ref_indicateurs!$M:$M,MATCH($A71,ref_indicateurs!$A:$A,0))&"") | F71: =IF($A71="","",IF(INDEX(ref_indicateurs!$O:$O,MATCH($A71,ref_indicateurs!$A:$A,0))="","",INDEX(ref_indicateurs!$O:$O,MATCH($A71,ref_indicateurs!$A:$A,0)))) | G71: =IF($A71="","",SUMIFS(saisie_hebdo!$L:$L,saisie_hebdo!$I:$I,$A71)) | H71: =IF($A71="","",SUMIFS(saisie_hebdo!$M:$M,saisie_hebdo!$I:$I,$A71)) | I71: =IF(OR($A71="",L71=0),"",IF(D71="Pourcentage",IF(H71>0,G71/H71*100,""),G71)) | J71: =IF(OR(I71="",F71="",F71=0),"",I71/F71) | K71: =IF(OR($A71="",L71=0),"",IF(_xlfn.MAXIFS(saisie_hebdo!$C:$C,saisie_hebdo!$I:$I,$A71)=0,"",_xlfn.MAXIFS(saisie_hebdo!$C:$C,saisie_hebdo!$I:$I,$A71))) | L71: =IF($A71="","",COUNTIFS(saisie_hebdo!$I:$I,$A71)) | M71: =IF($A71="","",IF(L71=0,"Non rapporté",IF(F71="","Suivi sans cible",IF(D71="Pourcentage",IF(I71>=F71,"Cible atteinte","Sous la cible"),IF(J71>=1,"Cible atteinte","En cours")))))
A72: =IFERROR(INDEX(ref_indicateurs!$A:$A,69)&"","") | B72: =IF($A72="","",INDEX(ref_indicateurs!$B:$B,MATCH($A72,ref_indicateurs!$A:$A,0))&"") | C72: =IF($A72="","",INDEX(ref_indicateurs!$C:$C,MATCH($A72,ref_indicateurs!$A:$A,0))&"") | D72: =IF($A72="","",INDEX(ref_indicateurs!$E:$E,MATCH($A72,ref_indicateurs!$A:$A,0))&"") | E72: =IF($A72="","",INDEX(ref_indicateurs!$M:$M,MATCH($A72,ref_indicateurs!$A:$A,0))&"") | F72: =IF($A72="","",IF(INDEX(ref_indicateurs!$O:$O,MATCH($A72,ref_indicateurs!$A:$A,0))="","",INDEX(ref_indicateurs!$O:$O,MATCH($A72,ref_indicateurs!$A:$A,0)))) | G72: =IF($A72="","",SUMIFS(saisie_hebdo!$L:$L,saisie_hebdo!$I:$I,$A72)) | H72: =IF($A72="","",SUMIFS(saisie_hebdo!$M:$M,saisie_hebdo!$I:$I,$A72)) | I72: =IF(OR($A72="",L72=0),"",IF(D72="Pourcentage",IF(H72>0,G72/H72*100,""),G72)) | J72: =IF(OR(I72="",F72="",F72=0),"",I72/F72) | K72: =IF(OR($A72="",L72=0),"",IF(_xlfn.MAXIFS(saisie_hebdo!$C:$C,saisie_hebdo!$I:$I,$A72)=0,"",_xlfn.MAXIFS(saisie_hebdo!$C:$C,saisie_hebdo!$I:$I,$A72))) | L72: =IF($A72="","",COUNTIFS(saisie_hebdo!$I:$I,$A72)) | M72: =IF($A72="","",IF(L72=0,"Non rapporté",IF(F72="","Suivi sans cible",IF(D72="Pourcentage",IF(I72>=F72,"Cible atteinte","Sous la cible"),IF(J72>=1,"Cible atteinte","En cours")))))
A73: =IFERROR(INDEX(ref_indicateurs!$A:$A,70)&"","") | B73: =IF($A73="","",INDEX(ref_indicateurs!$B:$B,MATCH($A73,ref_indicateurs!$A:$A,0))&"") | C73: =IF($A73="","",INDEX(ref_indicateurs!$C:$C,MATCH($A73,ref_indicateurs!$A:$A,0))&"") | D73: =IF($A73="","",INDEX(ref_indicateurs!$E:$E,MATCH($A73,ref_indicateurs!$A:$A,0))&"") | E73: =IF($A73="","",INDEX(ref_indicateurs!$M:$M,MATCH($A73,ref_indicateurs!$A:$A,0))&"") | F73: =IF($A73="","",IF(INDEX(ref_indicateurs!$O:$O,MATCH($A73,ref_indicateurs!$A:$A,0))="","",INDEX(ref_indicateurs!$O:$O,MATCH($A73,ref_indicateurs!$A:$A,0)))) | G73: =IF($A73="","",SUMIFS(saisie_hebdo!$L:$L,saisie_hebdo!$I:$I,$A73)) | H73: =IF($A73="","",SUMIFS(saisie_hebdo!$M:$M,saisie_hebdo!$I:$I,$A73)) | I73: =IF(OR($A73="",L73=0),"",IF(D73="Pourcentage",IF(H73>0,G73/H73*100,""),G73)) | J73: =IF(OR(I73="",F73="",F73=0),"",I73/F73) | K73: =IF(OR($A73="",L73=0),"",IF(_xlfn.MAXIFS(saisie_hebdo!$C:$C,saisie_hebdo!$I:$I,$A73)=0,"",_xlfn.MAXIFS(saisie_hebdo!$C:$C,saisie_hebdo!$I:$I,$A73))) | L73: =IF($A73="","",COUNTIFS(saisie_hebdo!$I:$I,$A73)) | M73: =IF($A73="","",IF(L73=0,"Non rapporté",IF(F73="","Suivi sans cible",IF(D73="Pourcentage",IF(I73>=F73,"Cible atteinte","Sous la cible"),IF(J73>=1,"Cible atteinte","En cours")))))
A74: =IFERROR(INDEX(ref_indicateurs!$A:$A,71)&"","") | B74: =IF($A74="","",INDEX(ref_indicateurs!$B:$B,MATCH($A74,ref_indicateurs!$A:$A,0))&"") | C74: =IF($A74="","",INDEX(ref_indicateurs!$C:$C,MATCH($A74,ref_indicateurs!$A:$A,0))&"") | D74: =IF($A74="","",INDEX(ref_indicateurs!$E:$E,MATCH($A74,ref_indicateurs!$A:$A,0))&"") | E74: =IF($A74="","",INDEX(ref_indicateurs!$M:$M,MATCH($A74,ref_indicateurs!$A:$A,0))&"") | F74: =IF($A74="","",IF(INDEX(ref_indicateurs!$O:$O,MATCH($A74,ref_indicateurs!$A:$A,0))="","",INDEX(ref_indicateurs!$O:$O,MATCH($A74,ref_indicateurs!$A:$A,0)))) | G74: =IF($A74="","",SUMIFS(saisie_hebdo!$L:$L,saisie_hebdo!$I:$I,$A74)) | H74: =IF($A74="","",SUMIFS(saisie_hebdo!$M:$M,saisie_hebdo!$I:$I,$A74)) | I74: =IF(OR($A74="",L74=0),"",IF(D74="Pourcentage",IF(H74>0,G74/H74*100,""),G74)) | J74: =IF(OR(I74="",F74="",F74=0),"",I74/F74) | K74: =IF(OR($A74="",L74=0),"",IF(_xlfn.MAXIFS(saisie_hebdo!$C:$C,saisie_hebdo!$I:$I,$A74)=0,"",_xlfn.MAXIFS(saisie_hebdo!$C:$C,saisie_hebdo!$I:$I,$A74))) | L74: =IF($A74="","",COUNTIFS(saisie_hebdo!$I:$I,$A74)) | M74: =IF($A74="","",IF(L74=0,"Non rapporté",IF(F74="","Suivi sans cible",IF(D74="Pourcentage",IF(I74>=F74,"Cible atteinte","Sous la cible"),IF(J74>=1,"Cible atteinte","En cours")))))
A75: =IFERROR(INDEX(ref_indicateurs!$A:$A,72)&"","") | B75: =IF($A75="","",INDEX(ref_indicateurs!$B:$B,MATCH($A75,ref_indicateurs!$A:$A,0))&"") | C75: =IF($A75="","",INDEX(ref_indicateurs!$C:$C,MATCH($A75,ref_indicateurs!$A:$A,0))&"") | D75: =IF($A75="","",INDEX(ref_indicateurs!$E:$E,MATCH($A75,ref_indicateurs!$A:$A,0))&"") | E75: =IF($A75="","",INDEX(ref_indicateurs!$M:$M,MATCH($A75,ref_indicateurs!$A:$A,0))&"") | F75: =IF($A75="","",IF(INDEX(ref_indicateurs!$O:$O,MATCH($A75,ref_indicateurs!$A:$A,0))="","",INDEX(ref_indicateurs!$O:$O,MATCH($A75,ref_indicateurs!$A:$A,0)))) | G75: =IF($A75="","",SUMIFS(saisie_hebdo!$L:$L,saisie_hebdo!$I:$I,$A75)) | H75: =IF($A75="","",SUMIFS(saisie_hebdo!$M:$M,saisie_hebdo!$I:$I,$A75)) | I75: =IF(OR($A75="",L75=0),"",IF(D75="Pourcentage",IF(H75>0,G75/H75*100,""),G75)) | J75: =IF(OR(I75="",F75="",F75=0),"",I75/F75) | K75: =IF(OR($A75="",L75=0),"",IF(_xlfn.MAXIFS(saisie_hebdo!$C:$C,saisie_hebdo!$I:$I,$A75)=0,"",_xlfn.MAXIFS(saisie_hebdo!$C:$C,saisie_hebdo!$I:$I,$A75))) | L75: =IF($A75="","",COUNTIFS(saisie_hebdo!$I:$I,$A75)) | M75: =IF($A75="","",IF(L75=0,"Non rapporté",IF(F75="","Suivi sans cible",IF(D75="Pourcentage",IF(I75>=F75,"Cible atteinte","Sous la cible"),IF(J75>=1,"Cible atteinte","En cours")))))
A76: =IFERROR(INDEX(ref_indicateurs!$A:$A,73)&"","") | B76: =IF($A76="","",INDEX(ref_indicateurs!$B:$B,MATCH($A76,ref_indicateurs!$A:$A,0))&"") | C76: =IF($A76="","",INDEX(ref_indicateurs!$C:$C,MATCH($A76,ref_indicateurs!$A:$A,0))&"") | D76: =IF($A76="","",INDEX(ref_indicateurs!$E:$E,MATCH($A76,ref_indicateurs!$A:$A,0))&"") | E76: =IF($A76="","",INDEX(ref_indicateurs!$M:$M,MATCH($A76,ref_indicateurs!$A:$A,0))&"") | F76: =IF($A76="","",IF(INDEX(ref_indicateurs!$O:$O,MATCH($A76,ref_indicateurs!$A:$A,0))="","",INDEX(ref_indicateurs!$O:$O,MATCH($A76,ref_indicateurs!$A:$A,0)))) | G76: =IF($A76="","",SUMIFS(saisie_hebdo!$L:$L,saisie_hebdo!$I:$I,$A76)) | H76: =IF($A76="","",SUMIFS(saisie_hebdo!$M:$M,saisie_hebdo!$I:$I,$A76)) | I76: =IF(OR($A76="",L76=0),"",IF(D76="Pourcentage",IF(H76>0,G76/H76*100,""),G76)) | J76: =IF(OR(I76="",F76="",F76=0),"",I76/F76) | K76: =IF(OR($A76="",L76=0),"",IF(_xlfn.MAXIFS(saisie_hebdo!$C:$C,saisie_hebdo!$I:$I,$A76)=0,"",_xlfn.MAXIFS(saisie_hebdo!$C:$C,saisie_hebdo!$I:$I,$A76))) | L76: =IF($A76="","",COUNTIFS(saisie_hebdo!$I:$I,$A76)) | M76: =IF($A76="","",IF(L76=0,"Non rapporté",IF(F76="","Suivi sans cible",IF(D76="Pourcentage",IF(I76>=F76,"Cible atteinte","Sous la cible"),IF(J76>=1,"Cible atteinte","En cours")))))
A77: =IFERROR(INDEX(ref_indicateurs!$A:$A,74)&"","") | B77: =IF($A77="","",INDEX(ref_indicateurs!$B:$B,MATCH($A77,ref_indicateurs!$A:$A,0))&"") | C77: =IF($A77="","",INDEX(ref_indicateurs!$C:$C,MATCH($A77,ref_indicateurs!$A:$A,0))&"") | D77: =IF($A77="","",INDEX(ref_indicateurs!$E:$E,MATCH($A77,ref_indicateurs!$A:$A,0))&"") | E77: =IF($A77="","",INDEX(ref_indicateurs!$M:$M,MATCH($A77,ref_indicateurs!$A:$A,0))&"") | F77: =IF($A77="","",IF(INDEX(ref_indicateurs!$O:$O,MATCH($A77,ref_indicateurs!$A:$A,0))="","",INDEX(ref_indicateurs!$O:$O,MATCH($A77,ref_indicateurs!$A:$A,0)))) | G77: =IF($A77="","",SUMIFS(saisie_hebdo!$L:$L,saisie_hebdo!$I:$I,$A77)) | H77: =IF($A77="","",SUMIFS(saisie_hebdo!$M:$M,saisie_hebdo!$I:$I,$A77)) | I77: =IF(OR($A77="",L77=0),"",IF(D77="Pourcentage",IF(H77>0,G77/H77*100,""),G77)) | J77: =IF(OR(I77="",F77="",F77=0),"",I77/F77) | K77: =IF(OR($A77="",L77=0),"",IF(_xlfn.MAXIFS(saisie_hebdo!$C:$C,saisie_hebdo!$I:$I,$A77)=0,"",_xlfn.MAXIFS(saisie_hebdo!$C:$C,saisie_hebdo!$I:$I,$A77))) | L77: =IF($A77="","",COUNTIFS(saisie_hebdo!$I:$I,$A77)) | M77: =IF($A77="","",IF(L77=0,"Non rapporté",IF(F77="","Suivi sans cible",IF(D77="Pourcentage",IF(I77>=F77,"Cible atteinte","Sous la cible"),IF(J77>=1,"Cible atteinte","En cours")))))
A78: =IFERROR(INDEX(ref_indicateurs!$A:$A,75)&"","") | B78: =IF($A78="","",INDEX(ref_indicateurs!$B:$B,MATCH($A78,ref_indicateurs!$A:$A,0))&"") | C78: =IF($A78="","",INDEX(ref_indicateurs!$C:$C,MATCH($A78,ref_indicateurs!$A:$A,0))&"") | D78: =IF($A78="","",INDEX(ref_indicateurs!$E:$E,MATCH($A78,ref_indicateurs!$A:$A,0))&"") | E78: =IF($A78="","",INDEX(ref_indicateurs!$M:$M,MATCH($A78,ref_indicateurs!$A:$A,0))&"") | F78: =IF($A78="","",IF(INDEX(ref_indicateurs!$O:$O,MATCH($A78,ref_indicateurs!$A:$A,0))="","",INDEX(ref_indicateurs!$O:$O,MATCH($A78,ref_indicateurs!$A:$A,0)))) | G78: =IF($A78="","",SUMIFS(saisie_hebdo!$L:$L,saisie_hebdo!$I:$I,$A78)) | H78: =IF($A78="","",SUMIFS(saisie_hebdo!$M:$M,saisie_hebdo!$I:$I,$A78)) | I78: =IF(OR($A78="",L78=0),"",IF(D78="Pourcentage",IF(H78>0,G78/H78*100,""),G78)) | J78: =IF(OR(I78="",F78="",F78=0),"",I78/F78) | K78: =IF(OR($A78="",L78=0),"",IF(_xlfn.MAXIFS(saisie_hebdo!$C:$C,saisie_hebdo!$I:$I,$A78)=0,"",_xlfn.MAXIFS(saisie_hebdo!$C:$C,saisie_hebdo!$I:$I,$A78))) | L78: =IF($A78="","",COUNTIFS(saisie_hebdo!$I:$I,$A78)) | M78: =IF($A78="","",IF(L78=0,"Non rapporté",IF(F78="","Suivi sans cible",IF(D78="Pourcentage",IF(I78>=F78,"Cible atteinte","Sous la cible"),IF(J78>=1,"Cible atteinte","En cours")))))
A79: =IFERROR(INDEX(ref_indicateurs!$A:$A,76)&"","") | B79: =IF($A79="","",INDEX(ref_indicateurs!$B:$B,MATCH($A79,ref_indicateurs!$A:$A,0))&"") | C79: =IF($A79="","",INDEX(ref_indicateurs!$C:$C,MATCH($A79,ref_indicateurs!$A:$A,0))&"") | D79: =IF($A79="","",INDEX(ref_indicateurs!$E:$E,MATCH($A79,ref_indicateurs!$A:$A,0))&"") | E79: =IF($A79="","",INDEX(ref_indicateurs!$M:$M,MATCH($A79,ref_indicateurs!$A:$A,0))&"") | F79: =IF($A79="","",IF(INDEX(ref_indicateurs!$O:$O,MATCH($A79,ref_indicateurs!$A:$A,0))="","",INDEX(ref_indicateurs!$O:$O,MATCH($A79,ref_indicateurs!$A:$A,0)))) | G79: =IF($A79="","",SUMIFS(saisie_hebdo!$L:$L,saisie_hebdo!$I:$I,$A79)) | H79: =IF($A79="","",SUMIFS(saisie_hebdo!$M:$M,saisie_hebdo!$I:$I,$A79)) | I79: =IF(OR($A79="",L79=0),"",IF(D79="Pourcentage",IF(H79>0,G79/H79*100,""),G79)) | J79: =IF(OR(I79="",F79="",F79=0),"",I79/F79) | K79: =IF(OR($A79="",L79=0),"",IF(_xlfn.MAXIFS(saisie_hebdo!$C:$C,saisie_hebdo!$I:$I,$A79)=0,"",_xlfn.MAXIFS(saisie_hebdo!$C:$C,saisie_hebdo!$I:$I,$A79))) | L79: =IF($A79="","",COUNTIFS(saisie_hebdo!$I:$I,$A79)) | M79: =IF($A79="","",IF(L79=0,"Non rapporté",IF(F79="","Suivi sans cible",IF(D79="Pourcentage",IF(I79>=F79,"Cible atteinte","Sous la cible"),IF(J79>=1,"Cible atteinte","En cours")))))
A80: =IFERROR(INDEX(ref_indicateurs!$A:$A,77)&"","") | B80: =IF($A80="","",INDEX(ref_indicateurs!$B:$B,MATCH($A80,ref_indicateurs!$A:$A,0))&"") | C80: =IF($A80="","",INDEX(ref_indicateurs!$C:$C,MATCH($A80,ref_indicateurs!$A:$A,0))&"") | D80: =IF($A80="","",INDEX(ref_indicateurs!$E:$E,MATCH($A80,ref_indicateurs!$A:$A,0))&"") | E80: =IF($A80="","",INDEX(ref_indicateurs!$M:$M,MATCH($A80,ref_indicateurs!$A:$A,0))&"") | F80: =IF($A80="","",IF(INDEX(ref_indicateurs!$O:$O,MATCH($A80,ref_indicateurs!$A:$A,0))="","",INDEX(ref_indicateurs!$O:$O,MATCH($A80,ref_indicateurs!$A:$A,0)))) | G80: =IF($A80="","",SUMIFS(saisie_hebdo!$L:$L,saisie_hebdo!$I:$I,$A80)) | H80: =IF($A80="","",SUMIFS(saisie_hebdo!$M:$M,saisie_hebdo!$I:$I,$A80)) | I80: =IF(OR($A80="",L80=0),"",IF(D80="Pourcentage",IF(H80>0,G80/H80*100,""),G80)) | J80: =IF(OR(I80="",F80="",F80=0),"",I80/F80) | K80: =IF(OR($A80="",L80=0),"",IF(_xlfn.MAXIFS(saisie_hebdo!$C:$C,saisie_hebdo!$I:$I,$A80)=0,"",_xlfn.MAXIFS(saisie_hebdo!$C:$C,saisie_hebdo!$I:$I,$A80))) | L80: =IF($A80="","",COUNTIFS(saisie_hebdo!$I:$I,$A80)) | M80: =IF($A80="","",IF(L80=0,"Non rapporté",IF(F80="","Suivi sans cible",IF(D80="Pourcentage",IF(I80>=F80,"Cible atteinte","Sous la cible"),IF(J80>=1,"Cible atteinte","En cours")))))
A81: =IFERROR(INDEX(ref_indicateurs!$A:$A,78)&"","") | B81: =IF($A81="","",INDEX(ref_indicateurs!$B:$B,MATCH($A81,ref_indicateurs!$A:$A,0))&"") | C81: =IF($A81="","",INDEX(ref_indicateurs!$C:$C,MATCH($A81,ref_indicateurs!$A:$A,0))&"") | D81: =IF($A81="","",INDEX(ref_indicateurs!$E:$E,MATCH($A81,ref_indicateurs!$A:$A,0))&"") | E81: =IF($A81="","",INDEX(ref_indicateurs!$M:$M,MATCH($A81,ref_indicateurs!$A:$A,0))&"") | F81: =IF($A81="","",IF(INDEX(ref_indicateurs!$O:$O,MATCH($A81,ref_indicateurs!$A:$A,0))="","",INDEX(ref_indicateurs!$O:$O,MATCH($A81,ref_indicateurs!$A:$A,0)))) | G81: =IF($A81="","",SUMIFS(saisie_hebdo!$L:$L,saisie_hebdo!$I:$I,$A81)) | H81: =IF($A81="","",SUMIFS(saisie_hebdo!$M:$M,saisie_hebdo!$I:$I,$A81)) | I81: =IF(OR($A81="",L81=0),"",IF(D81="Pourcentage",IF(H81>0,G81/H81*100,""),G81)) | J81: =IF(OR(I81="",F81="",F81=0),"",I81/F81) | K81: =IF(OR($A81="",L81=0),"",IF(_xlfn.MAXIFS(saisie_hebdo!$C:$C,saisie_hebdo!$I:$I,$A81)=0,"",_xlfn.MAXIFS(saisie_hebdo!$C:$C,saisie_hebdo!$I:$I,$A81))) | L81: =IF($A81="","",COUNTIFS(saisie_hebdo!$I:$I,$A81)) | M81: =IF($A81="","",IF(L81=0,"Non rapporté",IF(F81="","Suivi sans cible",IF(D81="Pourcentage",IF(I81>=F81,"Cible atteinte","Sous la cible"),IF(J81>=1,"Cible atteinte","En cours")))))
A82: =IFERROR(INDEX(ref_indicateurs!$A:$A,79)&"","") | B82: =IF($A82="","",INDEX(ref_indicateurs!$B:$B,MATCH($A82,ref_indicateurs!$A:$A,0))&"") | C82: =IF($A82="","",INDEX(ref_indicateurs!$C:$C,MATCH($A82,ref_indicateurs!$A:$A,0))&"") | D82: =IF($A82="","",INDEX(ref_indicateurs!$E:$E,MATCH($A82,ref_indicateurs!$A:$A,0))&"") | E82: =IF($A82="","",INDEX(ref_indicateurs!$M:$M,MATCH($A82,ref_indicateurs!$A:$A,0))&"") | F82: =IF($A82="","",IF(INDEX(ref_indicateurs!$O:$O,MATCH($A82,ref_indicateurs!$A:$A,0))="","",INDEX(ref_indicateurs!$O:$O,MATCH($A82,ref_indicateurs!$A:$A,0)))) | G82: =IF($A82="","",SUMIFS(saisie_hebdo!$L:$L,saisie_hebdo!$I:$I,$A82)) | H82: =IF($A82="","",SUMIFS(saisie_hebdo!$M:$M,saisie_hebdo!$I:$I,$A82)) | I82: =IF(OR($A82="",L82=0),"",IF(D82="Pourcentage",IF(H82>0,G82/H82*100,""),G82)) | J82: =IF(OR(I82="",F82="",F82=0),"",I82/F82) | K82: =IF(OR($A82="",L82=0),"",IF(_xlfn.MAXIFS(saisie_hebdo!$C:$C,saisie_hebdo!$I:$I,$A82)=0,"",_xlfn.MAXIFS(saisie_hebdo!$C:$C,saisie_hebdo!$I:$I,$A82))) | L82: =IF($A82="","",COUNTIFS(saisie_hebdo!$I:$I,$A82)) | M82: =IF($A82="","",IF(L82=0,"Non rapporté",IF(F82="","Suivi sans cible",IF(D82="Pourcentage",IF(I82>=F82,"Cible atteinte","Sous la cible"),IF(J82>=1,"Cible atteinte","En cours")))))
A83: =IFERROR(INDEX(ref_indicateurs!$A:$A,80)&"","") | B83: =IF($A83="","",INDEX(ref_indicateurs!$B:$B,MATCH($A83,ref_indicateurs!$A:$A,0))&"") | C83: =IF($A83="","",INDEX(ref_indicateurs!$C:$C,MATCH($A83,ref_indicateurs!$A:$A,0))&"") | D83: =IF($A83="","",INDEX(ref_indicateurs!$E:$E,MATCH($A83,ref_indicateurs!$A:$A,0))&"") | E83: =IF($A83="","",INDEX(ref_indicateurs!$M:$M,MATCH($A83,ref_indicateurs!$A:$A,0))&"") | F83: =IF($A83="","",IF(INDEX(ref_indicateurs!$O:$O,MATCH($A83,ref_indicateurs!$A:$A,0))="","",INDEX(ref_indicateurs!$O:$O,MATCH($A83,ref_indicateurs!$A:$A,0)))) | G83: =IF($A83="","",SUMIFS(saisie_hebdo!$L:$L,saisie_hebdo!$I:$I,$A83)) | H83: =IF($A83="","",SUMIFS(saisie_hebdo!$M:$M,saisie_hebdo!$I:$I,$A83)) | I83: =IF(OR($A83="",L83=0),"",IF(D83="Pourcentage",IF(H83>0,G83/H83*100,""),G83)) | J83: =IF(OR(I83="",F83="",F83=0),"",I83/F83) | K83: =IF(OR($A83="",L83=0),"",IF(_xlfn.MAXIFS(saisie_hebdo!$C:$C,saisie_hebdo!$I:$I,$A83)=0,"",_xlfn.MAXIFS(saisie_hebdo!$C:$C,saisie_hebdo!$I:$I,$A83))) | L83: =IF($A83="","",COUNTIFS(saisie_hebdo!$I:$I,$A83)) | M83: =IF($A83="","",IF(L83=0,"Non rapporté",IF(F83="","Suivi sans cible",IF(D83="Pourcentage",IF(I83>=F83,"Cible atteinte","Sous la cible"),IF(J83>=1,"Cible atteinte","En cours")))))
A84: =IFERROR(INDEX(ref_indicateurs!$A:$A,81)&"","") | B84: =IF($A84="","",INDEX(ref_indicateurs!$B:$B,MATCH($A84,ref_indicateurs!$A:$A,0))&"") | C84: =IF($A84="","",INDEX(ref_indicateurs!$C:$C,MATCH($A84,ref_indicateurs!$A:$A,0))&"") | D84: =IF($A84="","",INDEX(ref_indicateurs!$E:$E,MATCH($A84,ref_indicateurs!$A:$A,0))&"") | E84: =IF($A84="","",INDEX(ref_indicateurs!$M:$M,MATCH($A84,ref_indicateurs!$A:$A,0))&"") | F84: =IF($A84="","",IF(INDEX(ref_indicateurs!$O:$O,MATCH($A84,ref_indicateurs!$A:$A,0))="","",INDEX(ref_indicateurs!$O:$O,MATCH($A84,ref_indicateurs!$A:$A,0)))) | G84: =IF($A84="","",SUMIFS(saisie_hebdo!$L:$L,saisie_hebdo!$I:$I,$A84)) | H84: =IF($A84="","",SUMIFS(saisie_hebdo!$M:$M,saisie_hebdo!$I:$I,$A84)) | I84: =IF(OR($A84="",L84=0),"",IF(D84="Pourcentage",IF(H84>0,G84/H84*100,""),G84)) | J84: =IF(OR(I84="",F84="",F84=0),"",I84/F84) | K84: =IF(OR($A84="",L84=0),"",IF(_xlfn.MAXIFS(saisie_hebdo!$C:$C,saisie_hebdo!$I:$I,$A84)=0,"",_xlfn.MAXIFS(saisie_hebdo!$C:$C,saisie_hebdo!$I:$I,$A84))) | L84: =IF($A84="","",COUNTIFS(saisie_hebdo!$I:$I,$A84)) | M84: =IF($A84="","",IF(L84=0,"Non rapporté",IF(F84="","Suivi sans cible",IF(D84="Pourcentage",IF(I84>=F84,"Cible atteinte","Sous la cible"),IF(J84>=1,"Cible atteinte","En cours")))))
A85: =IFERROR(INDEX(ref_indicateurs!$A:$A,82)&"","") | B85: =IF($A85="","",INDEX(ref_indicateurs!$B:$B,MATCH($A85,ref_indicateurs!$A:$A,0))&"") | C85: =IF($A85="","",INDEX(ref_indicateurs!$C:$C,MATCH($A85,ref_indicateurs!$A:$A,0))&"") | D85: =IF($A85="","",INDEX(ref_indicateurs!$E:$E,MATCH($A85,ref_indicateurs!$A:$A,0))&"") | E85: =IF($A85="","",INDEX(ref_indicateurs!$M:$M,MATCH($A85,ref_indicateurs!$A:$A,0))&"") | F85: =IF($A85="","",IF(INDEX(ref_indicateurs!$O:$O,MATCH($A85,ref_indicateurs!$A:$A,0))="","",INDEX(ref_indicateurs!$O:$O,MATCH($A85,ref_indicateurs!$A:$A,0)))) | G85: =IF($A85="","",SUMIFS(saisie_hebdo!$L:$L,saisie_hebdo!$I:$I,$A85)) | H85: =IF($A85="","",SUMIFS(saisie_hebdo!$M:$M,saisie_hebdo!$I:$I,$A85)) | I85: =IF(OR($A85="",L85=0),"",IF(D85="Pourcentage",IF(H85>0,G85/H85*100,""),G85)) | J85: =IF(OR(I85="",F85="",F85=0),"",I85/F85) | K85: =IF(OR($A85="",L85=0),"",IF(_xlfn.MAXIFS(saisie_hebdo!$C:$C,saisie_hebdo!$I:$I,$A85)=0,"",_xlfn.MAXIFS(saisie_hebdo!$C:$C,saisie_hebdo!$I:$I,$A85))) | L85: =IF($A85="","",COUNTIFS(saisie_hebdo!$I:$I,$A85)) | M85: =IF($A85="","",IF(L85=0,"Non rapporté",IF(F85="","Suivi sans cible",IF(D85="Pourcentage",IF(I85>=F85,"Cible atteinte","Sous la cible"),IF(J85>=1,"Cible atteinte","En cours")))))
A86: =IFERROR(INDEX(ref_indicateurs!$A:$A,83)&"","") | B86: =IF($A86="","",INDEX(ref_indicateurs!$B:$B,MATCH($A86,ref_indicateurs!$A:$A,0))&"") | C86: =IF($A86="","",INDEX(ref_indicateurs!$C:$C,MATCH($A86,ref_indicateurs!$A:$A,0))&"") | D86: =IF($A86="","",INDEX(ref_indicateurs!$E:$E,MATCH($A86,ref_indicateurs!$A:$A,0))&"") | E86: =IF($A86="","",INDEX(ref_indicateurs!$M:$M,MATCH($A86,ref_indicateurs!$A:$A,0))&"") | F86: =IF($A86="","",IF(INDEX(ref_indicateurs!$O:$O,MATCH($A86,ref_indicateurs!$A:$A,0))="","",INDEX(ref_indicateurs!$O:$O,MATCH($A86,ref_indicateurs!$A:$A,0)))) | G86: =IF($A86="","",SUMIFS(saisie_hebdo!$L:$L,saisie_hebdo!$I:$I,$A86)) | H86: =IF($A86="","",SUMIFS(saisie_hebdo!$M:$M,saisie_hebdo!$I:$I,$A86)) | I86: =IF(OR($A86="",L86=0),"",IF(D86="Pourcentage",IF(H86>0,G86/H86*100,""),G86)) | J86: =IF(OR(I86="",F86="",F86=0),"",I86/F86) | K86: =IF(OR($A86="",L86=0),"",IF(_xlfn.MAXIFS(saisie_hebdo!$C:$C,saisie_hebdo!$I:$I,$A86)=0,"",_xlfn.MAXIFS(saisie_hebdo!$C:$C,saisie_hebdo!$I:$I,$A86))) | L86: =IF($A86="","",COUNTIFS(saisie_hebdo!$I:$I,$A86)) | M86: =IF($A86="","",IF(L86=0,"Non rapporté",IF(F86="","Suivi sans cible",IF(D86="Pourcentage",IF(I86>=F86,"Cible atteinte","Sous la cible"),IF(J86>=1,"Cible atteinte","En cours")))))
A87: =IFERROR(INDEX(ref_indicateurs!$A:$A,84)&"","") | B87: =IF($A87="","",INDEX(ref_indicateurs!$B:$B,MATCH($A87,ref_indicateurs!$A:$A,0))&"") | C87: =IF($A87="","",INDEX(ref_indicateurs!$C:$C,MATCH($A87,ref_indicateurs!$A:$A,0))&"") | D87: =IF($A87="","",INDEX(ref_indicateurs!$E:$E,MATCH($A87,ref_indicateurs!$A:$A,0))&"") | E87: =IF($A87="","",INDEX(ref_indicateurs!$M:$M,MATCH($A87,ref_indicateurs!$A:$A,0))&"") | F87: =IF($A87="","",IF(INDEX(ref_indicateurs!$O:$O,MATCH($A87,ref_indicateurs!$A:$A,0))="","",INDEX(ref_indicateurs!$O:$O,MATCH($A87,ref_indicateurs!$A:$A,0)))) | G87: =IF($A87="","",SUMIFS(saisie_hebdo!$L:$L,saisie_hebdo!$I:$I,$A87)) | H87: =IF($A87="","",SUMIFS(saisie_hebdo!$M:$M,saisie_hebdo!$I:$I,$A87)) | I87: =IF(OR($A87="",L87=0),"",IF(D87="Pourcentage",IF(H87>0,G87/H87*100,""),G87)) | J87: =IF(OR(I87="",F87="",F87=0),"",I87/F87) | K87: =IF(OR($A87="",L87=0),"",IF(_xlfn.MAXIFS(saisie_hebdo!$C:$C,saisie_hebdo!$I:$I,$A87)=0,"",_xlfn.MAXIFS(saisie_hebdo!$C:$C,saisie_hebdo!$I:$I,$A87))) | L87: =IF($A87="","",COUNTIFS(saisie_hebdo!$I:$I,$A87)) | M87: =IF($A87="","",IF(L87=0,"Non rapporté",IF(F87="","Suivi sans cible",IF(D87="Pourcentage",IF(I87>=F87,"Cible atteinte","Sous la cible"),IF(J87>=1,"Cible atteinte","En cours")))))
A88: =IFERROR(INDEX(ref_indicateurs!$A:$A,85)&"","") | B88: =IF($A88="","",INDEX(ref_indicateurs!$B:$B,MATCH($A88,ref_indicateurs!$A:$A,0))&"") | C88: =IF($A88="","",INDEX(ref_indicateurs!$C:$C,MATCH($A88,ref_indicateurs!$A:$A,0))&"") | D88: =IF($A88="","",INDEX(ref_indicateurs!$E:$E,MATCH($A88,ref_indicateurs!$A:$A,0))&"") | E88: =IF($A88="","",INDEX(ref_indicateurs!$M:$M,MATCH($A88,ref_indicateurs!$A:$A,0))&"") | F88: =IF($A88="","",IF(INDEX(ref_indicateurs!$O:$O,MATCH($A88,ref_indicateurs!$A:$A,0))="","",INDEX(ref_indicateurs!$O:$O,MATCH($A88,ref_indicateurs!$A:$A,0)))) | G88: =IF($A88="","",SUMIFS(saisie_hebdo!$L:$L,saisie_hebdo!$I:$I,$A88)) | H88: =IF($A88="","",SUMIFS(saisie_hebdo!$M:$M,saisie_hebdo!$I:$I,$A88)) | I88: =IF(OR($A88="",L88=0),"",IF(D88="Pourcentage",IF(H88>0,G88/H88*100,""),G88)) | J88: =IF(OR(I88="",F88="",F88=0),"",I88/F88) | K88: =IF(OR($A88="",L88=0),"",IF(_xlfn.MAXIFS(saisie_hebdo!$C:$C,saisie_hebdo!$I:$I,$A88)=0,"",_xlfn.MAXIFS(saisie_hebdo!$C:$C,saisie_hebdo!$I:$I,$A88))) | L88: =IF($A88="","",COUNTIFS(saisie_hebdo!$I:$I,$A88)) | M88: =IF($A88="","",IF(L88=0,"Non rapporté",IF(F88="","Suivi sans cible",IF(D88="Pourcentage",IF(I88>=F88,"Cible atteinte","Sous la cible"),IF(J88>=1,"Cible atteinte","En cours")))))
A89: =IFERROR(INDEX(ref_indicateurs!$A:$A,86)&"","") | B89: =IF($A89="","",INDEX(ref_indicateurs!$B:$B,MATCH($A89,ref_indicateurs!$A:$A,0))&"") | C89: =IF($A89="","",INDEX(ref_indicateurs!$C:$C,MATCH($A89,ref_indicateurs!$A:$A,0))&"") | D89: =IF($A89="","",INDEX(ref_indicateurs!$E:$E,MATCH($A89,ref_indicateurs!$A:$A,0))&"") | E89: =IF($A89="","",INDEX(ref_indicateurs!$M:$M,MATCH($A89,ref_indicateurs!$A:$A,0))&"") | F89: =IF($A89="","",IF(INDEX(ref_indicateurs!$O:$O,MATCH($A89,ref_indicateurs!$A:$A,0))="","",INDEX(ref_indicateurs!$O:$O,MATCH($A89,ref_indicateurs!$A:$A,0)))) | G89: =IF($A89="","",SUMIFS(saisie_hebdo!$L:$L,saisie_hebdo!$I:$I,$A89)) | H89: =IF($A89="","",SUMIFS(saisie_hebdo!$M:$M,saisie_hebdo!$I:$I,$A89)) | I89: =IF(OR($A89="",L89=0),"",IF(D89="Pourcentage",IF(H89>0,G89/H89*100,""),G89)) | J89: =IF(OR(I89="",F89="",F89=0),"",I89/F89) | K89: =IF(OR($A89="",L89=0),"",IF(_xlfn.MAXIFS(saisie_hebdo!$C:$C,saisie_hebdo!$I:$I,$A89)=0,"",_xlfn.MAXIFS(saisie_hebdo!$C:$C,saisie_hebdo!$I:$I,$A89))) | L89: =IF($A89="","",COUNTIFS(saisie_hebdo!$I:$I,$A89)) | M89: =IF($A89="","",IF(L89=0,"Non rapporté",IF(F89="","Suivi sans cible",IF(D89="Pourcentage",IF(I89>=F89,"Cible atteinte","Sous la cible"),IF(J89>=1,"Cible atteinte","En cours")))))
A90: =IFERROR(INDEX(ref_indicateurs!$A:$A,87)&"","") | B90: =IF($A90="","",INDEX(ref_indicateurs!$B:$B,MATCH($A90,ref_indicateurs!$A:$A,0))&"") | C90: =IF($A90="","",INDEX(ref_indicateurs!$C:$C,MATCH($A90,ref_indicateurs!$A:$A,0))&"") | D90: =IF($A90="","",INDEX(ref_indicateurs!$E:$E,MATCH($A90,ref_indicateurs!$A:$A,0))&"") | E90: =IF($A90="","",INDEX(ref_indicateurs!$M:$M,MATCH($A90,ref_indicateurs!$A:$A,0))&"") | F90: =IF($A90="","",IF(INDEX(ref_indicateurs!$O:$O,MATCH($A90,ref_indicateurs!$A:$A,0))="","",INDEX(ref_indicateurs!$O:$O,MATCH($A90,ref_indicateurs!$A:$A,0)))) | G90: =IF($A90="","",SUMIFS(saisie_hebdo!$L:$L,saisie_hebdo!$I:$I,$A90)) | H90: =IF($A90="","",SUMIFS(saisie_hebdo!$M:$M,saisie_hebdo!$I:$I,$A90)) | I90: =IF(OR($A90="",L90=0),"",IF(D90="Pourcentage",IF(H90>0,G90/H90*100,""),G90)) | J90: =IF(OR(I90="",F90="",F90=0),"",I90/F90) | K90: =IF(OR($A90="",L90=0),"",IF(_xlfn.MAXIFS(saisie_hebdo!$C:$C,saisie_hebdo!$I:$I,$A90)=0,"",_xlfn.MAXIFS(saisie_hebdo!$C:$C,saisie_hebdo!$I:$I,$A90))) | L90: =IF($A90="","",COUNTIFS(saisie_hebdo!$I:$I,$A90)) | M90: =IF($A90="","",IF(L90=0,"Non rapporté",IF(F90="","Suivi sans cible",IF(D90="Pourcentage",IF(I90>=F90,"Cible atteinte","Sous la cible"),IF(J90>=1,"Cible atteinte","En cours")))))
A91: =IFERROR(INDEX(ref_indicateurs!$A:$A,88)&"","") | B91: =IF($A91="","",INDEX(ref_indicateurs!$B:$B,MATCH($A91,ref_indicateurs!$A:$A,0))&"") | C91: =IF($A91="","",INDEX(ref_indicateurs!$C:$C,MATCH($A91,ref_indicateurs!$A:$A,0))&"") | D91: =IF($A91="","",INDEX(ref_indicateurs!$E:$E,MATCH($A91,ref_indicateurs!$A:$A,0))&"") | E91: =IF($A91="","",INDEX(ref_indicateurs!$M:$M,MATCH($A91,ref_indicateurs!$A:$A,0))&"") | F91: =IF($A91="","",IF(INDEX(ref_indicateurs!$O:$O,MATCH($A91,ref_indicateurs!$A:$A,0))="","",INDEX(ref_indicateurs!$O:$O,MATCH($A91,ref_indicateurs!$A:$A,0)))) | G91: =IF($A91="","",SUMIFS(saisie_hebdo!$L:$L,saisie_hebdo!$I:$I,$A91)) | H91: =IF($A91="","",SUMIFS(saisie_hebdo!$M:$M,saisie_hebdo!$I:$I,$A91)) | I91: =IF(OR($A91="",L91=0),"",IF(D91="Pourcentage",IF(H91>0,G91/H91*100,""),G91)) | J91: =IF(OR(I91="",F91="",F91=0),"",I91/F91) | K91: =IF(OR($A91="",L91=0),"",IF(_xlfn.MAXIFS(saisie_hebdo!$C:$C,saisie_hebdo!$I:$I,$A91)=0,"",_xlfn.MAXIFS(saisie_hebdo!$C:$C,saisie_hebdo!$I:$I,$A91))) | L91: =IF($A91="","",COUNTIFS(saisie_hebdo!$I:$I,$A91)) | M91: =IF($A91="","",IF(L91=0,"Non rapporté",IF(F91="","Suivi sans cible",IF(D91="Pourcentage",IF(I91>=F91,"Cible atteinte","Sous la cible"),IF(J91>=1,"Cible atteinte","En cours")))))
A92: =IFERROR(INDEX(ref_indicateurs!$A:$A,89)&"","") | B92: =IF($A92="","",INDEX(ref_indicateurs!$B:$B,MATCH($A92,ref_indicateurs!$A:$A,0))&"") | C92: =IF($A92="","",INDEX(ref_indicateurs!$C:$C,MATCH($A92,ref_indicateurs!$A:$A,0))&"") | D92: =IF($A92="","",INDEX(ref_indicateurs!$E:$E,MATCH($A92,ref_indicateurs!$A:$A,0))&"") | E92: =IF($A92="","",INDEX(ref_indicateurs!$M:$M,MATCH($A92,ref_indicateurs!$A:$A,0))&"") | F92: =IF($A92="","",IF(INDEX(ref_indicateurs!$O:$O,MATCH($A92,ref_indicateurs!$A:$A,0))="","",INDEX(ref_indicateurs!$O:$O,MATCH($A92,ref_indicateurs!$A:$A,0)))) | G92: =IF($A92="","",SUMIFS(saisie_hebdo!$L:$L,saisie_hebdo!$I:$I,$A92)) | H92: =IF($A92="","",SUMIFS(saisie_hebdo!$M:$M,saisie_hebdo!$I:$I,$A92)) | I92: =IF(OR($A92="",L92=0),"",IF(D92="Pourcentage",IF(H92>0,G92/H92*100,""),G92)) | J92: =IF(OR(I92="",F92="",F92=0),"",I92/F92) | K92: =IF(OR($A92="",L92=0),"",IF(_xlfn.MAXIFS(saisie_hebdo!$C:$C,saisie_hebdo!$I:$I,$A92)=0,"",_xlfn.MAXIFS(saisie_hebdo!$C:$C,saisie_hebdo!$I:$I,$A92))) | L92: =IF($A92="","",COUNTIFS(saisie_hebdo!$I:$I,$A92)) | M92: =IF($A92="","",IF(L92=0,"Non rapporté",IF(F92="","Suivi sans cible",IF(D92="Pourcentage",IF(I92>=F92,"Cible atteinte","Sous la cible"),IF(J92>=1,"Cible atteinte","En cours")))))
A93: =IFERROR(INDEX(ref_indicateurs!$A:$A,90)&"","") | B93: =IF($A93="","",INDEX(ref_indicateurs!$B:$B,MATCH($A93,ref_indicateurs!$A:$A,0))&"") | C93: =IF($A93="","",INDEX(ref_indicateurs!$C:$C,MATCH($A93,ref_indicateurs!$A:$A,0))&"") | D93: =IF($A93="","",INDEX(ref_indicateurs!$E:$E,MATCH($A93,ref_indicateurs!$A:$A,0))&"") | E93: =IF($A93="","",INDEX(ref_indicateurs!$M:$M,MATCH($A93,ref_indicateurs!$A:$A,0))&"") | F93: =IF($A93="","",IF(INDEX(ref_indicateurs!$O:$O,MATCH($A93,ref_indicateurs!$A:$A,0))="","",INDEX(ref_indicateurs!$O:$O,MATCH($A93,ref_indicateurs!$A:$A,0)))) | G93: =IF($A93="","",SUMIFS(saisie_hebdo!$L:$L,saisie_hebdo!$I:$I,$A93)) | H93: =IF($A93="","",SUMIFS(saisie_hebdo!$M:$M,saisie_hebdo!$I:$I,$A93)) | I93: =IF(OR($A93="",L93=0),"",IF(D93="Pourcentage",IF(H93>0,G93/H93*100,""),G93)) | J93: =IF(OR(I93="",F93="",F93=0),"",I93/F93) | K93: =IF(OR($A93="",L93=0),"",IF(_xlfn.MAXIFS(saisie_hebdo!$C:$C,saisie_hebdo!$I:$I,$A93)=0,"",_xlfn.MAXIFS(saisie_hebdo!$C:$C,saisie_hebdo!$I:$I,$A93))) | L93: =IF($A93="","",COUNTIFS(saisie_hebdo!$I:$I,$A93)) | M93: =IF($A93="","",IF(L93=0,"Non rapporté",IF(F93="","Suivi sans cible",IF(D93="Pourcentage",IF(I93>=F93,"Cible atteinte","Sous la cible"),IF(J93>=1,"Cible atteinte","En cours")))))
A94: =IFERROR(INDEX(ref_indicateurs!$A:$A,91)&"","") | B94: =IF($A94="","",INDEX(ref_indicateurs!$B:$B,MATCH($A94,ref_indicateurs!$A:$A,0))&"") | C94: =IF($A94="","",INDEX(ref_indicateurs!$C:$C,MATCH($A94,ref_indicateurs!$A:$A,0))&"") | D94: =IF($A94="","",INDEX(ref_indicateurs!$E:$E,MATCH($A94,ref_indicateurs!$A:$A,0))&"") | E94: =IF($A94="","",INDEX(ref_indicateurs!$M:$M,MATCH($A94,ref_indicateurs!$A:$A,0))&"") | F94: =IF($A94="","",IF(INDEX(ref_indicateurs!$O:$O,MATCH($A94,ref_indicateurs!$A:$A,0))="","",INDEX(ref_indicateurs!$O:$O,MATCH($A94,ref_indicateurs!$A:$A,0)))) | G94: =IF($A94="","",SUMIFS(saisie_hebdo!$L:$L,saisie_hebdo!$I:$I,$A94)) | H94: =IF($A94="","",SUMIFS(saisie_hebdo!$M:$M,saisie_hebdo!$I:$I,$A94)) | I94: =IF(OR($A94="",L94=0),"",IF(D94="Pourcentage",IF(H94>0,G94/H94*100,""),G94)) | J94: =IF(OR(I94="",F94="",F94=0),"",I94/F94) | K94: =IF(OR($A94="",L94=0),"",IF(_xlfn.MAXIFS(saisie_hebdo!$C:$C,saisie_hebdo!$I:$I,$A94)=0,"",_xlfn.MAXIFS(saisie_hebdo!$C:$C,saisie_hebdo!$I:$I,$A94))) | L94: =IF($A94="","",COUNTIFS(saisie_hebdo!$I:$I,$A94)) | M94: =IF($A94="","",IF(L94=0,"Non rapporté",IF(F94="","Suivi sans cible",IF(D94="Pourcentage",IF(I94>=F94,"Cible atteinte","Sous la cible"),IF(J94>=1,"Cible atteinte","En cours")))))
A95: =IFERROR(INDEX(ref_indicateurs!$A:$A,92)&"","") | B95: =IF($A95="","",INDEX(ref_indicateurs!$B:$B,MATCH($A95,ref_indicateurs!$A:$A,0))&"") | C95: =IF($A95="","",INDEX(ref_indicateurs!$C:$C,MATCH($A95,ref_indicateurs!$A:$A,0))&"") | D95: =IF($A95="","",INDEX(ref_indicateurs!$E:$E,MATCH($A95,ref_indicateurs!$A:$A,0))&"") | E95: =IF($A95="","",INDEX(ref_indicateurs!$M:$M,MATCH($A95,ref_indicateurs!$A:$A,0))&"") | F95: =IF($A95="","",IF(INDEX(ref_indicateurs!$O:$O,MATCH($A95,ref_indicateurs!$A:$A,0))="","",INDEX(ref_indicateurs!$O:$O,MATCH($A95,ref_indicateurs!$A:$A,0)))) | G95: =IF($A95="","",SUMIFS(saisie_hebdo!$L:$L,saisie_hebdo!$I:$I,$A95)) | H95: =IF($A95="","",SUMIFS(saisie_hebdo!$M:$M,saisie_hebdo!$I:$I,$A95)) | I95: =IF(OR($A95="",L95=0),"",IF(D95="Pourcentage",IF(H95>0,G95/H95*100,""),G95)) | J95: =IF(OR(I95="",F95="",F95=0),"",I95/F95) | K95: =IF(OR($A95="",L95=0),"",IF(_xlfn.MAXIFS(saisie_hebdo!$C:$C,saisie_hebdo!$I:$I,$A95)=0,"",_xlfn.MAXIFS(saisie_hebdo!$C:$C,saisie_hebdo!$I:$I,$A95))) | L95: =IF($A95="","",COUNTIFS(saisie_hebdo!$I:$I,$A95)) | M95: =IF($A95="","",IF(L95=0,"Non rapporté",IF(F95="","Suivi sans cible",IF(D95="Pourcentage",IF(I95>=F95,"Cible atteinte","Sous la cible"),IF(J95>=1,"Cible atteinte","En cours")))))
A96: =IFERROR(INDEX(ref_indicateurs!$A:$A,93)&"","") | B96: =IF($A96="","",INDEX(ref_indicateurs!$B:$B,MATCH($A96,ref_indicateurs!$A:$A,0))&"") | C96: =IF($A96="","",INDEX(ref_indicateurs!$C:$C,MATCH($A96,ref_indicateurs!$A:$A,0))&"") | D96: =IF($A96="","",INDEX(ref_indicateurs!$E:$E,MATCH($A96,ref_indicateurs!$A:$A,0))&"") | E96: =IF($A96="","",INDEX(ref_indicateurs!$M:$M,MATCH($A96,ref_indicateurs!$A:$A,0))&"") | F96: =IF($A96="","",IF(INDEX(ref_indicateurs!$O:$O,MATCH($A96,ref_indicateurs!$A:$A,0))="","",INDEX(ref_indicateurs!$O:$O,MATCH($A96,ref_indicateurs!$A:$A,0)))) | G96: =IF($A96="","",SUMIFS(saisie_hebdo!$L:$L,saisie_hebdo!$I:$I,$A96)) | H96: =IF($A96="","",SUMIFS(saisie_hebdo!$M:$M,saisie_hebdo!$I:$I,$A96)) | I96: =IF(OR($A96="",L96=0),"",IF(D96="Pourcentage",IF(H96>0,G96/H96*100,""),G96)) | J96: =IF(OR(I96="",F96="",F96=0),"",I96/F96) | K96: =IF(OR($A96="",L96=0),"",IF(_xlfn.MAXIFS(saisie_hebdo!$C:$C,saisie_hebdo!$I:$I,$A96)=0,"",_xlfn.MAXIFS(saisie_hebdo!$C:$C,saisie_hebdo!$I:$I,$A96))) | L96: =IF($A96="","",COUNTIFS(saisie_hebdo!$I:$I,$A96)) | M96: =IF($A96="","",IF(L96=0,"Non rapporté",IF(F96="","Suivi sans cible",IF(D96="Pourcentage",IF(I96>=F96,"Cible atteinte","Sous la cible"),IF(J96>=1,"Cible atteinte","En cours")))))
A97: =IFERROR(INDEX(ref_indicateurs!$A:$A,94)&"","") | B97: =IF($A97="","",INDEX(ref_indicateurs!$B:$B,MATCH($A97,ref_indicateurs!$A:$A,0))&"") | C97: =IF($A97="","",INDEX(ref_indicateurs!$C:$C,MATCH($A97,ref_indicateurs!$A:$A,0))&"") | D97: =IF($A97="","",INDEX(ref_indicateurs!$E:$E,MATCH($A97,ref_indicateurs!$A:$A,0))&"") | E97: =IF($A97="","",INDEX(ref_indicateurs!$M:$M,MATCH($A97,ref_indicateurs!$A:$A,0))&"") | F97: =IF($A97="","",IF(INDEX(ref_indicateurs!$O:$O,MATCH($A97,ref_indicateurs!$A:$A,0))="","",INDEX(ref_indicateurs!$O:$O,MATCH($A97,ref_indicateurs!$A:$A,0)))) | G97: =IF($A97="","",SUMIFS(saisie_hebdo!$L:$L,saisie_hebdo!$I:$I,$A97)) | H97: =IF($A97="","",SUMIFS(saisie_hebdo!$M:$M,saisie_hebdo!$I:$I,$A97)) | I97: =IF(OR($A97="",L97=0),"",IF(D97="Pourcentage",IF(H97>0,G97/H97*100,""),G97)) | J97: =IF(OR(I97="",F97="",F97=0),"",I97/F97) | K97: =IF(OR($A97="",L97=0),"",IF(_xlfn.MAXIFS(saisie_hebdo!$C:$C,saisie_hebdo!$I:$I,$A97)=0,"",_xlfn.MAXIFS(saisie_hebdo!$C:$C,saisie_hebdo!$I:$I,$A97))) | L97: =IF($A97="","",COUNTIFS(saisie_hebdo!$I:$I,$A97)) | M97: =IF($A97="","",IF(L97=0,"Non rapporté",IF(F97="","Suivi sans cible",IF(D97="Pourcentage",IF(I97>=F97,"Cible atteinte","Sous la cible"),IF(J97>=1,"Cible atteinte","En cours")))))
A98: =IFERROR(INDEX(ref_indicateurs!$A:$A,95)&"","") | B98: =IF($A98="","",INDEX(ref_indicateurs!$B:$B,MATCH($A98,ref_indicateurs!$A:$A,0))&"") | C98: =IF($A98="","",INDEX(ref_indicateurs!$C:$C,MATCH($A98,ref_indicateurs!$A:$A,0))&"") | D98: =IF($A98="","",INDEX(ref_indicateurs!$E:$E,MATCH($A98,ref_indicateurs!$A:$A,0))&"") | E98: =IF($A98="","",INDEX(ref_indicateurs!$M:$M,MATCH($A98,ref_indicateurs!$A:$A,0))&"") | F98: =IF($A98="","",IF(INDEX(ref_indicateurs!$O:$O,MATCH($A98,ref_indicateurs!$A:$A,0))="","",INDEX(ref_indicateurs!$O:$O,MATCH($A98,ref_indicateurs!$A:$A,0)))) | G98: =IF($A98="","",SUMIFS(saisie_hebdo!$L:$L,saisie_hebdo!$I:$I,$A98)) | H98: =IF($A98="","",SUMIFS(saisie_hebdo!$M:$M,saisie_hebdo!$I:$I,$A98)) | I98: =IF(OR($A98="",L98=0),"",IF(D98="Pourcentage",IF(H98>0,G98/H98*100,""),G98)) | J98: =IF(OR(I98="",F98="",F98=0),"",I98/F98) | K98: =IF(OR($A98="",L98=0),"",IF(_xlfn.MAXIFS(saisie_hebdo!$C:$C,saisie_hebdo!$I:$I,$A98)=0,"",_xlfn.MAXIFS(saisie_hebdo!$C:$C,saisie_hebdo!$I:$I,$A98))) | L98: =IF($A98="","",COUNTIFS(saisie_hebdo!$I:$I,$A98)) | M98: =IF($A98="","",IF(L98=0,"Non rapporté",IF(F98="","Suivi sans cible",IF(D98="Pourcentage",IF(I98>=F98,"Cible atteinte","Sous la cible"),IF(J98>=1,"Cible atteinte","En cours")))))
A99: =IFERROR(INDEX(ref_indicateurs!$A:$A,96)&"","") | B99: =IF($A99="","",INDEX(ref_indicateurs!$B:$B,MATCH($A99,ref_indicateurs!$A:$A,0))&"") | C99: =IF($A99="","",INDEX(ref_indicateurs!$C:$C,MATCH($A99,ref_indicateurs!$A:$A,0))&"") | D99: =IF($A99="","",INDEX(ref_indicateurs!$E:$E,MATCH($A99,ref_indicateurs!$A:$A,0))&"") | E99: =IF($A99="","",INDEX(ref_indicateurs!$M:$M,MATCH($A99,ref_indicateurs!$A:$A,0))&"") | F99: =IF($A99="","",IF(INDEX(ref_indicateurs!$O:$O,MATCH($A99,ref_indicateurs!$A:$A,0))="","",INDEX(ref_indicateurs!$O:$O,MATCH($A99,ref_indicateurs!$A:$A,0)))) | G99: =IF($A99="","",SUMIFS(saisie_hebdo!$L:$L,saisie_hebdo!$I:$I,$A99)) | H99: =IF($A99="","",SUMIFS(saisie_hebdo!$M:$M,saisie_hebdo!$I:$I,$A99)) | I99: =IF(OR($A99="",L99=0),"",IF(D99="Pourcentage",IF(H99>0,G99/H99*100,""),G99)) | J99: =IF(OR(I99="",F99="",F99=0),"",I99/F99) | K99: =IF(OR($A99="",L99=0),"",IF(_xlfn.MAXIFS(saisie_hebdo!$C:$C,saisie_hebdo!$I:$I,$A99)=0,"",_xlfn.MAXIFS(saisie_hebdo!$C:$C,saisie_hebdo!$I:$I,$A99))) | L99: =IF($A99="","",COUNTIFS(saisie_hebdo!$I:$I,$A99)) | M99: =IF($A99="","",IF(L99=0,"Non rapporté",IF(F99="","Suivi sans cible",IF(D99="Pourcentage",IF(I99>=F99,"Cible atteinte","Sous la cible"),IF(J99>=1,"Cible atteinte","En cours")))))
A100: =IFERROR(INDEX(ref_indicateurs!$A:$A,97)&"","") | B100: =IF($A100="","",INDEX(ref_indicateurs!$B:$B,MATCH($A100,ref_indicateurs!$A:$A,0))&"") | C100: =IF($A100="","",INDEX(ref_indicateurs!$C:$C,MATCH($A100,ref_indicateurs!$A:$A,0))&"") | D100: =IF($A100="","",INDEX(ref_indicateurs!$E:$E,MATCH($A100,ref_indicateurs!$A:$A,0))&"") | E100: =IF($A100="","",INDEX(ref_indicateurs!$M:$M,MATCH($A100,ref_indicateurs!$A:$A,0))&"") | F100: =IF($A100="","",IF(INDEX(ref_indicateurs!$O:$O,MATCH($A100,ref_indicateurs!$A:$A,0))="","",INDEX(ref_indicateurs!$O:$O,MATCH($A100,ref_indicateurs!$A:$A,0)))) | G100: =IF($A100="","",SUMIFS(saisie_hebdo!$L:$L,saisie_hebdo!$I:$I,$A100)) | H100: =IF($A100="","",SUMIFS(saisie_hebdo!$M:$M,saisie_hebdo!$I:$I,$A100)) | I100: =IF(OR($A100="",L100=0),"",IF(D100="Pourcentage",IF(H100>0,G100/H100*100,""),G100)) | J100: =IF(OR(I100="",F100="",F100=0),"",I100/F100) | K100: =IF(OR($A100="",L100=0),"",IF(_xlfn.MAXIFS(saisie_hebdo!$C:$C,saisie_hebdo!$I:$I,$A100)=0,"",_xlfn.MAXIFS(saisie_hebdo!$C:$C,saisie_hebdo!$I:$I,$A100))) | L100: =IF($A100="","",COUNTIFS(saisie_hebdo!$I:$I,$A100)) | M100: =IF($A100="","",IF(L100=0,"Non rapporté",IF(F100="","Suivi sans cible",IF(D100="Pourcentage",IF(I100>=F100,"Cible atteinte","Sous la cible"),IF(J100>=1,"Cible atteinte","En cours")))))
A101: =IFERROR(INDEX(ref_indicateurs!$A:$A,98)&"","") | B101: =IF($A101="","",INDEX(ref_indicateurs!$B:$B,MATCH($A101,ref_indicateurs!$A:$A,0))&"") | C101: =IF($A101="","",INDEX(ref_indicateurs!$C:$C,MATCH($A101,ref_indicateurs!$A:$A,0))&"") | D101: =IF($A101="","",INDEX(ref_indicateurs!$E:$E,MATCH($A101,ref_indicateurs!$A:$A,0))&"") | E101: =IF($A101="","",INDEX(ref_indicateurs!$M:$M,MATCH($A101,ref_indicateurs!$A:$A,0))&"") | F101: =IF($A101="","",IF(INDEX(ref_indicateurs!$O:$O,MATCH($A101,ref_indicateurs!$A:$A,0))="","",INDEX(ref_indicateurs!$O:$O,MATCH($A101,ref_indicateurs!$A:$A,0)))) | G101: =IF($A101="","",SUMIFS(saisie_hebdo!$L:$L,saisie_hebdo!$I:$I,$A101)) | H101: =IF($A101="","",SUMIFS(saisie_hebdo!$M:$M,saisie_hebdo!$I:$I,$A101)) | I101: =IF(OR($A101="",L101=0),"",IF(D101="Pourcentage",IF(H101>0,G101/H101*100,""),G101)) | J101: =IF(OR(I101="",F101="",F101=0),"",I101/F101) | K101: =IF(OR($A101="",L101=0),"",IF(_xlfn.MAXIFS(saisie_hebdo!$C:$C,saisie_hebdo!$I:$I,$A101)=0,"",_xlfn.MAXIFS(saisie_hebdo!$C:$C,saisie_hebdo!$I:$I,$A101))) | L101: =IF($A101="","",COUNTIFS(saisie_hebdo!$I:$I,$A101)) | M101: =IF($A101="","",IF(L101=0,"Non rapporté",IF(F101="","Suivi sans cible",IF(D101="Pourcentage",IF(I101>=F101,"Cible atteinte","Sous la cible"),IF(J101>=1,"Cible atteinte","En cours")))))
...

Sheet saisie_hebdo
A1: annee | B1: periode | C1: semaine_iso | D1: date_debut | E1: date_fin | F1: ip | G1: province | H1: zone_sante | I1: id_indicateur | J1: libelle_indicateur | K1: desagregation | L1: numerateur | M1: denominateur | N1: valeur | O1: source_saisie | P1: saisi_par | Q1: date_saisie | R1: commentaire
A2: 2026 | B2: S41 | C2: 41 | D2: 46300 | E2: 46306 | F2: ADRA | G2: Ituri | H2: Rwampara | I2: SURV-02 | J2: Contacts suivis chaque jour pendant les 21 jours | L2: 1830 | M2: 2010 | N2: =IF(M2="",L2,IF(M2=0,"",L2/M2*100)) | O2: ODK | P2: Nom du point focal | Q2: 46306 | R2: Ligne d'exemple : à supprimer

Sheet sbc_activites
A1: date | B1: ip | C1: province | D1: zone_sante | E1: aire_sante | F1: village_quartier | G1: type_site | H1: nb_seances_prevues | I1: nb_seances_realisees | J1: nb_menages_prevus | K1: nb_menages_visites | L1: nb_vad | M1: nb_causeries | N1: nb_ecoute_negociation | O1: nb_debats_dialogues | P1: nb_sketchs | Q1: nb_emissions_radio | R1: nb_emissions_interactives | S1: nb_spots_radio | T1: themes | U1: sensibilises_h | V1: sensibilises_f | W1: alertes_malades | X1: alertes_deces | Y1: alertes_malades_notifiees_24h | Z1: alertes_deces_notifiees_24h | AA1: alertes_investiguees_24h | AB1: nb_visiteurs | AC1: provenance_visiteurs | AD1: malades_orientes_fosa | AE1: malades_arrives_fosa | AF1: malades_orientes_ct_cte | AG1: commentaire
A2: 46305 | B2: ADRA | C2: Ituri | D2: Rwampara | E2: Dele | F2: Village X | G2: Marché | H2: 2 | I2: 2 | L2: 0 | M2: 2 | N2: 0 | O2: 0 | P2: 0 | Q2: 0 | R2: 0 | S2: 0 | T2: Signes de la MVE ; numéro vert 151 | U2: 48 | V2: 61 | W2: 1 | X2: 0 | Y2: 1 | Z2: 0 | AA2: 1 | AB2: 3 | AC2: Bunia (ZS Bunia) | AD2: 1 | AE2: 1 | AF2: 0 | AG2: Ligne d'exemple : à supprimer

Sheet sbc_synthese_as
A1: date | B1: ip | C1: province | D1: zone_sante | E1: aire_sante | F1: reco_attendus | G1: reco_ayant_travaille | H1: contacts_listes_h | I1: contacts_listes_f | J1: contacts_sous_suivi_h | K1: contacts_sous_suivi_f | L1: contacts_vus_h | M1: contacts_vus_f | N1: contacts_symptomatiques | O1: contacts_symptomatiques_referes_24h | P1: contacts_fin_suivi_21j | Q1: contacts_perdus_de_vue | R1: contacts_sensibilises_vaccination | S1: contacts_vaccines | T1: deces_communautaires_notifies | U1: deces_communautaires_swabes | V1: deces_communautaires_eds | W1: alertes_verifiees_24h | X1: reticences_enregistrees | Y1: reticences_levees_meme_jour | Z1: reticences_levees_48h | AA1: rumeurs_enregistrees | AB1: rumeurs_traitees_48h | AC1: alertes_sante_animale | AD1: feedback_majeur | AE1: visa_as | AF1: visa_bcz
A2: 46305 | B2: ADRA | C2: Ituri | D2: Rwampara | E2: Dele | F2: 25 | G2: 22 | H2: 3 | I2: 4 | J2: 40 | K2: 52 | L2: 38 | M2: 49 | N2: 1 | O2: 1 | P2: 6 | Q2: 0 | R2: 0 | S2: 0 | T2: 1 | U2: 1 | V2: 1 | W2: 1 | X2: 2 | Y2: 1 | Z2: 2 | AA2: 3 | AB2: 2 | AC2: 0 | AD2: Rumeur : « le CTE ne nourrit pas les malades » | AE2: O | AF2: O

Sheet reunions
A1: id_reunion | B1: date | C1: niveau | D1: lieu | E1: objet | F1: duree_min | G1: nb_participants | H1: representant_cgpp | I1: fichier_rapport | J1: liste_presence_complete
A2: 20261012-ZS-RWAMPARA | B2: 46307 | C2: Zone de santé | D2: BCZ Rwampara | E2: Réunion de coordination de la ZS | F2: 60 | G2: 18 | H2: Point focal ADRA | I2: CR_ZS_Rwampara_2026-10-12.docx | J2: O

Sheet points_action
A1: id_action | B1: id_reunion | C1: action | D1: concerne_cgpp | E1: responsable | F1: echeance | G1: statut | H1: date_statut | I1: commentaire
A2: 20261012-ZS-RWAMPARA-01 | B2: 20261012-ZS-RWAMPARA | C2: Relancer les RECO de l'AS Dele pour la saisie quotidienne | D2: O | E2: Superviseur ADRA | F2: 46309 | G2: En cours | H2: 46307 | I2: Ligne d'exemple : à supprimer

Sheet sitrep_notes
A1: date_rapport | B1: section | C1: ordre | D1: texte | E1: auteur
A2: 46305 | B2: Faits marquants | C2: 1 | D2: Exemple : 35 RECO de l'AS de Nzere briefés sur l'approche village. | E2: Nom de l'auteur

Sheet qc_suivi
A1: id_anomalie | B1: date_detection | C1: regle | D1: source | E1: objet | F1: description | G1: gravite | H1: responsable | I1: statut | J1: date_resolution
A2: SR-11 | SitRep 146 | Taux d'occupation | B2: 46307 | C2: SR-11 | D2: SitRep 146 | E2: Taux d'occupation Nord-Kivu | F2: 84,2 % publié pour 169/209 (80,9 %) | G2: Majeure | H2: Data manager INSP | I2: Ouverte

Sheet ref_zones
A1: province | B1: zone_sante | C1: code_zs | D1: ip_cgpp | E1: statut_cgpp | F1: population | G1: source
A2: Nord-Kivu | B2: Goma | D2: WV | E2: intervention | G2: config.yaml
A3: Nord-Kivu | B3: Karisimbi | D3: WV | E3: intervention | G3: config.yaml
A4: Nord-Kivu | B4: Rwanguba | D4: WV | E4: intervention | G4: config.yaml
A5: Nord-Kivu | B5: Kalunguta | D5: WV | E5: intervention | G5: config.yaml
A6: Nord-Kivu | B6: Mutwanga | D6: WV | E6: intervention | G6: config.yaml
A7: Sud-Kivu | B7: Uvira | D7: WV | E7: intervention | G7: config.yaml
A8: Sud-Kivu | B8: Nundu | D8: WV | E8: intervention | G8: config.yaml
A9: Sud-Kivu | B9: Nyangezi | D9: WV | E9: intervention | G9: config.yaml
A10: Ituri | B10: Rwampara | D10: ADRA | E10: intervention | G10: config.yaml
A11: Ituri | B11: Lita | D11: ADRA | E11: intervention | G11: config.yaml
A12: Nord-Kivu | B12: Beni | D12: IMC | E12: intervention | G12: config.yaml
A13: Nord-Kivu | B13: Katwa | D13: IMC | E13: intervention | G13: config.yaml

Sheet ref_partenaires
A1: code_ip | B1: nom | C1: role | D1: provinces | E1: point_focal | F1: email_point_focal
A2: WV | B2: World Vision RDC | C2: Partenaire de mise en oeuvre
A3: ADRA | B3: Adventist Development and Relief Agency | C3: Partenaire de mise en oeuvre
A4: IMC | B4: International Medical Corps | C4: Partenaire de mise en oeuvre
A5: IRC | B5: International Rescue Committee | C5: Partenaire de mise en oeuvre

Sheet ref_indicateurs
A1: id_indicateur | B1: pilier | C1: libelle_fr | D1: libelle_en | E1: type | F1: niveau | G1: numerateur | H1: denominateur | I1: source_donnees | J1: champ_source | K1: frequence | L1: desagregation | M1: cible_dos | N1: cible_tranche5 | O1: cible_dos_num | P1: cible_t5_num | Q1: seuil_alerte | R1: id_barclay | S1: id_cadre_global | T1: statut | U1: priorite | V1: commentaire
A2: COORD-01 | B2: COORD | C2: Matrices 4W élaborées et mises à jour | D2: # of 4W matrices developed and updated | E2: Nombre | F2: Tier 2 | G2: Matrices 4W (1 nationale, 3 provinciales) mises à jour dans le mois | H2: N/A | I2: Matrices 4W | K2: Mensuelle | L2: Niveau (national, provincial) | M2: 4 | O2: 4 | R2: 1.1 | T2: existant | U2: 2
A3: COORD-02 | B3: COORD | C3: Matrice des partenaires CGPP tenue à jour | D3: # of CGPP partner matrices maintained | E3: Nombre | F3: Tier 2 | G3: Matrices partenaires mises à jour | H3: N/A | I3: Matrice partenaires | K3: Mensuelle | M3: 1 | O3: 1 | R3: 1.2 | T3: existant | U3: 3
A4: COORD-03 | B4: COORD | C4: Réunions de coordination auxquelles CGPP a participé ou qu'il a appuyées | D4: # of coordination meetings participated in or supported | E4: Nombre | F4: Tier 2 | G4: Réunions avec compte rendu et liste de présence complète | H4: N/A | I4: Feuille « reunions » de la base | J4: reunions | K4: Mensuelle | L4: Niveau, province | M4: 90 | O4: 90 | R4: 1.3 | S4: 21 | T4: à corriger | U4: 1 | V4: Ne compter que les réunions documentées (compte rendu + liste de présence complète).
A5: COORD-04 | B5: COORD | C5: Réunions bilatérales ou conjointes avec les partenaires financés par le DOS | D5: # of bilateral/joint coordination meetings with DOS-funded partners | E5: Nombre | F5: Tier 2 | G5: Réunions bilatérales/conjointes tenues | H5: N/A | I5: Notes de réunion | J5: reunions | K5: Mensuelle | L5: Partenaire | M5: 12 | O5: 12 | R5: 1.4 | T5: existant | U5: 3
A6: COORD-05 | B6: COORD | C6: Réunions hebdomadaires de coordination CGPP | D6: # of weekly CGPP coordination meetings conducted | E6: Nombre | F6: Tier 2 | G6: Réunions internes hebdomadaires tenues | H6: N/A | I6: Comptes rendus | J6: reunions | K6: Hebdomadaire | M6: 16 | O6: 16 | R6: 1.5 | T6: existant | U6: 3
A7: COORD-06 | B7: COORD | C7: Réunions de revue provinciales | D7: # of provincial review meetings conducted | E7: Nombre | F7: Tier 2 | G7: Revues provinciales tenues | H7: N/A | I7: Rapports de revue | J7: reunions | K7: Mensuelle | L7: Province | M7: 12 | O7: 12 | R7: 1.6 | T7: existant | U7: 3
A8: COORD-07 | B8: COORD | C8: Outil harmonisé de suivi EIR et de rapportage mis en place | D8: # of RRT/data reporting trackers established | E8: Nombre | F8: Tier 2 | G8: Outil en service | H8: N/A | I8: Outil de suivi | K8: Mensuelle | M8: 1 | O8: 1 | R8: 1.7 | T8: existant | U8: 1 | V8: La base Excel normalisée et la chaîne Python décrites dans ce rapport peuvent tenir ce rôle.
A9: COORD-08 | B9: COORD | C9: Mises à jour quotidiennes de terrain transmises | D9: # of daily field updates submitted | E9: Nombre | F9: Tier 2 | G9: Mises à jour quotidiennes transmises | H9: N/A | I9: Journal des envois | K9: Quotidienne | L9: IP | M9: 110 | O9: 110 | R9: 1.8 | T9: existant | U9: 2
A10: COORD-09 | B10: COORD | C10: Mises à jour hebdomadaires de coordination transmises | D10: # of weekly coordination updates submitted | E10: Nombre | F10: Tier 2 | G10: Mises à jour hebdomadaires transmises | H10: N/A | I10: Journal des envois | K10: Hebdomadaire | M10: 16 | O10: 16 | R10: 1.9 | T10: à corriger | U10: 2 | V10: Le plan DOS indique 16 (extrants du pilier 1) et 18 (activité 1.5) : arrêter une seule cible.
A11: COORD-10 | B11: COORD | C11: Séances de négociation ou de médiation de crise avec le pilier CREC | D11: # of crisis negotiation/mediation sessions conducted with CREC Pillar | E11: Nombre | F11: Tier 2 | G11: Séances tenues | H11: N/A | I11: Rapports de négociation | K11: Selon besoin | M11: 4 | O11: 4 | R11: 1.10 | T11: existant | U11: 3
A12: COORD-11 | B12: COORD | C12: Réunions de coordination transfrontalière | D12: # of cross-border coordination meetings held | E12: Nombre | F12: Tier 2 | G12: Réunions transfrontalières tenues | H12: N/A | I12: Comptes rendus | J12: reunions | K12: Mensuelle | L12: Frontière | M12: 6 | N12: 100 échanges transfrontaliers ou interprovinciaux | O12: 6 | R12: 1.11 | T12: existant | U12: 3
A13: COORD-12 | B13: COORD | C13: Points d'action des réunions réalisés dans les délais | D13: % of action points generated and followed up | E13: Pourcentage | F13: Tier 1 | G13: Points d'action réalisés à l'échéance | H13: Points d'action arrivés à échéance | I13: Feuille « points_action » de la base | J13: points_action | K13: Mensuelle | L13: Niveau de réunion | M13: 100 % | O13: 100 | Q13: < 70 % : rouge | R13: 1.12 | T13: à corriger | U13: 1 | V13: Intitulé « # » alors que c'est un pourcentage ; cible codée 1 ; les comptes rendus actuels ne listent pas de points d'action.
A14: SURV-01 | B14: SURV | C14: Contacts listés et suivis | D14: # of contacts line-listed and monitored | E14: Nombre | F14: Tier 1 | G14: Contacts listés (cas confirmés, probables, suspects) entrés dans le système de suivi | H14: N/A | I14: Liste des contacts ; Fiche SBC journalière (ODK) | J14: contacts_listes_h + contacts_listes_f | K14: Hebdomadaire | L14: Sexe, âge, ZS, niveau de risque | M14: 2 000 | N14: 30 000 | O14: 2000 | P14: 30000 | R14: 2.1 | S14: 8 | T14: existant | U14: 1
A15: SURV-02 | B15: SURV | C15: Contacts suivis chaque jour pendant les 21 jours | D15: % of listed contacts followed daily during 21-day follow-up | E15: Pourcentage | F15: Tier 1 | G15: Contacts-jours vus | H15: Contacts-jours attendus (contacts sous suivi x jours) | I15: Fiche SBC journalière (ODK) | J15: contacts_vus / contacts_sous_suivi | K15: Hebdomadaire | L15: ZS, sexe | M15: ≥ 90 % | N15: ≥ 90 % | O15: 90 | P15: 90 | Q15: < 90 % : rouge | R15: 2.2 | S15: 9 | T15: à corriger | U15: 1 | V15: La définition actuelle mélange le suivi quotidien et l'issue à J21 : l'issue devient SURV-21.
A16: SURV-03 | B16: SURV | C16: Investigations de cas réalisées | D16: # of case investigations conducted | E16: Nombre | F16: Tier 2 | G16: Investigations (cas confirmés, probables, suspects) appuyées | H16: N/A | I16: Rapports d'investigation | K16: Hebdomadaire | L16: ZS, classification | M16: 300 | N16: 2 000 | O16: 300 | P16: 2000 | R16: 2.3 | T16: existant | U16: 2
A17: SURV-04 | B17: SURV | C17: Cartographies d'exposition réalisées | D17: # of exposure mappings conducted | E17: Nombre | F17: Tier 2 | G17: Cartographies d'exposition autour d'un cas | H17: N/A | I17: Rapports de cartographie | K17: Hebdomadaire | L17: ZS | M17: 300 | N17: Incluses dans les 2 000 investigations | O17: 300 | R17: 2.4 | T17: existant | U17: 3
A18: SURV-05 | B18: SURV | C18: Alertes de suspicion de MVE détectées par les systèmes appuyés par CGPP | D18: # of suspected EVD alerts detected through CGPP-supported systems | E18: Nombre | F18: Tier 1 | G18: Alertes (malades et décès) détectées par les canaux appuyés par CGPP | H18: N/A | I18: Fiche SBC journalière (ODK) | J18: alertes_malades + alertes_deces | K18: Hebdomadaire | L18: Type (malade/décès), source, ZS | M18: 1 500 | N18: 35 000 | O18: 1500 | P18: 35000 | R18: 2.5 | S18: 1 | T18: existant | U18: 1
A19: SURV-06 | B19: SURV | C19: Alertes CGPP vérifiées en 24 h | D19: % of suspected EVD alerts reported by CGPP verified within 24 hours | E19: Pourcentage | F19: Tier 1 | G19: Alertes vérifiées par l'ESS/EIR dans les 24 h | H19: Alertes reçues | I19: Fiche SBC journalière (ODK) | J19: alertes_verifiees_24h (nouveau champ) / alertes | K19: Hebdomadaire | L19: ZS | M19: ≥ 80 % | N19: ≥ 85 % | O19: 80 | P19: 85 | Q19: < 80 % : rouge | R19: 2.6 | S19: 3 | T19: à corriger | U19: 1 | V19: Aucun champ ne mesure la vérification dans la fiche SBC actuelle.
A20: SURV-07 | B20: SURV | C20: Alertes notifiées aux autorités en 24 h | D20: % of suspected EVD alerts notified to authorities within 24 hours | E20: Pourcentage | F20: Tier 1 | G20: Alertes signalées au centre de santé dans les 24 h | H20: Alertes détectées | I20: Fiche SBC journalière (ODK) | J20: alertes_*_notifiees_24h / alertes | K20: Hebdomadaire | L20: ZS | M20: 100 % | O20: 100 | Q20: < 90 % : rouge | R20: 2.7 | S20: 4 | T20: à corriger | U20: 1 | V20: Cible codée « 1 » dans la matrice : à écrire 100 %.
A21: SURV-08 | B21: SURV | C21: Alertes investiguées dans les délais | D21: % of suspected EVD alerts investigated within 7 days | E21: Pourcentage | F21: Tier 1 | G21: Alertes investiguées dans le délai retenu | H21: Alertes détectées | I21: Fiche SBC journalière (ODK) | J21: alertes_investiguees_24h | K21: Hebdomadaire | L21: ZS | M21: 100 % | O21: 100 | R21: 2.8 | S21: 5 | T21: à corriger | U21: 1 | V21: Le cadre dit 7 jours, la fiche SBC mesure 24 h : retenir 24 h (cohérent avec 7-1-7 et le SitRep).
A22: SURV-09 | B22: SURV | C22: Acteurs de la surveillance à base communautaire formés et activés | D22: # of CBS actors/community volunteers trained and activated | E22: Nombre | F22: Tier 2 | G22: RECO, relais, informateurs, leaders formés et actifs | H22: N/A | I22: Rapports de formation ; listes d'activation | K22: Mensuelle | L22: Sexe, type d'acteur, ZS | M22: 2 024 | N22: 12 000 | O22: 2024 | P22: 12000 | R22: 2.9 | S22: 6 | T22: existant | U22: 2
A23: SURV-10 | B23: SURV | C23: Exercices PopCAB ou de cartographie des risques de mobilité | D23: # of risk mapping exercises conducted | E23: Nombre | F23: Tier 2 | G23: Exercices PopCAB réalisés | H23: N/A | I23: Rapports PopCAB | K23: Mensuelle | L23: ZS | M23: 12 | N23: 60 | O23: 12 | P23: 60 | R23: 2.10 | S23: 7 | T23: à corriger | U23: 3 | V23: Fréquence « annuelle » incompatible avec une cible de 12 : passer en mensuel.
A24: SURV-11 | B24: SURV | C24: Alertes communautaires reçues | D24: # of community alerts received | E24: Nombre | F24: Tier 2 | G24: Alertes communautaires et de FOSA reçues | H24: N/A | I24: Registre des alertes | K24: Hebdomadaire | L24: Source | M24: 1 500 | O24: 1500 | R24: 2.11 | T24: à corriger | U24: 2 | V24: Même cible et définition voisine de SURV-05 : fusionner ou distinguer clairement.
A25: SURV-12 | B25: SURV | C25: Déploiements d'équipes d'intervention rapide (EIR) appuyés | D25: # of RRT deployments supported | E25: Nombre | F25: Tier 2 | G25: Déploiements EIR appuyés | H25: N/A | I25: Journal des EIR | K25: Hebdomadaire | L25: ZS | M25: 300 | N25: 500 membres d'EIR recyclés | O25: 300 | R25: 2.12 | S25: 23 | T25: existant | U25: 2 | V25: L'indicateur 23 du cadre global mélange équipes, déploiements et alertes : il est scindé en SURV-12 et LOG-02.
A26: SURV-13 | B26: SURV | C26: PoE informels, PoC et points de mobilité appuyés pour le dépistage | D26: # of informal PoEs/PoCs supported for screening | E26: Nombre | F26: Tier 2 | G26: Sites appuyés et fonctionnels | H26: N/A | I26: Évaluations de site | K26: Mensuelle | L26: Type de site | M26: 60 | N26: 150 | O26: 60 | P26: 150 | R26: 2.13 | S26: 17 | T26: existant | U26: 2
A27: SURV-14 | B27: SURV | C27: Personnes dépistées aux PoE/PoC ou points de mobilité | D27: # of people screened at PoEs/PoCs or mobility points | E27: Nombre | F27: Tier 1 | G27: Voyageurs dépistés | H27: N/A | I27: Registres de dépistage | K27: Hebdomadaire | L27: Site, sexe | M27: 269 518 | O27: 269518 | R27: 2.14 | S27: 16 | T27: existant | U27: 2
A28: SURV-15 | B28: SURV | C28: Réseaux d'alerte frontaliers et communautaires établis | D28: # of border/community alert networks established | E28: Nombre | F28: Tier 2 | G28: Réseaux activés | H28: N/A | I28: Rapports d'activation | K28: Mensuelle | L28: Frontière | M28: 20 | O28: 20 | R28: 2.15 | T28: existant | U28: 3
A29: SURV-16 | B29: SURV | C29: Alertes et références transfrontalières documentées et suivies | D29: # of cross-border alerts/referrals documented and followed up | E29: Nombre | F29: Tier 2 | G29: Alertes suivies | H29: N/A | I29: Journal de notification | K29: Hebdomadaire | L29: Pays | M29: 70 | N29: 500 | O29: 70 | P29: 500 | R29: 2.16 | T29: existant | U29: 2
A30: SURV-17 | B30: SURV | C30: Cas confirmés dans les zones d'intervention CGPP | D30: # of confirmed Ebola cases identified within CGPP focal areas | E30: Nombre | F30: Contexte | G30: Cas confirmés (toutes sources) dans les ZS CGPP | H30: N/A | I30: SitRep national (tableaux par ZS) | J30: epi_zs.cas_cumul, nouveaux_cas_24h | K30: Quotidienne | L30: ZS, IP | M30: Suivi | R30: 2.17 | S30: 2 | T30: à corriger | U30: 1 | V30: À calculer automatiquement depuis le SitRep national et non à déclarer par les IP (le classeur affiche 1, le SitRep 2 586 au 10/10).
A31: SURV-18 | B31: SURV | C31: Décès inexpliqués ou communautaires investigués | D31: # of unexplained/community deaths investigated | E31: Nombre | F31: Tier 2 | G31: Décès investigués | H31: N/A | I31: Journal des décès | J31: deces_communautaires_notifies | K31: Hebdomadaire | L31: ZS | M31: 50 | O31: 50 | R31: 2.18 | T31: existant | U31: 2
A32: SURV-19 | B32: SURV | C32: Contacts symptomatiques référés vers une FOSA ou un CTE | D32: # of symptomatic contacts referred to health facilities/ETC | E32: Nombre | F32: Tier 2 | G32: Contacts référés | H32: N/A | I32: Fiche SBC journalière (ODK) | J32: contacts_symptomatiques_referes_24h | K32: Hebdomadaire | L32: ZS | M32: 100 | O32: 100 | R32: 2.19 | T32: existant | U32: 2
A33: SURV-20 | B33: SURV | C33: Nouveaux cas confirmés qui étaient des contacts connus | D33: % of new confirmed cases who were known contacts | E33: Pourcentage | F33: Tier 1 | G33: Nouveaux cas confirmés figurant sur une liste de contacts avant leur confirmation | H33: Nouveaux cas confirmés dans les ZS CGPP | I33: Liste linéaire des cas (DHIS2 Tracker) et liste des contacts | K33: Hebdomadaire | L33: ZS | Q33: Cible proposée ≥ 80 % (à valider) | T33: nouveau | U33: 1 | V33: Mesure directe de l'efficacité du suivi des contacts : c'est l'indicateur qui manque le plus.
A34: SURV-21 | B34: SURV | C34: Contacts ayant terminé les 21 jours de suivi | D34: % of contacts completing 21-day follow-up | E34: Pourcentage | F34: Tier 1 | G34: Contacts sortis du suivi à J21 sans interruption | H34: Contacts dont la fenêtre de 21 jours s'est terminée | I34: Fiche SBC journalière (ODK) | J34: contacts_fin_suivi_21j (nouveau) | K34: Hebdomadaire | L34: ZS | Q34: < 90 % : rouge | T34: nouveau | U34: 1 | V34: Publier aussi le pourcentage de perdus de vue (champ contacts_perdus_de_vue).
A35: SURV-22 | B35: SURV | C35: Nouveaux cas confirmés détectés après le décès (décès communautaires) | D35: % of new confirmed cases detected post-mortem | E35: Pourcentage | F35: Tier 1 | G35: Nouveaux cas confirmés issus de décès communautaires (swab +) | H35: Nouveaux cas confirmés | I35: SitRep national (tableaux par ZS) | J35: epi_zs.deces_communautaires_24h / nouveaux_cas_24h | K35: Hebdomadaire | L35: ZS | Q35: Tendance à la baisse attendue | T35: nouveau | U35: 1 | V35: Calculable dès maintenant : 44 % le 07/10 et 20 % le 10/10.
A36: SURV-23 | B36: SURV | C36: Délai entre le début des symptômes et l'isolement | D36: Median delay from symptom onset to isolation (days) | E36: Délai | F36: Tier 1 | G36: Médiane des délais (jours) des cas confirmés de la semaine ; part isolée en 3 jours ou moins | H36: N/A | I36: Liste linéaire des cas (DHIS2 Tracker) et liste des contacts | K36: Hebdomadaire | L36: ZS | Q36: Médiane > 3 j : rouge (seuil à valider) | T36: nouveau | U36: 2
A37: SURV-24 | B37: SURV | C37: Respect des délais 7-1-7 pour les événements détectés | D37: % of events meeting 7-1-7 timeliness targets | E37: Pourcentage | F37: Tier 1 | G37: Événements détectés ≤ 7 j, notifiés ≤ 1 j, réponse initiale ≤ 7 j | H37: Événements validés | I37: Registre des alertes et événements | K37: Mensuelle | L37: Étape (détection, notification, réponse) | T37: nouveau | U37: 2 | V37: Le plan DOS prévoit l'intégration du suivi 7-1-7 (activité 1.7.6 de la Tranche 5).
A38: SURV-25 | B38: SURV | C38: Contacts listés par cas confirmé | D38: Mean number of contacts listed per confirmed case | E38: Ratio | F38: Tier 1 | G38: Contacts listés autour des cas de la semaine | H38: Cas confirmés de la semaine | I38: Liste linéaire des cas (DHIS2 Tracker) et liste des contacts | K38: Hebdomadaire | L38: ZS | T38: nouveau | U38: 2 | V38: Un ratio bas signale un listage incomplet.
A39: SURV-26 | B39: SURV | C39: Contacts symptomatiques référés en 24 h ou moins | D39: % of symptomatic contacts referred within 24 hours | E39: Pourcentage | F39: Tier 1 | G39: Contacts symptomatiques référés dans les 24 h | H39: Contacts ayant présenté au moins un signe | I39: Fiche SBC journalière (ODK) | J39: contacts_symptomatiques_referes_24h / contacts_symptomatiques | K39: Hebdomadaire | L39: ZS | Q39: < 90 % : rouge | T39: nouveau | U39: 1
A40: SURV-27 | B40: SURV | C40: Alertes CGPP validées comme cas suspects (valeur prédictive) | D40: % of CGPP alerts validated as suspected cases | E40: Pourcentage | F40: Tier 2 | G40: Alertes CGPP validées | H40: Alertes CGPP vérifiées | I40: Registre des alertes | K40: Hebdomadaire | L40: ZS, type | T40: nouveau | U40: 2 | V40: Mesure la qualité des alertes communautaires (au niveau national : 15,8 % le 07/10).
A41: SURV-28 | B41: SURV | C41: Alertes pour 10 000 habitants par semaine | D41: Alert rate per 10,000 population per week | E41: Ratio | F41: Tier 2 | G41: Alertes de la semaine x 10 000 | H41: Population de la ZS | I41: Fiche SBC journalière (ODK) ; ref_zones.population | K41: Hebdomadaire | L41: ZS | T41: nouveau | U41: 2 | V41: Sensibilité de la surveillance communautaire ; nécessite la population par ZS.
A42: SURV-29 | B42: SURV | C42: Complétude des rapports SBC journaliers | D42: % of expected CBS daily reports received | E42: Pourcentage | F42: Tier 2 | G42: RECO/ACSA ayant travaillé et rapporté | H42: RECO/ACSA attendus | I42: Fiche SBC journalière (ODK) | J42: reco_ayant_travaille / reco_attendus | K42: Quotidienne | L42: AS, ZS, IP | Q42: < 80 % : rouge | T42: nouveau | U42: 1 | V42: Les champs existent déjà dans l'en-tête de la fiche SBC.
A43: SURV-30 | B43: SURV | C43: Décès communautaires notifiés et prélevés (swab) | D43: % of notified community deaths swabbed | E43: Pourcentage | F43: Tier 1 | G43: Décès communautaires prélevés | H43: Décès communautaires notifiés | I43: Fiche SBC journalière (ODK) | J43: deces_communautaires_swabes / deces_communautaires_notifies | K43: Hebdomadaire | L43: ZS | Q43: < 90 % : rouge | T43: nouveau | U43: 1
A44: SURV-31 | B44: SURV | C44: Alertes de santé animale (One Health) transmises aux services vétérinaires | D44: # of animal health alerts relayed (One Health) | E44: Nombre | F44: Tier 2 | G44: Alertes animales transmises | H44: N/A | I44: Fiche SBC journalière (ODK) | J44: alertes_sante_animale (nouveau) | K44: Hebdomadaire | L44: ZS | T44: nouveau | U44: 3
A45: CREC-01 | B45: CREC | C45: Ménages visités et séances d'engagement communautaire | D45: # of households reached with RCCE messages | E45: Nombre | F45: Tier 2 | G45: Ménages visités (porte à porte) ; séances d'engagement (à rapporter séparément) | H45: N/A | I45: Fiche SBC journalière (ODK) | J45: nb_menages_visites ; nb_seances_realisees | K45: Mensuelle | L45: Type (ménage, séance), ZS | M45: 2 515 | N45: 40 000 | O45: 2515 | P45: 40000 | R45: 3.1 | S45: 10 | T45: à corriger | U45: 1 | V45: L'intitulé parle de ménages mais le numérateur compte des séances : scinder en deux chiffres.
A46: CREC-02 | B46: CREC | C46: Séances de groupe ciblées | D46: # of targeted RCCE group sessions conducted | E46: Nombre | F46: Tier 2 | G46: Dialogues, forums, causeries, réunions de groupe | H46: N/A | I46: Fiche SBC journalière (ODK) | J46: nb_causeries + nb_debats_dialogues (hors VAD) | K46: Mensuelle | L46: Technique, ZS | M46: 300 | O46: 300 | R46: 3.2 | S46: 11 | T46: existant | U46: 2
A47: CREC-03 | B47: CREC | C47: Personnes atteintes par les messages CREC | D47: # of people reached with EVD RCCE messaging | E47: Nombre | F47: Tier 1 | G47: Personnes sensibilisées | H47: N/A | I47: Fiche SBC journalière (ODK) | J47: sensibilises_h + sensibilises_f | K47: Mensuelle | L47: Sexe, canal (VAD, groupe, médias), ZS | M47: 550 810 | N47: 5 000 000 | O47: 550810 | P47: 5000000 | R47: 3.3 | S47: 12 | T47: existant | U47: 1 | V47: Ne pas additionner l'audience radio estimée et les personnes atteintes en face à face.
A48: CREC-04 | B48: CREC | C48: Séances ciblées en milieux à haut risque | D48: # of targeted RCCE sessions conducted in high-risk settings | E48: Nombre | F48: Tier 2 | G48: Séances dans les sites à haut risque de la liste fixée | H48: N/A | I48: Fiche SBC journalière (ODK) | J48: nb_seances_realisees où type_site ∈ {école, marché, site minier, PoE, déplacés, parkings, guérison trad.} | K48: Mensuelle | L48: Type de site | M48: 300 | O48: 300 | R48: 3.4 | S48: 13 | T48: à corriger | U48: 2 | V48: Fixer la liste des types de site « à haut risque ».
A49: CREC-05 | B49: CREC | C49: Rumeurs et préoccupations communautaires enregistrées | D49: # of rumors or community concerns logged | E49: Nombre | F49: Tier 2 | G49: Rumeurs/préoccupations enregistrées | H49: N/A | I49: Fiche SBC journalière (ODK) | J49: rumeurs_enregistrees (nouveau) | K49: Hebdomadaire | L49: Catégorie, ZS | M49: 500 | N49: 10 000 | O49: 500 | P49: 10000 | R49: 3.5 | S49: 14 | T49: existant | U49: 1
A50: CREC-06 | B50: CREC | C50: Rumeurs et préoccupations traitées en 48 h | D50: % of rumors/community concerns addressed within 48 hours | E50: Pourcentage | F50: Tier 1 | G50: Rumeurs traitées dans les 48 h | H50: Rumeurs enregistrées | I50: Fiche SBC journalière (ODK) | J50: rumeurs_traitees_48h / rumeurs_enregistrees | K50: Hebdomadaire | L50: Catégorie | M50: ≥ 80 % | N50: ≥ 80 % | O50: 80 | P50: 80 | Q50: < 80 % : rouge | R50: 3.6 | S50: 15 | T50: à corriger | U50: 1 | V50: La fiche SBC mesure des réticences levées le jour même : ajouter les champs rumeurs.
A51: CREC-07 | B51: CREC | C51: Supports IEC produits ou distribués | D51: # of IEC materials produced/distributed | E51: Nombre | F51: Tier 2 | G51: Supports produits/distribués | H51: N/A | I51: Registres de production | K51: Mensuelle | L51: Type, langue | M51: 150 000 | N51: 1 500 000 | O51: 150000 | P51: 1500000 | R51: 3.7 | T51: existant | U51: 3
A52: CREC-08 | B52: CREC | C52: Spots ou jingles radio diffusés | D52: # of radio spots/jingles aired | E52: Nombre | F52: Tier 2 | G52: Spots diffusés | H52: N/A | I52: Journaux de diffusion | J52: nb_spots_radio | K52: Mensuelle | L52: Station | M52: 400 | N52: 3 000 | O52: 400 | P52: 3000 | R52: 3.8 | T52: existant | U52: 3
A53: CREC-09 | B53: CREC | C53: Émissions radio interactives | D53: # of interactive radio programs conducted | E53: Nombre | F53: Tier 2 | G53: Émissions réalisées | H53: N/A | I53: Journaux de diffusion | J53: nb_emissions_interactives | K53: Mensuelle | L53: Station | M53: 24 | N53: 300 | O53: 24 | P53: 300 | R53: 3.9 | T53: existant | U53: 3
A54: CREC-10 | B54: CREC | C54: Alertes, ménages ou événements à haut risque ayant reçu un appui CREC | D54: # of high-risk alerts/households/events receiving RCCE support | E54: Nombre | F54: Tier 2 | G54: Événements appuyés | H54: N/A | I54: Rapports de déploiement CREC | K54: Mensuelle | L54: Type d'événement | M54: 300 | N54: 5 000 | O54: 300 | P54: 5000 | R54: 3.10 | T54: existant | U54: 2
A55: CREC-11 | B55: CREC | C55: Leaders communautaires, religieux et tradipraticiens engagés | D55: # of community leaders/religious leaders/traditional healers engaged | E55: Nombre | F55: Tier 2 | G55: Leaders engagés | H55: N/A | I55: Rapports d'engagement | K55: Mensuelle | L55: Type de leader, sexe | M55: 200 | N55: 2 500 | O55: 200 | P55: 2500 | R55: 3.11 | T55: existant | U55: 3
A56: CREC-12 | B56: CREC | C56: Écoles atteintes par des séances de sensibilisation | D56: # of schools reached with EVD awareness sessions | E56: Nombre | F56: Tier 2 | G56: Écoles atteintes | H56: N/A | I56: Fiche SBC journalière (ODK) | J56: type_site = École | K56: Mensuelle | L56: ZS | M56: 100 | O56: 100 | R56: 3.12 | T56: existant | U56: 3
A57: CREC-13 | B57: CREC | C57: Mécanismes de retour communautaire établis | D57: # of community feedback loops established | E57: Nombre | F57: Tier 2 | G57: Canaux de retour fonctionnels | H57: N/A | I57: Rapports du système de retour | K57: Mensuelle | L57: Type de canal | M57: 15 | N57: 150 (milieux de déplacement) | O57: 15 | R57: 3.13 | T57: existant | U57: 3
A58: CREC-14 | B58: CREC | C58: Épisodes de résistance communautaire résolus en 48 h | D58: % of community resistance events resolved | E58: Pourcentage | F58: Tier 1 | G58: Réticences levées dans les 48 h | H58: Réticences enregistrées | I58: Fiche SBC journalière (ODK) | J58: reticences_levees_48h (nouveau) / reticences_enregistrees | K58: Mensuelle | L58: ZS | M58: ≥ 80 % | O58: 80 | Q58: < 80 % : rouge | R58: 3.14 | T58: à corriger | U58: 1 | V58: Ajouter le délai de 48 h et l'aligner sur la fiche SBC.
A59: CREC-15 | B59: CREC | C59: Retours communautaires clôturés avec réponse à la communauté | D59: % of feedback items closed with response to the community | E59: Pourcentage | F59: Tier 1 | G59: Retours clôturés avec réponse communiquée | H59: Retours enregistrés | I59: Registre des retours | K59: Mensuelle | L59: Catégorie | T59: nouveau | U59: 2
A60: CREC-16 | B60: CREC | C60: Typologie hebdomadaire des rumeurs | D60: Distribution of rumors by category | E60: Ratio | F60: Contexte | G60: Rumeurs par catégorie (déni, peur du CTE, EDS, vaccin, stigmatisation...) | H60: Total des rumeurs | I60: Registre des rumeurs | K60: Hebdomadaire | L60: Catégorie, ZS | T60: nouveau | U60: 2
A61: CREC-17 | B61: CREC | C61: Acceptation des enterrements dignes et sécurisés dans les ZS CGPP | D61: SDB acceptance rate in CGPP areas | E61: Pourcentage | F61: Tier 1 | G61: EDS réalisés | H61: Alertes de décès nécessitant un EDS | I61: SitRep national (tableaux par ZS) ; Fiche SBC journalière (ODK) | J61: deces_communautaires_eds / deces_communautaires_notifies | K61: Hebdomadaire | L61: ZS | Q61: < 80 % : rouge | T61: nouveau | U61: 1 | V61: En Ituri, 21 % des EDS échouent (SitRep 149) ; CGPP agit en amont par l'engagement des familles.
A62: CREC-18 | B62: CREC | C62: Connaissances clés de la population (enquête rapide) | D62: % of people knowing ≥3 EVD signs and the 151 hotline | E62: Pourcentage | F62: Résultat | G62: Personnes interrogées connaissant au moins 3 signes et le numéro vert 151 | H62: Personnes interrogées | I62: Enquête rapide (téléphone ou ménages) | K62: Trimestrielle | L62: Sexe, âge, ZS | T62: nouveau | U62: 3
A63: CREC-19 | B63: CREC | C63: Personnel et volontaires CGPP formés à la PSEA (code de conduite signé) | D63: % of CGPP staff and volunteers trained in PSEA | E63: Pourcentage | F63: Tier 2 | G63: Agents et volontaires formés ayant signé le code de conduite | H63: Agents et volontaires actifs | I63: Registres RH et de formation | K63: Mensuelle | L63: IP, sexe | Q63: < 100 % : rouge | T63: nouveau | U63: 1 | V63: Le SitRep relève que seules 13 ZS sur 36 en Ituri connaissent le mécanisme de signalement.
A64: PCI-01 | B64: PCI | C64: Alertes de décès communautaires référées aux équipes EDS | D64: # of community death alerts referred to SDB teams | E64: Nombre | F64: Tier 2 | G64: Alertes de décès référées | H64: N/A | I64: Fiche SBC journalière (ODK) | J64: deces_communautaires_notifies | K64: Hebdomadaire | L64: ZS | M64: 300 | N64: 1 000 | O64: 300 | P64: 1000 | R64: 4.1 | T64: existant | U64: 1
A65: PCI-02 | B65: PCI | C65: Événements funéraires éligibles appuyés pour identifier les contacts | D65: % of eligible funeral-linked events supported for contact identification | E65: Pourcentage | F65: Tier 1 | G65: Événements appuyés | H65: Événements éligibles | I65: Journal de surveillance funéraire | K65: Hebdomadaire | L65: ZS | M65: 100 % | O65: 100 | R65: 4.2 | T65: à corriger | U65: 2 | V65: Cible codée « 1 » : écrire 100 %.
A66: PCI-03 | B66: PCI | C66: FOSA et sites communautaires appuyés en PCI | D66: # of health facilities/community sites supported with IPC/readiness inputs | E66: Nombre | F66: Tier 2 | G66: Sites ayant reçu un appui PCI | H66: N/A | I66: Rapports de supervision | K66: Mensuelle | L66: Type de site, ZS | M66: 150 | N66: 1 200 | O66: 150 | P66: 1200 | R66: 4.3 | S66: 20 | T66: existant | U66: 2
A67: PCI-04 | B67: PCI | C67: Kits EPI/PCI acquis et distribués | D67: # of PPE/IPC kits or supplies procured and distributed | E67: Nombre | F67: Tier 2 | G67: Kits distribués | H67: N/A | I67: Registres d'achat et de distribution | K67: Mensuelle | L67: Type de kit | M67: 1 500 | N67: 250 kits PCI/WASH + 500 kits de préparation | O67: 1500 | R67: 4.4 | S67: 19 | T67: à corriger | U67: 2 | V67: La cible de 1 500 correspond aux 1 500 agents équipés en EPI (activité 5.6) : ne pas compter deux fois.
A68: PCI-05 | B68: PCI | C68: Références (cas suspects, contacts symptomatiques, échantillons) coordonnées et suivies | D68: # of suspected case, symptomatic contact, referral, or sample transport actions coordinated and tracked | E68: Nombre | F68: Tier 1 | G68: Références coordonnées et suivies | H68: N/A | I68: Registre des références ; Fiche SBC journalière (ODK) | J68: malades_orientes_ct_cte ; transport d'échantillons | K68: Hebdomadaire | L68: Type (cas suspect, contact, échantillon) | M68: 400 | N68: 5 000 (milieux de déplacement) | O68: 400 | R68: 4.5 | S68: 18 | T68: existant | U68: 1
A69: PCI-06 | B69: PCI | C69: Contacts à haut risque appuyés pendant la quarantaine | D69: # of high-risk contacts supported through quarantine follow-up | E69: Nombre | F69: Tier 2 | G69: Contacts appuyés | H69: N/A | I69: Registres de quarantaine | K69: Hebdomadaire | L69: ZS | M69: 1 000 | O69: 1000 | R69: 4.6 | T69: existant | U69: 2
A70: PCI-07 | B70: PCI | C70: Séances d'orientation ou de formation PCI | D70: # of IPC orientation/training sessions conducted | E70: Nombre | F70: Tier 2 | G70: Séances tenues (et participants formés, à rapporter à part) | H70: N/A | I70: Rapports de formation | K70: Mensuelle | L70: Type de participant, sexe | M70: 150 | N70: 8 000 participants | O70: 150 | R70: 4.7 | T70: à corriger | U70: 2 | V70: Le plan DOS compte des séances, la Tranche 5 des participants : rapporter les deux.
A71: PCI-08 | B71: PCI | C71: Circuits de référence cartographiés et mis à jour | D71: # of referral pathways mapped and updated | E71: Nombre | F71: Tier 2 | G71: Circuits cartographiés | H71: N/A | I71: Cartographies | K71: Mensuelle | L71: ZS | M71: 20 | O71: 20 | R71: 4.8 | T71: existant | U71: 3
A72: PCI-09 | B72: PCI | C72: Références dont l'aboutissement est confirmé | D72: % of referrals with confirmed completion | E72: Pourcentage | F72: Tier 1 | G72: Références arrivées à destination | H72: Références suivies | I72: Registre des références ; Fiche SBC journalière (ODK) | J72: malades_arrives_fosa / malades_orientes_fosa | K72: Hebdomadaire | L72: Type | M72: ≥ 90 % | O72: 90 | Q72: < 90 % : rouge | R72: 4.9 | T72: existant | U72: 1
A73: PCI-10 | B73: PCI | C73: Séances d'engagement des familles pour l'acceptation des EDS | D73: # of family engagement sessions conducted for SDB acceptance | E73: Nombre | F73: Tier 2 | G73: Séances tenues | H73: N/A | I73: Rapports d'engagement EDS | K73: Mensuelle | L73: ZS | M73: 250 | O73: 250 | R73: 4.10 | T73: existant | U73: 2
A74: PCI-11 | B74: PCI | C74: FOSA appuyées avec un score PCI d'au moins 80 % | D74: % of supported facilities with IPC score ≥80% | E74: Pourcentage | F74: Résultat | G74: FOSA appuyées avec score ≥ 80 % | H74: FOSA appuyées évaluées | I74: Score card PCI | K74: Mensuelle | L74: ZS | T74: nouveau | U74: 2 | V74: Le SitRep montre des scores moyens de 31 à 38 % au Nord-Kivu.
A75: PCI-12 | B75: PCI | C75: Infections de prestataires de première ligne dans les ZS CGPP | D75: # of health worker infections in CGPP areas | E75: Nombre | F75: Contexte | G75: PPL confirmés | H75: N/A | I75: SitRep national (tableaux par ZS) | K75: Hebdomadaire | L75: ZS | Q75: Tout cas : alerte | T75: nouveau | U75: 1 | V75: Indicateur sentinelle d'échec de la PCI.
A76: PCI-13 | B76: PCI | C76: FOSA appuyées avec triage et poste de lavage des mains fonctionnels | D76: % of supported facilities with functional triage and handwashing station | E76: Pourcentage | F76: Résultat | G76: FOSA avec triage et lavage des mains fonctionnels | H76: FOSA appuyées | I76: Supervision PCI | K76: Mensuelle | L76: ZS | T76: nouveau | U76: 2 | V76: Les réunions de coordination signalent le manque d'eau aux PoC et dans les écoles.
A77: PCI-14 | B77: PCI | C77: Sites évalués et priorisés en PCI/WASH | D77: # of IPC/WASH sites assessed | E77: Nombre | F77: Tier 2 | G77: Sites évalués | H77: N/A | I77: Évaluations PCI/WASH | K77: Mensuelle | L77: Type de site | N77: 600 | P77: 600 | T77: nouveau | U77: 2 | V77: Propre à la Tranche 5.
A78: PCI-15 | B78: PCI | C78: Décontaminations (ménages, FOSA, sites) appuyées ou coordonnées | D78: # of decontamination events supported | E78: Nombre | F78: Tier 2 | G78: Événements de décontamination | H78: N/A | I78: Rapports de décontamination | K78: Hebdomadaire | L78: Type | N78: 800 | P78: 800 | T78: nouveau | U78: 2 | V78: Propre à la Tranche 5.
A79: PCI-16 | B79: PCI | C79: Visites de supervision ou contrôles ponctuels PCI | D79: # of IPC supervision/spot-check visits | E79: Nombre | F79: Tier 2 | G79: Visites réalisées | H79: N/A | I79: Rapports de supervision | K79: Mensuelle | L79: ZS | N79: 1 000 | P79: 1000 | T79: nouveau | U79: 2 | V79: Propre à la Tranche 5.
A80: PCI-17 | B80: PCI | C80: Agents et acteurs communautaires formés ou recyclés en PCI | D80: # of frontline workers and community actors trained in IPC | E80: Nombre | F80: Tier 2 | G80: Participants formés | H80: N/A | I80: Rapports de formation | K80: Mensuelle | L80: Sexe, type | N80: 8 000 | P80: 8000 | T80: nouveau | U80: 2 | V80: Propre à la Tranche 5.
A81: LOG-01 | B81: LOG | C81: Équipes de suivi des contacts appuyées | D81: # of contact tracing teams supported | E81: Nombre | F81: Tier 2 | G81: Équipes appuyées | H81: N/A | I81: Registres logistiques | K81: Mensuelle | L81: ZS | M81: 150 | O81: 150 | R81: 5.1 | T81: existant | U81: 2
A82: LOG-02 | B82: LOG | C82: EIR ou équipes d'investigation appuyées | D82: # of RRTs/investigation teams supported | E82: Nombre | F82: Tier 2 | G82: Équipes appuyées | H82: N/A | I82: Journal des EIR | K82: Hebdomadaire | L82: ZS | M82: 50 | O82: 50 | R82: 5.2 | S82: 23 | T82: existant | U82: 2
A83: LOG-03 | B83: LOG | C83: Smartphones et terminaux de rapportage acquis ou appuyés | D83: # of smartphones/reporting devices procured or supported | E83: Nombre | F83: Tier 2 | G83: Terminaux | H83: N/A | I83: Registres d'achat | K83: Mensuelle | M83: 500 | O83: 500 | R83: 5.3 | T83: existant | U83: 3
A84: LOG-04 | B84: LOG | C84: Véhicules, motos et bateaux appuyés | D84: # of vehicles, motorcycles, and/or boats supported | E84: Nombre | F84: Tier 2 | G84: Moyens de transport appuyés | H84: N/A | I84: Registres de transport | K84: Mensuelle | L84: Type (véhicule, moto, bateau) | M84: 125 | O84: 125 | R84: 5.4 | T84: à corriger | U84: 3 | V84: 125 additionne 20 véhicules, 80 motos et 25 déploiements de bateau : désagréger.
A85: LOG-05 | B85: LOG | C85: Téléphones, SIM ou forfaits appuyés | D85: # of phones/SIMs or airtime/data packages supported | E85: Nombre | F85: Tier 2 | G85: Forfaits appuyés | H85: N/A | I85: Registres de distribution | K85: Mensuelle | M85: 700 | O85: 700 | R85: 5.5 | T85: existant | U85: 3
A86: LOG-06 | B86: LOG | C86: Agents de terrain ayant reçu des EPI | D86: # of field staff/contact tracers/community teams receiving PPE | E86: Nombre | F86: Tier 2 | G86: Agents équipés | H86: N/A | I86: Registres de distribution | K86: Mensuelle | L86: IP | M86: 1 500 | O86: 1500 | R86: 5.6 | T86: existant | U86: 2
A87: LOG-07 | B87: LOG | C87: Déploiements dans les zones difficiles d'accès ou frontalières | D87: # of deployments to hard-to-reach/informal border areas supported | E87: Nombre | F87: Tier 2 | G87: Déploiements | H87: N/A | I87: Journal des déploiements | K87: Mensuelle | L87: ZS | M87: 100 | N87: 100 déploiements de renfort | O87: 100 | R87: 5.7 | T87: existant | U87: 3
A88: LOG-08 | B88: LOG | C88: Agents de renfort et superviseurs recrutés | D88: # of surge staff and supervisors recruited or supported | E88: Nombre | F88: Tier 2 | G88: Agents recrutés | H88: N/A | I88: Registres RH | K88: Mensuelle | L88: Fonction | M88: 75 | O88: 75 | R88: 5.8 | T88: existant | U88: 3
A89: LOG-09 | B89: LOG | C89: Traceurs communautaires sur la liste de réserve | D89: # of flexible community contact tracers maintained on roster | E89: Nombre | F89: Tier 2 | G89: Traceurs sur la liste | H89: N/A | I89: Liste de réserve | K89: Mensuelle | L89: ZS | M89: 1 000 | N89: 200 listes d'activation | O89: 1000 | R89: 5.9 | T89: existant | U89: 3
A90: LOG-10 | B90: LOG | C90: Visites de supervision de terrain (contacts manqués, refus) | D90: # of supervisory field visits conducted | E90: Nombre | F90: Tier 2 | G90: Visites réalisées | H90: N/A | I90: Rapports de supervision | K90: Mensuelle | L90: ZS | M90: 48 | O90: 48 | R90: 5.10 | T90: à corriger | U90: 2 | V90: Même cible (48) que MEL-01 : distinguer supervision opérationnelle et qualité des données.
A91: LOG-11 | B91: LOG | C91: Revues des gaps logistiques | D91: # of logistics gap reviews conducted | E91: Nombre | F91: Tier 2 | G91: Revues tenues | H91: N/A | I91: Rapports logistiques | K91: Mensuelle | M91: 35 | O91: 35 | R91: 5.11 | T91: existant | U91: 3
A92: LOG-12 | B92: LOG | C92: Sites de prépositionnement établis | D92: # of pre-positioned supply locations established | E92: Nombre | F92: Tier 2 | G92: Sites établis | H92: N/A | I92: Rapports de stock | K92: Mensuelle | M92: 15 | O92: 15 | R92: 5.12 | T92: existant | U92: 3
A93: LOG-13 | B93: LOG | C93: Briefings sécurité et autorisations de mouvement | D93: # of security briefings and movement clearances conducted | E93: Nombre | F93: Tier 2 | G93: Briefings et autorisations | H93: N/A | I93: Rapports sécurité | K93: Mensuelle | M93: 100 | O93: 100 | R93: 5.13 | T93: existant | U93: 3
A94: LOG-14 | B94: LOG | C94: Déploiements couverts par une procédure de sécurité (doublon) | D94: % of field deployments covered by security clearance procedures | E94: Pourcentage | F94: Tier 2 | G94: Déploiements couverts | H94: Déploiements | I94: Journal sécurité | K94: Mensuelle | M94: 100 % | O94: 100 | R94: 5.14 | T94: à corriger | U94: 3 | V94: Doublon de MEL-14 : à supprimer.
A95: LOG-15 | B95: LOG | C95: Jours-équipe perdus pour insécurité ou accès | D95: % of team-days lost to insecurity or access constraints | E95: Pourcentage | F95: Contexte | G95: Jours-équipe perdus | H95: Jours-équipe planifiés | I95: Journal des déploiements | K95: Hebdomadaire | L95: ZS | T95: nouveau | U95: 2 | V95: Les SitReps et réunions signalent attaques et arrêts d'activités (Mambasa, Biakato).
A96: LOG-16 | B96: LOG | C96: Incidents de sécurité affectant les équipes CGPP | D96: # of security incidents affecting CGPP teams | E96: Nombre | F96: Contexte | G96: Incidents | H96: N/A | I96: Rapports d'incident | K96: Hebdomadaire | L96: ZS, type | Q96: Tout incident : alerte | T96: nouveau | U96: 1
A97: LOG-17 | B97: LOG | C97: Jours de rupture de stock d'EPI ou d'intrants | D97: Stock-out days for PPE/IPC supplies | E97: Nombre | F97: Contexte | G97: Jours de rupture par site | H97: N/A | I97: Fiches de stock | K97: Mensuelle | L97: Site, article | T97: nouveau | U97: 3
A98: MEL-01 | B98: MEL | C98: Visites de supervision et de qualité des données | D98: # of supervision/data quality visits conducted | E98: Nombre | F98: Tier 2 | G98: Visites DQA réalisées | H98: N/A | I98: Rapports de supervision ; grilles DQA | K98: Mensuelle | L98: Province | M98: 48 | O98: 48 | R98: 6.1 | S98: 24 | T98: existant | U98: 1
A99: MEL-02 | B99: MEL | C99: Alertes de suspicion rapportées dans la SIMR (IDSR) | D99: % of suspected EVD alerts reported through IDSR | E99: Pourcentage | F99: Tier 1 | G99: Alertes CGPP retrouvées dans la SIMR | H99: Alertes CGPP détectées | I99: SIMR/DHIS2 ; Fiche SBC journalière (ODK) | K99: Mensuelle | L99: ZS | M99: 100 % | O99: 100 | R99: 6.2 | S99: 25 | T99: à corriger | U99: 2 | V99: Dans le cadre global, cette ligne porte la définition des visites de supervision : définition à rétablir.
A100: MEL-03 | B100: MEL | C100: Exercices de simulation, exercices de préparation et revues après action | D100: # of simulation exercises/readiness drills/AARs conducted | E100: Nombre | F100: Tier 2 | G100: Exercices et revues réalisés | H100: N/A | I100: Rapports SimEx et AAR | K100: Mensuelle ou trimestrielle | L100: Type | M100: 3 | N100: 96 simulations + 48 exercices + 40 revues | O100: 3 | R100: 6.3 | S100: 22 | T100: existant | U100: 3
...

Sheet ref_semaines
A1: annee | B1: semaine_iso | C1: date_debut | D1: date_fin | E1: libelle

Sheet sitrep_meta
A1: sitrep_no | B1: date_rapport | C1: date_publication | D1: fichier_source | E1: cas_cumul | F1: deces_cumul | G1: gueris_cumul | H1: taux_suivi_contacts | I1: letalite | J1: patients_isolement | K1: aires_sante_touchees | L1: aires_sante_total | M1: nouveaux_cas_24h | N1: deces_communautaires_24h | O1: deces_cte_24h | P1: gueris_24h | Q1: echantillons_24h | R1: faits_saillants | S1: date_extraction

Sheet epi_province
A1: sitrep_no | B1: date_rapport | C1: province | D1: nouveaux_cas_24h | E1: cas_cumul | F1: deces_cumul | G1: letalite_publiee | H1: zs_touchees | I1: zs_total

Sheet epi_zs
A1: sitrep_no | B1: date_rapport | C1: province | D1: zone_sante | E1: cas_cumul | F1: deces_cumul | G1: letalite_publiee | H1: nouveaux_cas_24h | I1: deces_communautaires_24h | J1: deces_cte_24h | K1: deces_total_24h | L1: est_a_ventiler

Sheet alertes_province
A1: sitrep_no | B1: date_rapport | C1: province | D1: statut_donnees | E1: recues_vivants | F1: recues_deces | G1: recues_total | H1: validees_vivants | I1: validees_deces | J1: invalidees_vivants | K1: invalidees_deces | L1: suspects_investigues | M1: suspects_transferes

Sheet contacts_province
A1: sitrep_no | B1: date_rapport | C1: province | D1: statut_donnees | E1: contacts_suivis | F1: contacts_vus | G1: taux_publie

Sheet labo_province
A1: sitrep_no | B1: date_rapport | C1: province | D1: echantillons | E1: positifs | F1: positifs_vivants | G1: positifs_deces | H1: positivite_publiee | I1: texte_source

Sheet pec_province
A1: sitrep_no | B1: date_rapport | C1: province | D1: admissions | E1: sorties | F1: guerisons | G1: patients_isolement | H1: texte_source

Sheet poe_province
A1: sitrep_no | B1: date_rapport | C1: indicateur | D1: province | E1: valeur_texte | F1: valeur | G1: numerateur | H1: denominateur

Sheet sitrep_texte
A1: sitrep_no | B1: ordre | C1: section | D1: sous_section | E1: texte

Sheet historique
A1: date_reference | B1: source | C1: territoire | D1: indicateur | E1: valeur | F1: commentaire

Sheet autres_epidemies
A1: annee | B1: semaine_epi | C1: province | D1: maladie | E1: zs_notifiantes | F1: zs_total | G1: cas | H1: deces | I1: zs_en_epidemie | J1: zs_cgpp_concernees | K1: cas_suspects_referes_cgpp | L1: detail_references | M1: source

Sheet dictionnaire
A1: feuille | B1: titre de la feuille | C1: colonne | D1: type | E1: description | F1: obligatoire | G1: valeurs autorisées
A2: ref_zones | B2: Référentiel des zones de santé | C2: province | D2: texte | E2: Province (nom canonique) | F2: oui | G2: liste « provinces»
A3: ref_zones | B3: Référentiel des zones de santé | C3: zone_sante | D3: texte | E3: Zone de santé (nom canonique du SitRep national) | F3: oui
A4: ref_zones | B4: Référentiel des zones de santé | C4: code_zs | D4: texte | E4: Code ou UID DHIS2 de la ZS (à compléter) | F4: non
A5: ref_zones | B5: Référentiel des zones de santé | C5: ip_cgpp | D5: texte | E5: Partenaire CGPP intervenant dans la ZS | F5: non | G5: liste « ip»
A6: ref_zones | B6: Référentiel des zones de santé | C6: statut_cgpp | D6: texte | E6: Intervention / préparation / hors zone CGPP | F6: non | G6: liste « statut_cgpp»
A7: ref_zones | B7: Référentiel des zones de santé | C7: population | D7: entier | E7: Population de la ZS (dénominateur des taux) | F7: non
A8: ref_zones | B8: Référentiel des zones de santé | C8: source | D8: texte | E8: Origine de la ligne | F8: non
A9: ref_partenaires | B9: Référentiel des partenaires de mise en oeuvre | C9: code_ip | D9: texte | E9: Code court du partenaire | F9: oui
A10: ref_partenaires | B10: Référentiel des partenaires de mise en oeuvre | C10: nom | D10: texte | E10: Nom complet | F10: oui
A11: ref_partenaires | B11: Référentiel des partenaires de mise en oeuvre | C11: role | D11: texte | E11: Rôle dans le consortium | F11: non
A12: ref_partenaires | B12: Référentiel des partenaires de mise en oeuvre | C12: provinces | D12: texte | E12: Provinces couvertes | F12: non
A13: ref_partenaires | B13: Référentiel des partenaires de mise en oeuvre | C13: point_focal | D13: texte | E13: Point focal données | F13: non
A14: ref_partenaires | B14: Référentiel des partenaires de mise en oeuvre | C14: email_point_focal | D14: texte | E14: Courriel du point focal | F14: non
A15: ref_indicateurs | B15: Matrice maîtresse des indicateurs | C15: id_indicateur | D15: texte | E15: Identifiant stable (texte, ex. SURV.05) | F15: oui
A16: ref_indicateurs | B16: Matrice maîtresse des indicateurs | C16: pilier | D16: texte | E16: Pilier du plan de travail DOS | F16: oui | G16: liste « piliers»
A17: ref_indicateurs | B17: Matrice maîtresse des indicateurs | C17: libelle_fr | D17: texte | E17: Intitulé en français | F17: oui
A18: ref_indicateurs | B18: Matrice maîtresse des indicateurs | C18: libelle_en | D18: texte | E18: Intitulé en anglais (rapport DOS) | F18: non
A19: ref_indicateurs | B19: Matrice maîtresse des indicateurs | C19: type | D19: texte | E19: Nombre / Pourcentage / Délai | F19: oui | G19: liste « type_indicateur»
A20: ref_indicateurs | B20: Matrice maîtresse des indicateurs | C20: niveau | D20: texte | E20: Tier 1 (performance) / Tier 2 (extrant) / Contexte | F20: non
A21: ref_indicateurs | B21: Matrice maîtresse des indicateurs | C21: numerateur | D21: texte | E21: Définition du numérateur | F21: oui
A22: ref_indicateurs | B22: Matrice maîtresse des indicateurs | C22: denominateur | D22: texte | E22: Définition du dénominateur (N/A pour un nombre) | F22: non
A23: ref_indicateurs | B23: Matrice maîtresse des indicateurs | C23: source_donnees | D23: texte | E23: Source primaire | F23: oui
A24: ref_indicateurs | B24: Matrice maîtresse des indicateurs | C24: champ_source | D24: texte | E24: Champ(s) de la fiche SBC / ODK / SitRep | F24: non
A25: ref_indicateurs | B25: Matrice maîtresse des indicateurs | C25: frequence | D25: texte | E25: Fréquence de rapportage | F25: oui
A26: ref_indicateurs | B26: Matrice maîtresse des indicateurs | C26: desagregation | D26: texte | E26: Désagrégations requises | F26: non
A27: ref_indicateurs | B27: Matrice maîtresse des indicateurs | C27: cible_dos | D27: texte | E27: Cible du plan de travail DOS | F27: non
A28: ref_indicateurs | B28: Matrice maîtresse des indicateurs | C28: cible_tranche5 | D28: texte | E28: Cible de la Tranche 5 | F28: non
A29: ref_indicateurs | B29: Matrice maîtresse des indicateurs | C29: cible_dos_num | D29: decimal | E29: Cible DOS en nombre (pour les calculs ; % en points) | F29: non
A30: ref_indicateurs | B30: Matrice maîtresse des indicateurs | C30: cible_t5_num | D30: decimal | E30: Cible Tranche 5 en nombre | F30: non
A31: ref_indicateurs | B31: Matrice maîtresse des indicateurs | C31: seuil_alerte | D31: texte | E31: Seuil de performance (code couleur) | F31: non
... A33: ref_indicateurs | B33: Matrice maîtresse des indicateurs | C33: id_cadre_global | D33: texte | E33: Rang dans le cadre global (1 à 25) | F33: non
A34: ref_indicateurs | B34: Matrice maîtresse des indicateurs | C34: statut | D34: texte | E34: existant / à corriger / nouveau | F34: oui | G34: liste « statut_indicateur»
A35: ref_indicateurs | B35: Matrice maîtresse des indicateurs | C35: priorite | D35: texte | E35: Priorité de mise en oeuvre (1 à 3) | F35: non
A36: ref_indicateurs | B36: Matrice maîtresse des indicateurs | C36: commentaire | D36: texte | E36: Remarques, écarts relevés | F36: non
A37: ref_semaines | B37: Calendrier des semaines épidémiologiques (ISO) | C37: annee | D37: entier | E37: Année ISO | F37: oui
A38: ref_semaines | B38: Calendrier des semaines épidémiologiques (ISO) | C38: semaine_iso | D38: entier | E38: Numéro de semaine ISO | F38: oui
A39: ref_semaines | B39: Calendrier des semaines épidémiologiques (ISO) | C39: date_debut | D39: date | E39: Lundi | F39: oui
A40: ref_semaines | B40: Calendrier des semaines épidémiologiques (ISO) | C40: date_fin | D40: date | E40: Dimanche | F40: oui
A41: ref_semaines | B41: Calendrier des semaines épidémiologiques (ISO) | C41: libelle | D41: texte | E41: Libellé affiché | F41: oui
A42: sitrep_meta | B42: SitReps nationaux : en-tête et chiffres clés | C42: sitrep_no | D42: entier | E42: Numéro du SitRep national | F42: oui
A43: sitrep_meta | B43: SitReps nationaux : en-tête et chiffres clés | C43: date_rapport | D43: date | E43: Date des données | F43: oui
A44: sitrep_meta | B44: SitReps nationaux : en-tête et chiffres clés | C44: date_publication | D44: date | E44: Date de publication | F44: non
A45: sitrep_meta | B45: SitReps nationaux : en-tête et chiffres clés | C45: fichier_source | D45: texte | E45: Fichier d'origine | F45: oui
A46: sitrep_meta | B46: SitReps nationaux : en-tête et chiffres clés | C46: cas_cumul | D46: entier | E46: Cumul des cas confirmés (encadré) | F46: oui
... A62: epi_province | B62: Situation par province (Tableau 1 du SitRep) | C62: date_rapport | D62: date | E62: Date des données | F62: oui
A63: epi_province | B63: Situation par province (Tableau 1 du SitRep) | C63: province | D63: texte | E63: Province | F63: oui | G63: liste « provinces»
A64: epi_province | B64: Situation par province (Tableau 1 du SitRep) | C64: nouveaux_cas_24h | D64: entier | E64: Nouveaux cas confirmés (24 h) | F64: oui
A65: epi_province | B65: Situation par province (Tableau 1 du SitRep) | C65: cas_cumul | D65: entier | E65: Cas confirmés cumulés | F65: oui
A66: epi_province | B66: Situation par province (Tableau 1 du SitRep) | C66: deces_cumul | D66: entier | E66: Décès confirmés cumulés | F66: oui
A67: epi_province | B67: Situation par province (Tableau 1 du SitRep) | C67: letalite_publiee | D67: decimal | E67: Létalité publiée (%) | F67: non
A68: epi_province | B68: Situation par province (Tableau 1 du SitRep) | C68: zs_touchees | D68: entier | E68: ZS touchées | F68: non
A69: epi_province | B69: Situation par province (Tableau 1 du SitRep) | C69: zs_total | D69: entier | E69: ZS de la province | F69: non
A70: epi_zs | B70: Situation par zone de santé (Tableau 2 du SitRep) | C70: sitrep_no | D70: entier | E70: Numéro du SitRep | F70: oui
A71: epi_zs | B71: Situation par zone de santé (Tableau 2 du SitRep) | C71: date_rapport | D71: date | E71: Date des données | F71: oui
A72: epi_zs | B72: Situation par zone de santé (Tableau 2 du SitRep) | C72: province | D72: texte | E72: Province | F72: oui | G72: liste « provinces»
A73: epi_zs | B73: Situation par zone de santé (Tableau 2 du SitRep) | C73: zone_sante | D73: texte | E73: Zone de santé | F73: oui
A74: epi_zs | B74: Situation par zone de santé (Tableau 2 du SitRep) | C74: cas_cumul | D74: entier | E74: Cas confirmés cumulés | F74: non
A75: epi_zs | B75: Situation par zone de santé (Tableau 2 du SitRep) | C75: deces_cumul | D75: entier | E75: Décès confirmés cumulés | F75: oui
A76: epi_zs | B76: Situation par zone de santé (Tableau 2 du SitRep) | C76: letalite_publiee | D76: decimal | E76: Létalité publiée (%) | F76: non
A77: epi_zs | B77: Situation par zone de santé (Tableau 2 du SitRep) | C77: nouveaux_cas_24h | D77: entier | E77: Nouveaux cas (24 h) | F77: non
A78: epi_zs | B78: Situation par zone de santé (Tableau 2 du SitRep) | C78: deces_communautaires_24h | D78: entier | E78: Décès communautaires swab+ (24 h) | F78: non
A79: epi_zs | B79: Situation par zone de santé (Tableau 2 du SitRep) | C79: deces_cte_24h | D79: entier | E79: Décès confirmés intra-CTE (24 h) | F79: non
A80: epi_zs | B80: Situation par zone de santé (Tableau 2 du SitRep) | C80: deces_total_24h | D80: entier | E80: Total des décès confirmés (24 h) | F80: non
A81: epi_zs | B81: Situation par zone de santé (Tableau 2 du SitRep) | C81: est_a_ventiler | D81: booleen | E81: Ligne « à ventiler » (décès non attribués à une ZS) | F81: non
A82: alertes_province | B82: Alertes par province (Tableau 3 du SitRep) | C82: sitrep_no | D82: entier | E82: Numéro du SitRep | F82: oui
A83: alertes_province | B83: Alertes par province (Tableau 3 du SitRep) | C83: date_rapport | D83: date | E83: Date des données | F83: oui
A84: alertes_province | B84: Alertes par province (Tableau 3 du SitRep) | C84: province | D84: texte | E84: Province | F84: oui | G84: liste « provinces»
A85: alertes_province | B85: Alertes par province (Tableau 3 du SitRep) | C85: statut_donnees | D85: texte | E85: OK ou ND (non disponible) | F85: oui | G85: liste « statut_donnees»
A86: alertes_province | B86: Alertes par province (Tableau 3 du SitRep) | C86: recues_vivants | D86: entier | E86: Alertes reçues : vivants | F86: non
A87: alertes_province | B87: Alertes par province (Tableau 3 du SitRep) | C87: recues_deces | D87: entier | E87: Alertes reçues : décès | F87: non
A88: alertes_province | B88: Alertes par province (Tableau 3 du SitRep) | C88: recues_total | D88: entier | E88: Total des alertes | F88: non
A89: alertes_province | B89: Alertes par province (Tableau 3 du SitRep) | C89: validees_vivants | D89: entier | E89: Validées (cas suspects) : vivants | F89: non
A90: alertes_province | B90: Alertes par province (Tableau 3 du SitRep) | C90: validees_deces | D90: entier | E90: Validées : décès | F90: non
A91: alertes_province | B91: Alertes par province (Tableau 3 du SitRep) | C91: invalidees_vivants | D91: entier | E91: Invalidées : vivants | F91: non
A92: alertes_province | B92: Alertes par province (Tableau 3 du SitRep) | C92: invalidees_deces | D92: entier | E92: Invalidées : décès | F92: non
A93: alertes_province | B93: Alertes par province (Tableau 3 du SitRep) | C93: suspects_investigues | D93: entier | E93: Suspects investigués | F93: non
A94: alertes_province | B94: Alertes par province (Tableau 3 du SitRep) | C94: suspects_transferes | D94: entier | E94: Suspects transférés au CT/CTE | F94: non
A95: contacts_province | B95: Suivi des contacts par province | C95: sitrep_no | D95: entier | E95: Numéro du SitRep | F95: oui
A96: contacts_province | B96: Suivi des contacts par province | C96: date_rapport | D96: date | E96: Date des données | F96: oui
A97: contacts_province | B97: Suivi des contacts par province | C97: province | D97: texte | E97: Province | F97: oui | G97: liste « provinces»
A98: contacts_province | B98: Suivi des contacts par province | C98: statut_donnees | D98: texte | E98: OK ou ND | F98: oui | G98: liste « statut_donnees»
A99: contacts_province | B99: Suivi des contacts par province | C99: contacts_suivis | D99: entier | E99: Contacts en cours de suivi | F99: non
A100: contacts_province | B100: Suivi des contacts par province | C100: contacts_vus | D100: entier | E100: Contacts vus dans les 24 h | F100: non
A101: contacts_province | B101: Suivi des contacts par province | C101: taux_publie | D101: decimal | E101: Taux publié (%) | F101: non
A102: labo_province | B102: Laboratoire par province | C102: sitrep_no | D102: entier | E102: Numéro du SitRep | F102: oui
A103: labo_province | B103: Laboratoire par province | C103: date_rapport | D103: date | E103: Date des données | F103: oui
A104: labo_province | B104: Laboratoire par province | C104: province | D104: texte | E104: Province | F104: oui | G104: liste « provinces»
A105: labo_province | B105: Laboratoire par province | C105: echantillons | D105: entier | E105: Échantillons reçus et analysés | F105: non
A106: labo_province | B106: Laboratoire par province | C106: positifs | D106: entier | E106: Résultats positifs | F106: non
A107: labo_province | B107: Laboratoire par province | C107: positifs_vivants | D107: entier | E107: Positifs vivants | F107: non
A108: labo_province | B108: Laboratoire par province | C108: positifs_deces | D108: entier | E108: Positifs décédés | F108: non
A109: labo_province | B109: Laboratoire par province | C109: positivite_publiee | D109: decimal | E109: Positivité publiée (%) | F109: non
A110: labo_province | B110: Laboratoire par province | C110: texte_source | D110: texte | E110: Phrase source | F110: non
A111: pec_province | B111: Prise en charge par province | C111: sitrep_no | D111: entier | E111: Numéro du SitRep | F111: oui
A112: pec_province | B112: Prise en charge par province | C112: date_rapport | D112: date | E112: Date des données | F112: oui
A113: pec_province | B113: Prise en charge par province | C113: province | D113: texte | E113: Province | F113: oui | G113: liste « provinces»
A114: pec_province | B114: Prise en charge par province | C114: admissions | D114: entier | E114: Nouvelles admissions | F114: non
A115: pec_province | B115: Prise en charge par province | C115: sorties | D115: entier | E115: Sorties | F115: non
A116: pec_province | B116: Prise en charge par province | C116: guerisons | D116: entier | E116: Guérisons | F116: non
...

Sheet listes
A1: provinces | B1: ip | C1: statut_cgpp | D1: piliers | E1: type_indicateur | F1: statut_indicateur | G1: statut_donnees | H1: types_site | I1: oui_non | J1: niveau_reunion | K1: statut_action | L1: gravite | M1: statut_anomalie | N1: section_note | O1: maladies
A2: Ituri | B2: WV | C2: intervention | D2: COORD | E2: Nombre | F2: existant | G2: OK | H2: CPN | I2: O | J2: National | K2: À faire | L2: Critique | M2: Ouverte | N2: Faits marquants | O2: Choléra
A3: Nord-Kivu | B3: ADRA | C3: préparation | D3: SURV | E3: Pourcentage | F3: à corriger | G3: ND | H3: CPS | I3: N | J3: Provincial | K3: En cours | L3: Majeure | M3: Corrigée | N3: Activités | O3: Mpox
A4: Haut-Uélé | B4: IMC | C4: hors zone CGPP | D4: CREC | E4: Délai | F4: nouveau | H4: Porte à porte (VAD) | J4: Zone de santé | K4: Réalisé | L4: Mineure | M4: Acceptée | N4: Sécurité | O4: Rougeole
A5: Bas-Uélé | B5: IRC | D5: PCI | E5: Ratio | H5: Lieu religieux (église) | J5: Pilier | K5: Abandonné | N5: Défis | O5: Autre
A6: Tshopo | B6: CGPP | D6: LOG | H6: Chambre de prière | J6: Partenaires | N6: Actions
A7: Sud-Kivu | D7: MEL | H7: École | J7: Interne CGPP | N7: Commentaire
A8: Sud-Ubangi | H8: Marché
H9: Rond-point
H10: Radio
H11: Site de guérison traditionnelle
H12: Ferme laitière / centre d'engraissement
H13: Point d'eau
H14: Site de distribution alimentaire ou cash
H15: Camp de réfugiés
H16: Site de déplacés
H17: Point d'entrée
H18: Boucherie
H19: Restaurant
H20: Carré / site minier
... H23: Autre
